Workbook
Name INFERIOR: 'COSTO UNITARIO'!$G$17:$G$23
Name SUPERIOR: 'COSTO UNITARIO'!$I$17:$I$20
Name INCAPACIDADES: incap!$B$3:$E$1048576

Sheet SIMULACION 
E1: 30min | F1: 29min
B2: SIMULACIÓN VELOCIDAD
B3: # | C3: # RESES | D3: VELOCIDAD BRUTA (Reses/Hora) | E3: PARADA PROGRAMADA (Hr) | F3: VACIADO LÍNEA (Hr) | G3: DURACIÓN PROCESO DESEADA (Hr) | H3: DURACIÓN EFECTIVA DE PROCESO (Hr) | I3: DURACION EFECTIVA PARA NOQUEAR EL TOTAL | J3: VELOCIDAD NETA (Reses/Hora) | K3: VELOCIDAD NETA NOQUEO/HORA | L3: # RESES/MIN | M3: MIN/RES | P3: NOQUEAR CADA SEG/RES | S3: Información Editable
B4: 1 | C4: 306 | D4: 75 | E4: 0 | F4: 0.49 | G4: =+(C4/D4) -> 4.08 | H4: =+G4-E4 -> 4.08 | I4: =H4-F4 -> 3.59 | J4: =+C4/H4 -> 75 | K4: =+C4/I4 -> 85.236769 | L4: =+K4/60 -> 1.4206128 | M4: =(60/K4)/60/24 -> 0.00048883442 | N4: =+MINUTE(M4) -> 0 | O4: =+SECOND(M4) -> 42 | P4: =+(N4*60)+O4 -> 42
J6: Aca siempre debe dar 75 | K6: A esto se debe avanzar por hora | V6: 60 | W6: 76
C7: HORA DE INICIO | D7: 0.84583333 | V7: 30 | W7: x
C8: ULTIMA PESADA | D8: =+D7+D9 -> 1.0158333 | G8: =C4 -> 306
C9: TIEMPO LABORADO | D9: =+G4/24 -> 0.17 | F9: =G8*4 -> 1224 | G9: =G8*2 -> 612 | P9: 0.33 | R9: 15min | V9: =V7*W6/V6 -> 38
F11: TOLERANCIA | G11: PIELES/ C.G | H11: C.P/SR | P11: 1 | R11: 60 min
C12: 344 | F12: =(F13/F9)*100 -> 0.7 | G12: =(G13/G9)*100 -> 1.5 | H12: =H13/G9*100 -> 1
F13: =F9*0.007 -> 8.568 | G13: =G9*0.015 -> 9.18 | H13: =G9*0.01 -> 6.12 | U13: =13+10+39+5 -> 67
H15: 0.5 | I15: 30 | P15: 0.75 | R15: 45 min
H16: 0.33 | I16: x | J16: =H16*I15/H15 -> 19.8 | P16: 0.67 | R16: 40min
P17: 0.5 | R17: 30 min
I19: si en 60 min | J19: pasan x
C20: TOPE MINIMO | I20: 60 | J20: 76
C21: 344 | I21: 28.5 | J21: x
J22: =I21*J20/I20 -> 36.1
M26: 0.64930556
M27: 0.68402778 | P27: =M27-M26 -> 0.034722222

Sheet RESUMEN DEL DIA 
Y1: En las paradas y al final dejar menos canales
C3: RESUMEN PARCIAL DE SACRIFICIO | K3: =+HOUR(I5) -> 15 | L3: =+MINUTE(I5) -> 5 | O3: HORA | P3: META | R3: OBSERVACIÓN- LIMITANTE | S3: DIFE | Y3: =TODAY() -> 46262 | AA3: SEGUMIENTO A CLIENTES DEL DIA
C4: =NOW() -> 46262.475 | M4: 19 | O4: 0.58333333 | P4: 79 | Q4: 73 | R4: 36 | S4: =P4-Q4 -> 6 | Y4: CLIENTE | Z4: # | AA4: OBSERVACION
C5: # | D5: ITEM | E5: CIFRA/TOTAL | I5: =+I6-E6 -> 46261.629 | L5: =+K3*60+L3 -> 905 | M5: 38 | O5: 0.625 | P5: 79 | Q5: 50 | S5: =P5-Q5 -> 29 | Y5: COLBEEF S.A.S | Z5: 7 | AA5: Van sucias
C6: 1 | D6: Hora de inicio | E6: ='CIERRE DE PROCESO '!D3 -> 0.84583333 | I6: =NOW() -> 46262.475 | J6: =I5*24/60 -> 18504.652 | L6: =+L5/60 -> 15.083333 | M6: 57 | O6: 0.66666667 | P6: 79 | Q6: 29 | S6: =P6-Q6 -> 50 | Y6: CRUZ LEONIDAS | Z6: 21 | AA6: Garantizar lustres y presentacion de canales
C7: 2 | D7: Total de sacrificio | E7: ='CIERRE DE PROCESO '!D2 -> 306 | G7: =I6*24*60 -> 66617963 | I7: hora actual | M7: 76 | O7: 0.70833333 | P7: 79 | Q7: 80 | S7: =P7-Q7 -> -1 | Y7: GOMEZ QUINTERO JUDITH TORCOROMA | Z7: 14 | AA7: Garantizar lustres y presentacion de canales
C8: 3 | D8: Reses sacrificadas | E8: 126 | G8: =G7-785 -> 66617178 | O8: 0.75 | P8: 40 | Q8: 80 | R8: Parada programada 30 min | S8: =P8-Q8 -> -40 | Y8: INVERSIONES ZULUAGA RUEDA S.A.S. | Z8: 14 | AA8: Limpieza y desgrase profundo y retiro de medula al 100%
C9: 4 | D9: Reses faltantes | E9: =E7-E8 -> 180 | O9: 0.79166667 | P9: 79 | Q9: 40 | S9: =P9-Q9 -> 39 | Y9: JAIMES JAIMES LUIS JOSE (FORTUNATO) | Z9: 46 | AA9: Garantizar lustres y presentacion de canales
C10: 5 | D10: Velocidad de línea (Reses/hora) | E10: ='CIERRE DE PROCESO '!D9 -> 255 | G10: =J6/60 -> 308.41086 | O10: 0.83333333 | P10: 79 | Q10: 80 | R10: Parada programada 30 min | S10: =P10-Q10 -> -1 | Y10: PRODUCTOS OFACOL S.A.S. | Z10: 8 | AA10: Van sucias
C11: 6 | D11: Hora estimada de finalización | E11: =O23 -> 0.89791667 | G11: =+E9/60 -> 3 | J11: =+E7-E8 -> 180 | O11: 0.875 | P11: 79 | Q11: 75 | R11: Falla en maquina de pandos 90 min | S11: =P11-Q11 -> 4 | T11: 35 | Y11: SUPERTIENDAS Y DROGUERIA OLIMPICA S.A. | Z11: 95 | AA11: Van sucias
O12: 0.91666667 | P12: 21 | R12: Falla en maquina de pandos 90 min | S12: =P12-Q12 -> 21
O13: 0.95833333 | S13: 36
O14: 1 | S14: 36
O15: 1.0416667 | S15: 36 | AI15: @Gestor LyD @Coordinación Calidad
O16: 1.0833333 | S16: 36
O17: 1.125 | S17: 36
G18: =+G11*60 -> 180 | J18: =+J11/E10 -> 0.70588235 | O18: 1.1666667 | S18: 36
G20: =+G18+G7 -> 66618143 | J20: =+J18+L6 -> 15.789216 | O20: TOTAL | P20: =SUM(P4:P19) -> 614 | Q20: =SUM(Q4:Q19) -> 507
O21: PROYECCION
G22: =G20/60 -> 1110302.4 | J22: =+J20/24 -> 0.65788399 | O22: ULTIMO INSENSIBILIZADO | Q22: ULTIMA CANAL PESADA | AE22: 2311-07182 | AF22: =AF20-3 -> -3 | AG22: =AG20-3 -> -3 | AH22: Este es el peso final descontando las poleas
O23: =Q23-0.01875 -> 0.89791667 | Q23: ='CIERRE DE PROCESO '!D16 -> 0.91666667 | AE23: MERMA | AF23: 2kg | AG23: 2 kg | AH23: Conclusion cada media merma 2kg
O26: TOTAL | P26: =Q20 -> 507
O27: ULTIMO INSENSIBILIZADO
O28: =O23 -> 0.89791667
Z31: RUIZ RODRIGUEZ LUIS HERNAN | AA31: 17
Y35: GRUPO MANZANARES S.A.S. | AA35: Limpias de riñonada y capadura y asegurar choque y PC
Y36: INVERSIONES ZULUAGA RUEDA S.A.S. | AA36: Limpieza y desgrase profundo y retiro de medula al 100%
Y37: CARNES SANTACRUZ S.A.S | AA37: No se les despejan riñones
D38: Ingreso de cuchillas neumaticas | Y38: PETROCASINOS S.A. | AA38: Van sucias
D39: 46062 | Y39: SUPERMERCADOS MAS POR MENOS S.A.S. | AA39: Van sucias y retiro completo de medula
D40: 46087 | Y40: PRODUCTOS OFACOL S.A.S. | AA40: Van sucias
D41: 46118 | Y41: SUPERTIENDAS OLIMPICA S.A.S | AA41: Van sucias
Y42: COLBEEF S.A.S | AA42: Van sucias
Y43: BUFASAN S.A.S. | AA43: Van sucias

Sheet CIERRE DE PROCESO 
I1: =TODAY() -> 46262
C2: Animales beneficiados | D2: ='SIMULACION '!C4 -> 306 | I2: INDICADORES | J2: META | K2: CIERRE DEL DIA | N2: ENTRENAMIENTO | O2: =I1 -> 46262
C3: Hora de inicio | D3: ='SIMULACION '!D7 -> 0.84583333 | I3: INVENTARIO EN CORRALES | K3: 30 | N3: COLABORADOR | O3: PUESTO DE TRABAJO
C4: Hora ultima pesada | D4: 0.91666667 | F4: H.L | I4: TOTAL DE BENEFICIO | K4: =D2 -> 306 | N4: CASTRO CARLOS SAUL | O4: DEGUELLO
C5: Duracion minutos | D5: =(D4-D3)*24*60 -> 102 | F5: =D5/60 -> 1.7 | I5: HORA DE INICIO | K5: =D3 -> 0.84583333 | N5: PINTON MARLON | O5: RAYADO Y CORTE DE MANOS
C6: paradas presentadas | D6: =F10 -> 0 | I6: HORA FIN | K6: =D4 -> 0.91666667 | N6: JUAN GABRIEL HERNÁNDEZ | O6: AUX. DESUELLO MECANICO
C7: Comida o descanso de personal | D7: 30 | I7: TIEMPO IMPRODUCTIVO (min) | K7: =F10 -> 0 | N7: AYALA CRISTIAN | O7: DESUELLO PRIMERA PIERNA
C8: Productividad | D8: =D2/((D5-D7)/60) -> 255 | E8: 75 | I8: PARADAS PROGRAMADAS (min) | K8: =D7 -> 30 | N8: GUERRERO MIGUEL ANGEL | O8: CORTE DE ESTERNON
C9: Neta | D9: =D2/((D5-(D6+D7))/60) -> 255 | E9: 75 | I9: VELOCIDAD LÍNEA DE BENEFICIO | K9: =K13 -> 255
C10: Bruta | D10: =D2/F5 -> 180 | E10: 75 | F10: =SUM(F6:F9) -> 0 | I10: HORAS LABORADAS | K10: =F5 -> 1.7
I11: TARDANZA DE INICIO | K11: 0
I12: PRODUCTIVIDAD | J12: 55 | K12: =D8 -> 255
I13: VELOCIDAD NETA | J13: 74.55 | K13: =D9 -> 255
C14: TIEMPO DE VACIADO DE LINEA | D14: 0.01875 | I14: VELOCIDAD BRUTA | J14: 55 | K14: =D10 -> 180
C15: ULTIMO INSENSIBILIZADO | D15: =(D4-D14) -> 0.89791667 | I15: TOLERANCIA CERO | J15: 0.01 | K15: 0.0032
C16: ULTIMA CANAL PESADA | D16: =D4 -> 0.91666667 | I16: PIELES | J16: 0.031 | K16: ='CIERRE DE PIELES '!D14/D2 -> 0.081699346
D17: =D16-0.01875 -> 0.89791667 | I17: CORTE EN PIERNA | J17: 0.01 | K17: =IFERROR(VLOOKUP($I$1,'LIBERACION DE CANALES'!B:K,9,FALSE),"DOM") -> DOM
I18: SOBREBARRIGAS ROTAS | J18: 0.01 | K18: =IFERROR(VLOOKUP($I$1,'LIBERACION DE CANALES'!B:K,10,FALSE),"DOM") -> DOM
I19: COBERTURA GRASA | J19: 0.015 | K19: =IFERROR(VLOOKUP($I$1,'LIBERACION DE CANALES'!B:K,7,FALSE),"DOM") -> DOM
I20: DIAS SIN ACCIDENTES | J20: 60 | K20: 0
AU64: DIA | AV64: VELOCIDAD BRUTA | AW64: NOVEDAD
AU65: 13 DE JULIO | AV65: 44 | AW65: Se realiza caractirizacion en la PTAR con velocidad permitida de 44
AU66: 15 DE JULIO | AV66: 53 | AW66: Se presenta ruptura de la tuberia de la bañadera de corrales, lo que nos genera 30 min de tiempos improductivos
AU67: 18 DE JULIO | AV67: 53 | AW67: Se presenta falla mecanica en la trasferencia numero 1, y no se logra solucionar lo que nos implico terminar a un ritmo menor con la trasferencia
AU68: 22 DE JULIO | AV68: 52 | AW68: Se presentan parada de 30 min por altas temperaturas en el cuarto de pre refrigeracion oreo
AU69: 25 DE JULIO | AV69: 53 | AW69: Se presenta parada de 30min de tiempo improductivo por motivo de que no se contaba con ganchos para colgar viscera roja
I88: CIERRE DE OCTUBRE 2025
I89: INDICADORES | J89: META | K89: CIERRE DEL MES
I90: O.E.E. | J90: 0.95 | K90: 0.923
I91: PRODUCTIVIDAD | J91: 55 | K91: 57
I92: VELOCIDAD NETA | J92: 75 | K92: 75
I93: VELOCIDAD BRUTA | J93: 55 | K93: 54
I94: TOLERANCIA CERO | J94: 0.01 | K94: 0.006
I95: PIELES | J95: 0.03 | K95: 0.0223
I96: CORTE EN PIERNA | J96: 0.01 | K96: 0.004
I97: SOBREBARRIGAS ROTAS | J97: 0.01 | K97: 0.005
I98: HEMATOMAS | J98: 0.005 | K98: 0.001
I99: COBERTURA GRASA | J99: 0.015 | K99: 0.004
I100: DIAS SIN ACCIDENTES | J100: 0 | K100: 68 DIAS SIN A.T.

Sheet CIERRE DE PROCESO
C1: =UPPER(TEXT(B3,"MMMM")) -> AGOSTO
B2: CIERRE DE PROCESO LÍNEA DE BENEFICIO | E2: FALLOS EN MAQUINARIA | G2: OBSERVACIONES DE PROCESO | L2: =IFERROR(__xludf.DUMMYFUNCTION("IMPORTRANGE(""https://docs.google.com/spreadsheets/d/1OjTekbeLGM33cmRz9M_4nXVIyMrUrINjwBqTFNIG2fQ/edit?gid=440714860#gid=440714860"",""RESUMEN!H3:M12"")"),"OPERATIVIDAD DE LINEA") -> OPERATIVIDAD DE LINEA | M2: =IFERROR(__xludf.DUMMYFUNCTION("""COMPUTED_VALUE"""),"REAL") -> REAL | N2: =IFERROR(__xludf.DUMMYFUNCTION("""COMPUTED_VALUE"""),"%") -> % | O2: =IFERROR(__xludf.DUMMYFUNCTION("""COMPUTED_VALUE"""),46261.0) -> 46261 | Q2: =IFERROR(__xludf.DUMMYFUNCTION("""COMPUTED_VALUE"""),"DIF") -> DIF | S2: EJECUCIÓN PTTO BENEFICIO - 2026
B3: 46261 | E3: 1- No se cuenta con contingencias habilitadas, desolladora, sierra canal y box de noqueo . | G3: =VLOOKUP($B$3,'BASE DE DATOS CIERRE'!A:V,22,0) -> 1. Se registra parada por tanque cañón ruminal tapado (20) | L3: =IFERROR(__xludf.DUMMYFUNCTION("""COMPUTED_VALUE"""),"LIDER/APOYO") -> LIDER/APOYO | M3: =IFERROR(__xludf.DUMMYFUNCTION("""COMPUTED_VALUE"""),1.0) -> 1 | N3: =IFERROR(__xludf.DUMMYFUNCTION("""COMPUTED_VALUE"""),0.016666666666666666) -> 0.016666667 | O3: =IFERROR(__xludf.DUMMYFUNCTION("""COMPUTED_VALUE"""),0.0) -> 0 | P3: =IFERROR(__xludf.DUMMYFUNCTION("""COMPUTED_VALUE"""),0.0) -> 0 | Q3: =IFERROR(__xludf.DUMMYFUNCTION("""COMPUTED_VALUE"""),-0.016666666666666666) -> -0.016666667 | S3: # | T3: MES | U3: PPTO MES | V3: RESES BENEFICIADAS | W3: % CUMPL.
B4: INDICADORES | L4: =IFERROR(__xludf.DUMMYFUNCTION("""COMPUTED_VALUE"""),"OPERACION") -> OPERACION | M4: =IFERROR(__xludf.DUMMYFUNCTION("""COMPUTED_VALUE"""),45.0) -> 45 | N4: =IFERROR(__xludf.DUMMYFUNCTION("""COMPUTED_VALUE"""),0.75) -> 0.75 | O4: =IFERROR(__xludf.DUMMYFUNCTION("""COMPUTED_VALUE"""),48.0) -> 48 | P4: =IFERROR(__xludf.DUMMYFUNCTION("""COMPUTED_VALUE"""),0.8) -> 0.8 | Q4: =IFERROR(__xludf.DUMMYFUNCTION("""COMPUTED_VALUE"""),0.050000000000000044) -> 0.05 | S4: 1 | T4: ENERO | U4: 12366 | V4: 11514 | W4: =IF(V4="","",V4/U4) -> 0.93110141
B5: TOTAL DE BENEFICIO | C5: =VLOOKUP($B$3,'BASE DE DATOS CIERRE'!A:AA,3,0) -> 440 | L5: =IFERROR(__xludf.DUMMYFUNCTION("""COMPUTED_VALUE"""),"VACACIONES") -> VACACIONES | M5: =IFERROR(__xludf.DUMMYFUNCTION("""COMPUTED_VALUE"""),3.0) -> 3 | N5: =IFERROR(__xludf.DUMMYFUNCTION("""COMPUTED_VALUE"""),0.05) -> 0.05 | O5: =IFERROR(__xludf.DUMMYFUNCTION("""COMPUTED_VALUE"""),1.0) -> 1 | P5: =IFERROR(__xludf.DUMMYFUNCTION("""COMPUTED_VALUE"""),0.016666666666666666) -> 0.016666667 | Q5: =IFERROR(__xludf.DUMMYFUNCTION("""COMPUTED_VALUE"""),0.03333333333333334) -> 0.033333333 | S5: 2 | T5: FEBRERO | U5: 11925 | V5: 10786 | W5: =IF(V5="","",V5/U5) -> 0.90448637
B6: HORA DE INICIO | C6: =VLOOKUP($B$3,'BASE DE DATOS CIERRE'!A:AA,4,0) -> 0.63194444 | L6: =IFERROR(__xludf.DUMMYFUNCTION("""COMPUTED_VALUE"""),"INC, DF, SUS, PER, PAT") -> INC, DF, SUS, PER, PAT | M6: =IFERROR(__xludf.DUMMYFUNCTION("""COMPUTED_VALUE"""),4.0) -> 4 | N6: =IFERROR(__xludf.DUMMYFUNCTION("""COMPUTED_VALUE"""),0.06666666666666667) -> 0.066666667 | O6: =IFERROR(__xludf.DUMMYFUNCTION("""COMPUTED_VALUE"""),6.0) -> 6 | P6: =IFERROR(__xludf.DUMMYFUNCTION("""COMPUTED_VALUE"""),0.1) -> 0.1 | Q6: =IFERROR(__xludf.DUMMYFUNCTION("""COMPUTED_VALUE"""),-0.03333333333333334) -> -0.033333333 | S6: 3 | T6: MARZO | U6: 12157 | V6: 12094 | W6: =IF(V6="","",V6/U6) -> 0.9948178
B7: HORA FIN | C7: =VLOOKUP($B$3,'BASE DE DATOS CIERRE'!A:AA,5,0) -> 0.91180556 | L7: =IFERROR(__xludf.DUMMYFUNCTION("""COMPUTED_VALUE"""),"POR CONTRATAR") -> POR CONTRATAR | M7: =IFERROR(__xludf.DUMMYFUNCTION("""COMPUTED_VALUE"""),0.0) -> 0 | N7: =IFERROR(__xludf.DUMMYFUNCTION("""COMPUTED_VALUE"""),0.0) -> 0 | O7: =IFERROR(__xludf.DUMMYFUNCTION("""COMPUTED_VALUE"""),0.0) -> 0 | P7: =IFERROR(__xludf.DUMMYFUNCTION("""COMPUTED_VALUE"""),0.0) -> 0 | Q7: =IFERROR(__xludf.DUMMYFUNCTION("""COMPUTED_VALUE"""),0.0) -> 0 | S7: 4 | T7: ABRIL | U7: 11728 | V7: =SUMIF('BASE DE DATOS CIERRE'!AC:AC,T7,'BASE DE DATOS CIERRE'!C:C) -> 10983 | W7: =IF(V7="","",V7/U7) -> 0.93647681
B8: INDICADOR O.E.E (Mes) | C8: =VLOOKUP(C1,'CONSOLIDADO OEE'!B:O,13,0) -> 0.88163128 | L8: =IFERROR(__xludf.DUMMYFUNCTION("""COMPUTED_VALUE"""),"REUBICADO") -> REUBICADO | M8: =IFERROR(__xludf.DUMMYFUNCTION("""COMPUTED_VALUE"""),1.0) -> 1 | N8: =IFERROR(__xludf.DUMMYFUNCTION("""COMPUTED_VALUE"""),0.016666666666666666) -> 0.016666667 | O8: =IFERROR(__xludf.DUMMYFUNCTION("""COMPUTED_VALUE"""),2.0) -> 2 | P8: =IFERROR(__xludf.DUMMYFUNCTION("""COMPUTED_VALUE"""),0.03333333333333333) -> 0.033333333 | Q8: =IFERROR(__xludf.DUMMYFUNCTION("""COMPUTED_VALUE"""),0.016666666666666666) -> 0.016666667 | S8: 5 | T8: MAYO | U8: 12554 | V8: =SUMIF('BASE DE DATOS CIERRE'!AC:AC,T8,'BASE DE DATOS CIERRE'!C:C) -> 12904 | W8: =IF(V8="","",V8/U8) -> 1.0278796
B9: INDICADOR O.E.E (Dia) | C9: =VLOOKUP($B$3,'BASE DE DATOS CIERRE'!A:AA,2,0) -> 0.91233147 | L9: =IFERROR(__xludf.DUMMYFUNCTION("""COMPUTED_VALUE"""),"ENTRENAMIENTO") -> ENTRENAMIENTO | M9: =IFERROR(__xludf.DUMMYFUNCTION("""COMPUTED_VALUE"""),3.0) -> 3 | N9: =IFERROR(__xludf.DUMMYFUNCTION("""COMPUTED_VALUE"""),0.05) -> 0.05 | O9: =IFERROR(__xludf.DUMMYFUNCTION("""COMPUTED_VALUE"""),3.0) -> 3 | P9: =IFERROR(__xludf.DUMMYFUNCTION("""COMPUTED_VALUE"""),0.05) -> 0.05 | Q9: =IFERROR(__xludf.DUMMYFUNCTION("""COMPUTED_VALUE"""),0.0) -> 0 | S9: 6 | T9: JUNIO | U9: 12635 | V9: =SUMIF('BASE DE DATOS CIERRE'!AC:AC,T9,'BASE DE DATOS CIERRE'!C:C) -> 12920 | W9: =IF(V9="","",V9/U9) -> 1.0225564
B10: VELOCIDAD LÍNEA DE BENEFICIO | C10: =VLOOKUP($B$3,'BASE DE DATOS CIERRE'!A:AA,9,0) -> 74.787535 | L10: =IFERROR(__xludf.DUMMYFUNCTION("""COMPUTED_VALUE"""),"INCAPACIDAD LARGAS") -> INCAPACIDAD LARGAS | M10: =IFERROR(__xludf.DUMMYFUNCTION("""COMPUTED_VALUE"""),0.0) -> 0 | N10: =IFERROR(__xludf.DUMMYFUNCTION("""COMPUTED_VALUE"""),0.0) -> 0 | O10: =IFERROR(__xludf.DUMMYFUNCTION("""COMPUTED_VALUE"""),1.0) -> 1 | P10: =IFERROR(__xludf.DUMMYFUNCTION("""COMPUTED_VALUE"""),0.0) -> 0 | S10: 7 | T10: JULIO | U10: 12797 | V10: =SUMIF('BASE DE DATOS CIERRE'!AC:AC,T10,'BASE DE DATOS CIERRE'!C:C) -> 13022 | W10: =IF(V10="","",V10/U10) -> 1.0175822
B11: HORAS LABORADAS | C11: =VLOOKUP($B$3,'BASE DE DATOS CIERRE'!A:AA,10,0) -> 6.7166667 | M11: =IFERROR(__xludf.DUMMYFUNCTION("""COMPUTED_VALUE"""),60.0) -> 60 | O11: =IFERROR(__xludf.DUMMYFUNCTION("""COMPUTED_VALUE"""),60.0) -> 60 | S11: 8 | T11: AGOSTO | U11: 12843 | V11: =SUMIF('BASE DE DATOS CIERRE'!AC:AC,T11,'BASE DE DATOS CIERRE'!C:C) -> 10982 | W11: =IF(V11="","",V11/U11) -> 0.85509616
B12: TARDANZA DE INICIO | C12: =VLOOKUP($B$3,'BASE DE DATOS CIERRE'!A:AA,11,0) -> 0 | E12: OPERATIVIDAD LINEA DE BENEFICIO | S12: 9 | T12: SEPTIEMBRE | U12: 12905 | V12: =SUMIF('BASE DE DATOS CIERRE'!AC:AC,T12,'BASE DE DATOS CIERRE'!C:C) -> 0 | W12: =IF(V12="","",V12/U12) -> 0
B13: INDICADORES | E13: ITEM | F13: CRITERIO | G13: # PERSONAL | H13: % DE PART. | I13: COLABORADOR | S13: 10 | T13: OCTUBRE | U13: 13939 | V13: =SUMIF('BASE DE DATOS CIERRE'!AC:AC,T13,'BASE DE DATOS CIERRE'!C:C) -> 0 | W13: =IF(V13="","",V13/U13) -> 0
B14: PRODUCTIVIDAD | C14: =VLOOKUP($B$3,'BASE DE DATOS CIERRE'!A:AA,12,0) -> 70.77748 | E14: 1 | F14: =IFERROR(__xludf.DUMMYFUNCTION("IMPORTRANGE(""https://docs.google.com/spreadsheets/d/1OjTekbeLGM33cmRz9M_4nXVIyMrUrINjwBqTFNIG2fQ/edit?gid=440714860#gid=440714860"",""RESUMEN!C26:F34"")"),"LABORANDO") -> LABORANDO | G14: =IFERROR(__xludf.DUMMYFUNCTION("""COMPUTED_VALUE"""),51.0) -> 51 | H14: =IFERROR(__xludf.DUMMYFUNCTION("""COMPUTED_VALUE"""),0.85) -> 0.85 | I14: =IFERROR(__xludf.DUMMYFUNCTION("""COMPUTED_VALUE"""),"") | S14: 11 | T14: NOVIEMBRE | U14: 13909 | V14: =SUMIF('BASE DE DATOS CIERRE'!AC:AC,T14,'BASE DE DATOS CIERRE'!C:C) -> 0 | W14: =IF(V14="","",V14/U14) -> 0
B15: VELOCIDAD NETA | C15: =VLOOKUP($B$3,'BASE DE DATOS CIERRE'!A:AA,13,0) -> 74.787535 | E15: =IF(F15="","",E14+1) -> 2 | F15: =IFERROR(__xludf.DUMMYFUNCTION("""COMPUTED_VALUE"""),"VACACIONES") -> VACACIONES | G15: =IFERROR(__xludf.DUMMYFUNCTION("""COMPUTED_VALUE"""),1.0) -> 1 | H15: =IFERROR(__xludf.DUMMYFUNCTION("""COMPUTED_VALUE"""),0.016666666666666666) -> 0.016666667 | I15: =IFERROR(__xludf.DUMMYFUNCTION("""COMPUTED_VALUE"""),"QUINTERO GERSON") -> QUINTERO GERSON | S15: 12 | T15: DICIEMBRE | U15: 14752 | V15: =SUMIF('BASE DE DATOS CIERRE'!AC:AC,T15,'BASE DE DATOS CIERRE'!C:C) -> 0 | W15: =IF(V15="","",V15/U15) -> 0
B16: VELOCIDAD BRUTA | C16: =VLOOKUP($B$3,'BASE DE DATOS CIERRE'!A:AA,14,0) -> 65.508685 | E16: =IF(F16="","",E15+1) -> 3 | F16: =IFERROR(__xludf.DUMMYFUNCTION("""COMPUTED_VALUE"""),"INCAPACIDAD") -> INCAPACIDAD | G16: =IFERROR(__xludf.DUMMYFUNCTION("""COMPUTED_VALUE"""),3.0) -> 3 | H16: =IFERROR(__xludf.DUMMYFUNCTION("""COMPUTED_VALUE"""),0.05) -> 0.05 | I16: =IFERROR(__xludf.DUMMYFUNCTION("""COMPUTED_VALUE"""),"MANTILLA LUIS/ PADILLA MILEXANDE/ PAJARO YAIR") -> MANTILLA LUIS/ PADILLA MILEXANDE/ PAJARO YAIR | S16: TOTAL | U16: =SUM(U4:U15) -> 154510 | V16: =SUM(V4:V15) -> 95205 | W16: =V16/U16 -> 0.61617371
B17: TOLERANCIA CERO | C17: =VLOOKUP($B$3,'BASE DE DATOS CIERRE'!A:AA,15,0) -> 0.0068 | E17: =IF(F17="","",E16+1) -> 4 | F17: =IFERROR(__xludf.DUMMYFUNCTION("""COMPUTED_VALUE"""),"AMORTIZAR EXTRAS") -> AMORTIZAR EXTRAS | G17: =IFERROR(__xludf.DUMMYFUNCTION("""COMPUTED_VALUE"""),1.0) -> 1 | H17: =IFERROR(__xludf.DUMMYFUNCTION("""COMPUTED_VALUE"""),0.016666666666666666) -> 0.016666667 | I17: =IFERROR(__xludf.DUMMYFUNCTION("""COMPUTED_VALUE"""),"JOSE BAUTISTA") -> JOSE BAUTISTA
B18: PIELES | C18: =VLOOKUP($B$3,'BASE DE DATOS CIERRE'!A:AA,16,0) -> 0.056818182 | E18: =IF(F18="","",E17+1) -> 5 | F18: =IFERROR(__xludf.DUMMYFUNCTION("""COMPUTED_VALUE"""),"REUBICADO") -> REUBICADO | G18: =IFERROR(__xludf.DUMMYFUNCTION("""COMPUTED_VALUE"""),2.0) -> 2 | H18: =IFERROR(__xludf.DUMMYFUNCTION("""COMPUTED_VALUE"""),0.03333333333333333) -> 0.033333333 | I18: =IFERROR(__xludf.DUMMYFUNCTION("""COMPUTED_VALUE"""),"CANCINO JAVIER/ MORALES EFRAIN") -> CANCINO JAVIER/ MORALES EFRAIN
B19: CORTE EN PIERNA | C19: =VLOOKUP($B$3,'BASE DE DATOS CIERRE'!A:AA,17,0) -> 0.008 | E19: =IF(F19="","",E18+1) -> 6 | F19: =IFERROR(__xludf.DUMMYFUNCTION("""COMPUTED_VALUE"""),"RENUNCIA") -> RENUNCIA | G19: =IFERROR(__xludf.DUMMYFUNCTION("""COMPUTED_VALUE"""),1.0) -> 1 | H19: =IFERROR(__xludf.DUMMYFUNCTION("""COMPUTED_VALUE"""),0.016666666666666666) -> 0.016666667 | I19: =IFERROR(__xludf.DUMMYFUNCTION("""COMPUTED_VALUE"""),"SUAREZ ANDREY") -> SUAREZ ANDREY
B20: SOBREBARRIGAS ROTAS | C20: =VLOOKUP($B$3,'BASE DE DATOS CIERRE'!A:AA,18,0) -> 0.01 | E20: =IF(F20="","",E19+1) -> 7 | F20: =IFERROR(__xludf.DUMMYFUNCTION("""COMPUTED_VALUE"""),"DIA DE CERO A.T.") -> DIA DE CERO A.T. | G20: =IFERROR(__xludf.DUMMYFUNCTION("""COMPUTED_VALUE"""),1.0) -> 1 | H20: =IFERROR(__xludf.DUMMYFUNCTION("""COMPUTED_VALUE"""),0.016666666666666666) -> 0.016666667 | I20: =IFERROR(__xludf.DUMMYFUNCTION("""COMPUTED_VALUE"""),"BARAJAS EULISIS") -> BARAJAS EULISIS
B21: COBERTURA GRASA | C21: =VLOOKUP($B$3,'BASE DE DATOS CIERRE'!A:AA,19,0) -> 0.0148 | E21: =IF(F21="","",E20+1)
B22: PARADAS PROGRAMADAS (min) | C22: =VLOOKUP($B$3,'BASE DE DATOS CIERRE'!A:AA,8,0) -> 30 | E22: =IF(F22="","",E21+1)
B23: TIEMPOS IMPRODUCTIVOS (min) | C23: =VLOOKUP($B$3,'BASE DE DATOS CIERRE'!A:AA,7,0) -> 20 | E23: TOTAL | G23: =SUM(G14:G22) -> 60 | H23: =SUM(H14:H22) -> 1 | I23: TOTAL AUSENTISMO | J23: =H23-H14 -> 0.15
B25: CIERRE DE PROCESO PRODUCTOS CARNICOS COM | E25: OPERATIVIDAD DE PRODUCTOS CARNICOS COMESTIBLES | L25: =IFERROR(__xludf.DUMMYFUNCTION("IMPORTRANGE(""https://docs.google.com/spreadsheets/d/1CNeKSHTeNNJnfn5EymHwGg5Mkuk6EcepW7_9QkJxalc/edit#gid=206977277"",""RESUMEN!H3:M11"")"),"OPERATIVIDAD DE PCCOM") -> OPERATIVIDAD DE PCCOM | M25: =IFERROR(__xludf.DUMMYFUNCTION("""COMPUTED_VALUE"""),"REAL") -> REAL | N25: =IFERROR(__xludf.DUMMYFUNCTION("""COMPUTED_VALUE"""),"%") -> % | O25: =IFERROR(__xludf.DUMMYFUNCTION("""COMPUTED_VALUE"""),46261.0) -> 46261 | Q25: =IFERROR(__xludf.DUMMYFUNCTION("""COMPUTED_VALUE"""),"DIF") -> DIF
B26: =IFERROR(__xludf.DUMMYFUNCTION("TRANSPOSE(IMPORTRANGE(""https://docs.google.com/spreadsheets/d/1D9Gaq0vid86JLkis77sokTcYmnzylSayfOL-qSUIuis/edit#gid=1366970263"",""CONSOLIDADO DE CIERRE!A1:L1""))"),"FECHA ") -> FECHA | C26: =$B$3 -> 46261 | E26: ITEM | F26: CRITERIO | G26: # PERSONAL | H26: % DE PART. | I26: COLABORADOR | L26: =IFERROR(__xludf.DUMMYFUNCTION("""COMPUTED_VALUE"""),"LIDER/APOYO") -> LIDER/APOYO | M26: =IFERROR(__xludf.DUMMYFUNCTION("""COMPUTED_VALUE"""),2.0) -> 2 | N26: =IFERROR(__xludf.DUMMYFUNCTION("""COMPUTED_VALUE"""),0.0392156862745098) -> 0.039215686 | O26: =IFERROR(__xludf.DUMMYFUNCTION("""COMPUTED_VALUE"""),2.0) -> 2 | P26: =IFERROR(__xludf.DUMMYFUNCTION("""COMPUTED_VALUE"""),0.038461538461538464) -> 0.038461538 | Q26: =IFERROR(__xludf.DUMMYFUNCTION("""COMPUTED_VALUE"""),-7.541478129713397E-4) -> -0.00075414781
B27: =IFERROR(__xludf.DUMMYFUNCTION("""COMPUTED_VALUE"""),"TOTAL DE BENEFICO") -> TOTAL DE BENEFICO | C27: =VLOOKUP($B$3,'CONSOLIDADO DE CIERRE'!$A:$L,2,0) -> 440 | E27: 1 | F27: =IFERROR(__xludf.DUMMYFUNCTION("IMPORTRANGE(""https://docs.google.com/spreadsheets/d/1CNeKSHTeNNJnfn5EymHwGg5Mkuk6EcepW7_9QkJxalc/edit#gid=206977277"",""RESUMEN!C26:F35"")"),"LABORANDO") -> LABORANDO | G27: =IFERROR(__xludf.DUMMYFUNCTION("""COMPUTED_VALUE"""),48.0) -> 48 | H27: =IFERROR(__xludf.DUMMYFUNCTION("""COMPUTED_VALUE"""),0.9230769230769231) -> 0.92307692 | I27: =IFERROR(__xludf.DUMMYFUNCTION("""COMPUTED_VALUE"""),"") | L27: =IFERROR(__xludf.DUMMYFUNCTION("""COMPUTED_VALUE"""),"OPERACION") -> OPERACION | M27: =IFERROR(__xludf.DUMMYFUNCTION("""COMPUTED_VALUE"""),41.0) -> 41 | N27: =IFERROR(__xludf.DUMMYFUNCTION("""COMPUTED_VALUE"""),0.803921568627451) -> 0.80392157 | O27: =IFERROR(__xludf.DUMMYFUNCTION("""COMPUTED_VALUE"""),46.0) -> 46 | P27: =IFERROR(__xludf.DUMMYFUNCTION("""COMPUTED_VALUE"""),0.8846153846153846) -> 0.88461538 | Q27: =IFERROR(__xludf.DUMMYFUNCTION("""COMPUTED_VALUE"""),0.08069381598793357) -> 0.080693816
B28: =IFERROR(__xludf.DUMMYFUNCTION("""COMPUTED_VALUE"""),"HORA INICIO CABEZAS") -> HORA INICIO CABEZAS | C28: =VLOOKUP($B$3,'CONSOLIDADO DE CIERRE'!$A:$L,3,0) -> 0.63194444 | E28: =IF(F28="","",E27+1) -> 2 | F28: =IFERROR(__xludf.DUMMYFUNCTION("""COMPUTED_VALUE"""),"INCAPACIDAD") -> INCAPACIDAD | G28: =IFERROR(__xludf.DUMMYFUNCTION("""COMPUTED_VALUE"""),1.0) -> 1 | H28: =IFERROR(__xludf.DUMMYFUNCTION("""COMPUTED_VALUE"""),0.019230769230769232) -> 0.019230769 | I28: =IFERROR(__xludf.DUMMYFUNCTION("""COMPUTED_VALUE"""),"AGUDELO DANIEL") -> AGUDELO DANIEL | L28: =IFERROR(__xludf.DUMMYFUNCTION("""COMPUTED_VALUE"""),"VACACIONES") -> VACACIONES | M28: =IFERROR(__xludf.DUMMYFUNCTION("""COMPUTED_VALUE"""),3.0) -> 3 | N28: =IFERROR(__xludf.DUMMYFUNCTION("""COMPUTED_VALUE"""),0.058823529411764705) -> 0.058823529 | O28: =IFERROR(__xludf.DUMMYFUNCTION("""COMPUTED_VALUE"""),0.0) -> 0 | P28: =IFERROR(__xludf.DUMMYFUNCTION("""COMPUTED_VALUE"""),0.0) -> 0 | Q28: =IFERROR(__xludf.DUMMYFUNCTION("""COMPUTED_VALUE"""),0.058823529411764705) -> 0.058823529
B29: =IFERROR(__xludf.DUMMYFUNCTION("""COMPUTED_VALUE"""),"HORA ULTIMA VISCERA AMARRADA") -> HORA ULTIMA VISCERA AMARRADA | C29: =VLOOKUP($B$3,'CONSOLIDADO DE CIERRE'!$A:$L,4,0) -> 0.93958333 | E29: =IF(F29="","",E28+1) -> 3 | F29: =IFERROR(__xludf.DUMMYFUNCTION("""COMPUTED_VALUE"""),"REUBICADO") -> REUBICADO | G29: =IFERROR(__xludf.DUMMYFUNCTION("""COMPUTED_VALUE"""),1.0) -> 1 | H29: =IFERROR(__xludf.DUMMYFUNCTION("""COMPUTED_VALUE"""),0.019230769230769232) -> 0.019230769 | I29: =IFERROR(__xludf.DUMMYFUNCTION("""COMPUTED_VALUE"""),"RENGIFO OSCAR") -> RENGIFO OSCAR | L29: =IFERROR(__xludf.DUMMYFUNCTION("""COMPUTED_VALUE"""),"INC, DF, SUS, PER, PAT") -> INC, DF, SUS, PER, PAT | M29: =IFERROR(__xludf.DUMMYFUNCTION("""COMPUTED_VALUE"""),4.0) -> 4 | N29: =IFERROR(__xludf.DUMMYFUNCTION("""COMPUTED_VALUE"""),0.0784313725490196) -> 0.078431373 | O29: =IFERROR(__xludf.DUMMYFUNCTION("""COMPUTED_VALUE"""),1.0) -> 1 | P29: =IFERROR(__xludf.DUMMYFUNCTION("""COMPUTED_VALUE"""),0.019230769230769232) -> 0.019230769 | Q29: =IFERROR(__xludf.DUMMYFUNCTION("""COMPUTED_VALUE"""),0.059200603318250375) -> 0.059200603
B30: =IFERROR(__xludf.DUMMYFUNCTION("""COMPUTED_VALUE"""),"TOTAL PAROS ") -> TOTAL PAROS | C30: =VLOOKUP($B$3,'CONSOLIDADO DE CIERRE'!$A:$L,5,0) -> 0.83333333 | E30: =IF(F30="","",E29+1) -> 4 | F30: =IFERROR(__xludf.DUMMYFUNCTION("""COMPUTED_VALUE"""),"PDTE POR CONTRATAR") -> PDTE POR CONTRATAR | G30: =IFERROR(__xludf.DUMMYFUNCTION("""COMPUTED_VALUE"""),2.0) -> 2 | H30: =IFERROR(__xludf.DUMMYFUNCTION("""COMPUTED_VALUE"""),0.038461538461538464) -> 0.038461538 | L30: =IFERROR(__xludf.DUMMYFUNCTION("""COMPUTED_VALUE"""),"POR CONTRATAR") -> POR CONTRATAR | M30: =IFERROR(__xludf.DUMMYFUNCTION("""COMPUTED_VALUE"""),0.0) -> 0 | N30: =IFERROR(__xludf.DUMMYFUNCTION("""COMPUTED_VALUE"""),0.0) -> 0 | O30: =IFERROR(__xludf.DUMMYFUNCTION("""COMPUTED_VALUE"""),2.0) -> 2 | P30: =IFERROR(__xludf.DUMMYFUNCTION("""COMPUTED_VALUE"""),0.038461538461538464) -> 0.038461538 | Q30: =IFERROR(__xludf.DUMMYFUNCTION("""COMPUTED_VALUE"""),0.038461538461538464) -> 0.038461538
B31: =IFERROR(__xludf.DUMMYFUNCTION("""COMPUTED_VALUE"""),"DURACIÓN PROCESO (Hrs)") -> DURACIÓN PROCESO (Hrs) | C31: =VLOOKUP($B$3,'CONSOLIDADO DE CIERRE'!$A:$L,6,0) -> 7.3833333 | E31: =IF(F31="","",E30+1) | L31: =IFERROR(__xludf.DUMMYFUNCTION("""COMPUTED_VALUE"""),"REUBICADO") -> REUBICADO | M31: =IFERROR(__xludf.DUMMYFUNCTION("""COMPUTED_VALUE"""),1.0) -> 1 | N31: =IFERROR(__xludf.DUMMYFUNCTION("""COMPUTED_VALUE"""),0.0196078431372549) -> 0.019607843 | O31: =IFERROR(__xludf.DUMMYFUNCTION("""COMPUTED_VALUE"""),1.0) -> 1 | P31: =IFERROR(__xludf.DUMMYFUNCTION("""COMPUTED_VALUE"""),0.019230769230769232) -> 0.019230769 | Q31: =IFERROR(__xludf.DUMMYFUNCTION("""COMPUTED_VALUE"""),-3.7707390648566985E-4) -> -0.00037707391
B32: =IFERROR(__xludf.DUMMYFUNCTION("""COMPUTED_VALUE"""),"RENDIMIENTO BRUTO (visceras/hora)") -> RENDIMIENTO BRUTO (visceras/hora) | C32: =VLOOKUP($B$3,'CONSOLIDADO DE CIERRE'!$A:$L,7,0) -> 59.593679 | E32: =IF(F32="","",E31+1) | L32: =IFERROR(__xludf.DUMMYFUNCTION("""COMPUTED_VALUE"""),"INCAPACIDAD LARGAS") -> INCAPACIDAD LARGAS | M32: =IFERROR(__xludf.DUMMYFUNCTION("""COMPUTED_VALUE"""),0.0) -> 0 | O32: =IFERROR(__xludf.DUMMYFUNCTION("""COMPUTED_VALUE"""),0.0) -> 0
B33: =IFERROR(__xludf.DUMMYFUNCTION("""COMPUTED_VALUE"""),"RENDIMIENTO NETO (visceras/hora)") -> RENDIMIENTO NETO (visceras/hora) | C33: =VLOOKUP($B$3,'CONSOLIDADO DE CIERRE'!$A:$L,8,0) -> 67.175573 | E33: =IF(F33="","",E32+1) | M33: =IFERROR(__xludf.DUMMYFUNCTION("""COMPUTED_VALUE"""),51.0) -> 51 | O33: =IFERROR(__xludf.DUMMYFUNCTION("""COMPUTED_VALUE"""),52.0) -> 52
B34: =IFERROR(__xludf.DUMMYFUNCTION("""COMPUTED_VALUE"""),"RENDIMIENTO (visceras/hr/hombre)") -> RENDIMIENTO (visceras/hr/hombre) | C34: =VLOOKUP($B$3, 'CONSOLIDADO DE CIERRE'!$A:$L, 9, 0) -> 1.241535 | E34: =IF(F34="","",E33+1)
B35: =IFERROR(__xludf.DUMMYFUNCTION("""COMPUTED_VALUE"""),"MINUTOS PAROS PROGRAMADOS") -> MINUTOS PAROS PROGRAMADOS | C35: =VLOOKUP($B$3,'CONSOLIDADO DE CIERRE'!$A:$L,10,0) -> 30 | E35: =IF(F35="","",E34+1)
B36: =IFERROR(__xludf.DUMMYFUNCTION("""COMPUTED_VALUE"""),"MINUTOS PAROS NO PROGRAMADOS") -> MINUTOS PAROS NO PROGRAMADOS | C36: =VLOOKUP($B$3,'CONSOLIDADO DE CIERRE'!$A:$L,11,0) -> 20 | E36: =IF(F36="","",E35+1)
B37: =IFERROR(__xludf.DUMMYFUNCTION("""COMPUTED_VALUE"""),"NOVEDADES:") -> NOVEDADES: | C37: =VLOOKUP($B$3,'CONSOLIDADO DE CIERRE'!$A:$L,12,0) | E37: TOTAL | G37: =SUM(G27:G36) -> 52 | H37: =SUM(H27:H36) -> 1 | I37: TOTAL AUSENTISMO | J37: =H37-H27 -> 0.076923077
B40: DISTRIBUCION DE PERSONAL PLANTA DE BENEFICIO
B42: LINEA DE BENEFICIO | F42: PCCOM | I42: =B3 -> 46261
B43: CARGO | F43: CARGO | I43: =CONCATENATE("Hora de Inicio proceso: *",TEXT("00:00",C6),"*") -> Hora de Inicio proceso: *15:10*
B44: ENMANGADO | C44: 1 | F44: IMPRESIÓN DE BRAZALETES | H44: 1 | I44: =CONCATENATE("Hora fin proceso: *",TEXT("00:00",C7),"*") -> Hora fin proceso: *21:53*
B45: AUX DIGITACION | C45: 1 | F45: DESCARETADO | H45: 1 | I45: =CONCATENATE("Parada programada: *",C22, "* Min") -> Parada programada: *30* Min
B46: INSENSIBILIZACION | C46: 1 | F46: LENGUA | H46: 1 | I46: =CONCATENATE("Tiempos improductivos y causas: ",C23, " Min ", G3) -> Tiempos improductivos y causas: 20 Min 1. Se registra parada por tanque cañón ruminal tapado (20)
B47: AUX.IZADO | C47: 1 | F47: IDENTIFICACION DE CABEZAS | H47: 1
B48: IZADO | C48: 1 | F48: RAYAR 1 | H48: 1 | I48: =CONCATENATE("Número de personas en proceso: *",O4+O9,"* Beneficio, *" ,O27 ,"* PCCOM") -> Número de personas en proceso: *51* Beneficio, *46* PCCOM
B49: SECCION DE GRANDE VASOS | C49: 1 | F49: RAYAR 2 | H49: 1 | I49: =CONCATENATE("Número de animales en beneficio: *" , C5 ,"*") -> Número de animales en beneficio: *440*
B50: ANUDADO DE ESOFAGO | C50: 1 | F50: MAQUINA DE CABEZAS | H50: 1
B51: ESTIMULADOR Y DESCORNADO | C51: 1 | F51: PARAR | H51: 1
B52: DEGUELLO | C52: 1 | F52: DESPOSTE 1 | H52: 1
B53: RAYADO Y CORTE DE MANOS | C53: 1 | F53: DESPOSTE 2 | H53: 1
B54: PATIN ZONA SUCIA | C54: 1 | F54: MAQUINA DE PATAS | H54: 1
B55: DESUELLO DE PRIMERA PIERNA 1 | C55: 1 | F55: DESCASCADOR | H55: 1
B56: DESUELLO DE PRIMERA PIERNA 2 | C56: 1 | F56: AMARRADO DE PATAS | H56: 1
B57: TRANSFERENCIA | C57: 1 | F57: ESOFAGO | H57: 1
B58: DESUELLO DE SEGUNDA PIERNA 1 | C58: 1 | F58: APARTAR | H58: 1
B59: DESUELLO DE SEGUNDA PIERNA 2 | C59: 1 | F59: DESURTIR | H59: 1
B60: TRANSFERENCIA 2 | C60: 1 | F60: LAVAR CANUTA | H60: 1
B61: DESUELLO COSTAL PROFUNDO 1 | C61: 1 | F61: VOLTEAR CANUTA | H61: 1
... B85: PESAJE | C85: 1 | F85: REUBICADO | H85: 1
B86: RESES DE EMERGENCIA | C86: 1
B87: AFILADO | C87: 1
B88: ALMACEN 1-2 Y CAJAS (REUBICADOS | C88: 0
B89: VACACIONES | C89: 3
B90: INCAPA /CALAD/D.D.L.F/LICENCIAS/RENUNCI | C90: 4
B91: ENTREANAMIENTO | C91: 3
B92: TOTAL | C92: =SUM(C44:C91) -> 56 | F92: TOTAL | H92: =SUM(H44:H91) -> 51
A93: 48475

Sheet BASE DE DATOS CIERRE
A1: FECHA | B1: INDICADOE O.E.E | C1: TOTAL DE BENEFICIO | D1: HORA DE INICIO | E1: HORA FIN | F1: Duracion minutos | G1: TIEMPO DE PARADAS (min) | H1: PARADA PROGRAMADA (min) | I1: VELOCIDAD LÍNEA DE BENEFICIO | J1: HORAS LABORADAS | K1: TARDANZA DE INICIO | L1: PRODUCTIVIDAD | M1: VELOCIDAD NETA | N1: VELOCIDAD BRUTA | O1: TOLERANCIA CERO | P1: PIELES | Q1: CORTE EN PIERNA | R1: SOBREBARRIGAS ROTAS | S1: COBERTURA GRASA | T1: HEMATOMAS | U1: TOTAL PIELES ROTAS | V1: OBSERVACION | W1: % tiempo improductivo | X1: Capacidad Instalada | Y1: Liberación canales | Z1: Disponibilidad | AA1: Rendimiento | AB1: Calidad | AC1: MES | AD1: AÑO
A2: 46094 | B2: {=IF(Z2:Z1000="","",Z2:Z1000*AA2:AA1000*AB2:AB1000)} -> 0 | C2: 421 | D2: 0.58333333 | E2: 0.88125 | F2: {=IF(E2:E1000="","",(E2:E1000-D2:D1000)*24*60)} -> 429 | G2: 61 | H2: 30 | I2: {=M2:M1000} -> 74.733728 | J2: {=IF(F2:F1000="","",(F2:F1000/60))} -> 7.15 | K2: 0 | L2: {=IFERROR($C$2:$C1000/(($F$2:F1000-$H$2:H1000)/60),"")} -> 63.308271 | M2: {=IFERROR(C2:C1000/((F2:F1000-(H2:H1000+G2:G1000))/60),"")} -> 74.733728 | N2: {=IFERROR(C2:C1000/J2:J1000,"")} -> 58.881119 | O2: 0.0096 | P2: {=IFERROR((U2:U1000/C2:C1000),"")} -> 0.023752969 | Q2: {=IFERROR(VLOOKUP($A2:$A50,'LIBERACION DE CANALES'!$B50:$K1000,9,0),"")} | R2: {=IFERROR(VLOOKUP($A2:$A50,'LIBERACION DE CANALES'!$B50:$K1000,10,0),"")} | S2: {=IFERROR(VLOOKUP($A2:$A50,'LIBERACION DE CANALES'!$B50:$K1000,7,0),"")} | T2: {=IFERROR(VLOOKUP($A2:$A50,'LIBERACION DE CANALES'!$B50:$K1000,8,0),"")} | U2: 10 | W2: {=IF(G2:G1000="","",G2:G1000/F2:F1000)} -> 0.14219114 | X2: {=IF(M2:M1000>75,M2:M1000,75)} -> 75 | Y2: {=IF(Q2:Q1000="","",Q2:Q1000+R2:R1000+S2:S1000+T2:T1000)} | Z2: {=IF(W2:W1000="","",1-W2:W1000)} -> 0.85780886 | AA2: {=IF(W2:W1000="","",M2:M1000/X2:X1000)} -> 0.9964497 | AB2: {=IF(Y2:Y1000="","",1-Y2:Y1000)} | AC2: {=UPPER(TEXT($A$2:$A1000,"MMMM"))} -> MARZO | AD2: {=UPPER(TEXT($A$2:$A1000,"YYY"))} -> 2026
A3: =IF(C3="","",A2+1) -> 46095 | B3: 0 | C3: 231 | D3: 0.625 | E3: 0.76597222 | F3: 203 | G3: 9 | H3: 30 | I3: 84.512195 | J3: 3.3833333 | K3: 0 | L3: 80.115607 | M3: 84.512195 | N3: 68.275862 | O3: 0.0033 | P3: 0.017316017 | U3: 4 | W3: 0.044334975 | X3: 84.512195 | Z3: 0.95566502 | AA3: 1 | AC3: MARZO | AD3: 2026
A4: =IF(C4="","",A3+1) -> 46096 | C4: 0 | AC4: MARZO | AD4: 2026
A5: =IF(C5="","",A4+1) -> 46097 | B5: 0 | C5: 554 | D5: 0.58333333 | E5: 0.91805556 | F5: 482 | G5: 30 | H5: 30 | I5: 78.767773 | J5: 8.0333333 | K5: 0 | L5: 73.539823 | M5: 78.767773 | N5: 68.962656 | O5: 0.0027 | P5: 0.02166065 | U5: 12 | W5: 0.062240664 | X5: 78.767773 | Z5: 0.93775934 | AA5: 1 | AC5: MARZO | AD5: 2026
A6: =IF(C6="","",A5+1) -> 46098 | B6: 0 | C6: 501 | D6: 0.58333333 | E6: 0.89166667 | F6: 444 | G6: 17 | H6: 30 | I6: 75.717884 | J6: 7.4 | K6: 0 | L6: 72.608696 | M6: 75.717884 | N6: 67.702703 | O6: 0.0096 | P6: 0.031936128 | U6: 16 | W6: 0.038288288 | X6: 75.717884 | Z6: 0.96171171 | AA6: 1 | AC6: MARZO | AD6: 2026
A7: =IF(C7="","",A6+1) -> 46099 | B7: 0 | C7: 322 | D7: 0.625 | E7: 0.85 | F7: 324 | G7: 30 | H7: 30 | I7: 73.181818 | J7: 5.4 | K7: 0 | L7: 65.714286 | M7: 73.181818 | N7: 59.62963 | O7: 0.0024 | P7: 0.01863354 | U7: 6 | W7: 0.092592593 | X7: 75 | Z7: 0.90740741 | AA7: 0.97575758 | AC7: MARZO | AD7: 2026
A8: =IF(C8="","",A7+1) -> 46100 | B8: 0 | C8: 618 | D8: 0.58333333 | E8: 0.95763889 | F8: 539 | G8: 37 | H8: 45 | I8: 81.137856 | J8: 8.9833333 | K8: 0 | L8: 75.060729 | M8: 81.137856 | N8: 68.794063 | O8: 0.0157 | P8: 0.021035599 | U8: 13 | W8: 0.06864564 | X8: 81.137856 | Z8: 0.93135436 | AA8: 1 | AC8: MARZO | AD8: 2026
A9: =IF(C9="","",A8+1) -> 46101 | B9: 0 | C9: 398 | D9: 0.58333333 | E9: 0.82916667 | F9: 354 | G9: 0 | H9: 30.4 | I9: 73.794808 | J9: 5.9 | K9: 0 | L9: 73.794808 | M9: 73.794808 | N9: 67.457627 | O9: 0.0032 | P9: 0.015075377 | U9: 6 | W9: 0 | X9: 75 | Z9: 1 | AA9: 0.98393078 | AC9: MARZO | AD9: 2026
A10: =IF(C10="","",A9+1) -> 46102 | B10: 0 | C10: 313 | D10: 0.625 | E10: 0.78055556 | F10: 224 | G10: 6 | H10: 0 | I10: 86.146789 | J10: 3.7333333 | K10: 0 | L10: 83.839286 | M10: 86.146789 | N10: 83.839286 | O10: 0.0048 | P10: 0.028753994 | U10: 9 | W10: 0.026785714 | X10: 86.146789 | Z10: 0.97321429 | AA10: 1 | AC10: MARZO | AD10: 2026
A11: =IF(C11="","",A10+1) -> 46103 | C11: 0 | AC11: MARZO | AD11: 2026
A12: =IF(C12="","",A11+1) -> 46104 | B12: 0 | C12: 721 | D12: 0.58333333 | E12: 1.0652778 | F12: 694 | G12: 30 | H12: 60 | I12: 71.622517 | J12: 11.566667 | K12: 0 | L12: 68.233438 | M12: 71.622517 | N12: 62.334294 | O12: 0.001 | P12: 0.012482663 | U12: 9 | W12: 0.043227666 | X12: 75 | Z12: 0.95677233 | AA12: 0.95496689 | AC12: MARZO | AD12: 2026
A13: =IF(C13="","",A12+1) -> 46105 | B13: 0 | C13: 328 | D13: 0.625 | E13: 0.82986111 | F13: 295 | G13: 20 | H13: 0 | I13: 71.563636 | J13: 4.9166667 | K13: 0 | L13: 66.711864 | M13: 71.563636 | N13: 66.711864 | O13: 0.0076 | P13: 0.018292683 | U13: 6 | V13: 1. Se registra parada debido a cambio de manguera de cuchillos neumáticos (8). 2. Se registra parada por animal atascado en el box de noqueó (6). 3. Se registra parada por cambio de cuchillas de cuchillos neumáticos (6). 4. Disnimucion de velocidad debido a alto porcentaje de ausentismo (Se requiroi mover personal reubiado para poder cubrir puestos de trabajo). | W13: 0.06779661 | X13: 75 | Z13: 0.93220339 | AA13: 0.95418182 | AC13: MARZO | AD13: 2026
A14: =IF(C14="","",A13+1) -> 46106 | B14: 0 | C14: 359 | D14: 0.625 | E14: 0.85902778 | F14: 337 | G14: 15 | H14: 30 | I14: 73.767123 | J14: 5.6166667 | K14: 0 | L14: 70.162866 | M14: 73.767123 | N14: 63.916914 | O14: 0.0049 | P14: 0.030640669 | U14: 11 | V14: 1. Se presenta parada por baja presión en cuchillos neumáticos y box (8). 2. Se registra parada por acumulacion en puesto de trabajo desolladora (4) (esto es debido a que se tuvo que poner personal en entrenamiento para darle descanso a titulares. 3.Se registra parada debido a sin animales, para continuar el proceso (3). | W14: 0.044510386 | X14: 75 | Z14: 0.95548961 | AA14: 0.98356164 | AC14: MARZO | AD14: 2026
A15: =IF(C15="","",A14+1) -> 46107 | B15: 0 | C15: 504 | D15: 0.58333333 | E15: 0.89305556 | F15: 446 | G15: 35 | H15: 30 | I15: 79.370079 | J15: 7.4333333 | K15: 0 | L15: 72.692308 | M15: 79.370079 | N15: 67.802691 | O15: 0.007 | P15: 0.035714286 | U15: 18 | W15: 0.078475336 | X15: 79.370079 | Z15: 0.92152466 | AA15: 1 | AC15: MARZO | AD15: 2026
A16: =IF(C16="","",A15+1) -> 46108 | B16: 0 | C16: 337 | D16: 0.625 | E16: 0.82708333 | F16: 291 | G16: 0 | H16: 30 | I16: 77.471264 | J16: 4.85 | K16: 0 | L16: 77.471264 | M16: 77.471264 | N16: 69.484536 | O16: 0.0067 | P16: 0.03264095 | U16: 11 | V16: 1. Se realiza parada porgramada para dar tiempo a animales por tiempos de ayudo | W16: 0 | X16: 77.471264 | Z16: 1 | AA16: 1 | AC16: MARZO | AD16: 2026
A17: =IF(C17="","",A16+1) -> 46109 | B17: 0 | C17: 456 | D17: 0.62986111 | E17: 0.90138889 | F17: 391 | G17: 36 | H17: 30 | I17: 84.184615 | J17: 6.5166667 | K17: 7 | L17: 75.789474 | M17: 84.184615 | N17: 69.974425 | O17: 0.0071 | P17: 0 | V17: 1. Se registra parada debido acumulación de canales en zona Intermedia debido a la novedad de sirt (6). 2. Se registra parada debido a gualla que se sale de polea en desensor de guilletes (3). 3. Se registra parada debido a gualla que se sale de freno manual de corte de manos (14). 4. Se registra parada para ajustar cadera de desolladora (13). | W17: 0.092071611 | X17: 84.184615 | Z17: 0.90792839 | AA17: 1 | AC17: MARZO | AD17: 2026
A18: =IF(C18="","",A17+1) -> 46110 | C18: 0 | AC18: MARZO | AD18: 2026
A19: =IF(C19="","",A18+1) -> 46111 | B19: 0 | C19: 678 | D19: 0.58333333 | E19: 1.0104167 | F19: 615 | G19: 20 | H19: 60 | I19: 76.037383 | J19: 10.25 | K19: 0 | L19: 73.297297 | M19: 76.037383 | N19: 66.146341 | O19: 0.0019 | P19: 0.028023599 | U19: 19 | V19: 1. Se registra parada debido a novedad con plataforma de eviscerado de blanca (15). 2. Se registra parada debido animal que se desprende el tendón (5). | W19: 0.032520325 | X19: 76.037383 | Z19: 0.96747967 | AA19: 1 | AC19: MARZO | AD19: 2026
A20: =IF(C20="","",A19+1) -> 46112 | B20: 0 | C20: 430 | D20: 0.58333333 | E20: 0.85138889 | F20: 386 | G20: =5+9 -> 14 | H20: 30 | I20: 75.438596 | J20: 6.4333333 | K20: 0 | L20: 72.47191 | M20: 75.438596 | N20: 66.839378 | O20: 0.0029 | P20: 0.023255814 | U20: 10 | V20: 1. Se registra parada por animal atascado en el riel de Izado, no encarra correctamente en el riel debido al péndulo que se genera al subir (9). 2. Se registra parada debido a techo de manga de ingreso a box que se cae (5). | W20: 0.03626943 | X20: 75.438596 | Z20: 0.96373057 | AA20: 1 | AC20: MARZO | AD20: 2026
A21: =IF(C21="","",A20+1) -> 46113 | B21: 0 | C21: 316 | D21: 0.58333333 | E21: 1.1701389 | F21: 845 | G21: 590 | H21: 0 | I21: 74.352941 | J21: 14.083333 | K21: 0 | L21: 22.43787 | M21: 74.352941 | N21: 22.43787 | O21: 0.0032 | P21: 0.018987342 | U21: 6 | V21: 1. Se registra parada debido a que no se cuenta con fluido eléctrico en planta benéficio (590 min de tiempo improductivo). | W21: 0.69822485 | X21: 75 | Z21: 0.30177515 | AA21: 0.99137255 | AC21: ABRIL | AD21: 2026
A22: =IF(C22="","",A21+1) -> 46114 | C22: 0 | AC22: ABRIL | AD22: 2026
A23: =IF(C23="","",A22+1) -> 46115 | C23: 0 | AC23: ABRIL | AD23: 2026
A24: =IF(C24="","",A23+1) -> 46116 | B24: 0 | C24: 431 | D24: 0.625 | E24: 0.87777778 | F24: 364 | G24: 0 | H24: 30 | I24: 77.42515 | J24: 6.0666667 | K24: 0 | L24: 77.42515 | M24: 77.42515 | N24: 71.043956 | O24: 0.007 | P24: 0.027842227 | U24: 12 | W24: 0 | X24: 77.42515 | Z24: 1 | AA24: 1 | AC24: ABRIL | AD24: 2026
A25: =IF(C25="","",A24+1) -> 46117 | C25: 0 | K25: 0 | AC25: ABRIL | AD25: 2026
A26: =IF(C26="","",A25+1) -> 46118 | B26: 0 | C26: 679 | D26: 0.58333333 | E26: 1.0368056 | F26: 653 | G26: 77 | H26: 60 | I26: 78.953488 | J26: 10.883333 | K26: 0 | L26: 68.701518 | M26: 78.953488 | N26: 62.388974 | O26: 0.008 | P26: 0.025036819 | U26: 17 | V26: 1. Se registra parada por válvula del temporizador cerrada (7min) 2. se registra parada por falla en el final de carrera de la plataforma titular de la desolladora (18min) 3. se registra parada por acumulación de canales en el puesto de corte de esternón, debido a falla en las dos sierras ( titular con perdida de fuerza y contingencia con pulsador directo) (20min) 4. se registra parada por tanque cañón de pieles tapado debido al beneficio de 50 Búfalos de Olímpica (24min) 5.se registra parada por animal atascado de una pata, en la manga de ingreso al box (8min) | W26: 0.1179173 | X26: 78.953488 | Z26: 0.8820827 | AA26: 1 | AC26: ABRIL | AD26: 2026
A27: =IF(C27="","",A26+1) -> 46119 | B27: 0 | C27: 445 | D27: 0.58333333 | E27: 0.89305556 | F27: 446 | G27: 30 | H27: 35 | I27: 70.07874 | J27: 7.4333333 | K27: 0 | L27: 64.963504 | M27: 70.07874 | N27: 59.865471 | O27: 0.0084 | P27: 0.024719101 | U27: 11 | V27: 1. Se presenta parada por novedad en transferencia 1 (9) 2. Se registra parada por animal atascado en el riel de Izado, no encarra correctamente en el riel debido al péndulo que se genera al subir. (9). 3. - Se registra parada debido a guilletes que se queda atascado en freno manual de escornado (12). 4. Se evidencia una desminucion de velocidad debido al alto porcentaje de ausentismo y cansancio de personal. | W27: 0.067264574 | X27: 75 | Z27: 0.93273543 | AA27: 0.9343832 | AC27: ABRIL | AD27: 2026
A28: =IF(C28="","",A27+1) -> 46120 | B28: 0 | C28: 489 | D28: 0.58333333 | E28: 0.91666667 | F28: 480 | G28: 70 | H28: 30 | I28: 77.210526 | J28: 8 | K28: 0 | L28: 65.2 | M28: 77.210526 | N28: 61.125 | O28: 0.0118 | P28: 0 | V28: 1. Se registra parada por falla en el final de carrera de la plataforma titular de la desolladora (21) 2. Se registra parada por cable suelto de pedal subir plataforma titular de desoresdora (20). 3. - Se registra parada debido a cable suelto en control de box. (6). 4. Se registra parada debido animal que no ingresa a box por tener los cachos grandes y se queda atascado en mango de ingreso (9). 5. Se registra parada por animal que no queria ingresar a box y tábano no estaba funcionando (10). 6. Se registra parada debido a animal caído en manga ingreso a box (4). | W28: 0.14583333 | X28: 77.210526 | Z28: 0.85416667 | AA28: 1 | AC28: ABRIL | AD28: 2026
A29: =IF(C29="","",A28+1) -> 46121 | B29: 0 | C29: 564 | D29: 0.58333333 | E29: 0.92291667 | F29: 489 | G29: 23 | H29: 30 | I29: 77.614679 | J29: 8.15 | K29: 0 | L29: 73.72549 | M29: 77.614679 | N29: 69.202454 | O29: 0.0081 | P29: 0.023049645 | U29: 13 | V29: 1. Se presenta parada por el descensor de guilletes que se queda pegado a mitad y se demora en atender, ya que técnico estába atendiendo otra solicitud (5) 2. Se registra parada sin animales en manga ingreso al box (2) 3. Se registra parada debido a básculas con memoria llena, (técnico no tenía conocimiento como hacer el procedimiento de borrado)(16) 4. Se presenta accidente grave al operario Barajas fidel, estando en puesto emmangado se sube en box y compeñero al momento de cerrar puertas de ingreso a box le apriciona el dedo indice de mano izquierda. | W29: 0.047034765 | X29: 77.614679 | Z29: 0.95296524 | AA29: 1 | AC29: ABRIL | AD29: 2026
A30: =IF(C30="","",A29+1) -> 46122 | B30: 0 | C30: 240 | D30: 0.625 | E30: 0.79166667 | F30: 240 | G30: 6 | H30: 35 | I30: 72.361809 | J30: 4 | K30: 0 | L30: 70.243902 | M30: 72.361809 | N30: 60 | O30: 0.0031 | P30: 0.029166667 | U30: 7 | V30: 1. Se registra parada por fallo en frenos automáticos de linea ( electro válvula pegada) (6) 2. Se realiza parada programada para dar tiempo a reses que no cumplian tiempos de ayuno, por ser bajo el beneficio no podimos cumplir con velocidad | W30: 0.025 | X30: 75 | Z30: 0.975 | AA30: 0.96482412 | AC30: ABRIL | AD30: 2026
A31: =IF(C31="","",A30+1) -> 46123 | B31: 0 | C31: 233 | D31: 0.625 | E31: 0.7625 | F31: 198 | G31: 14 | H31: 0 | I31: 75.978261 | J31: 3.3 | K31: 0 | L31: 70.606061 | M31: 75.978261 | N31: 70.606061 | O31: 0.0043 | P31: 0.034334764 | U31: 8 | V31: 1. Se registra parada por acumulaciónde de reses en desolladora debido a novedad con personal (8) 2. Se registra parada por cambio de cuchillas de cuchillo izquierdo (6) | W31: 0.070707071 | X31: 75.978261 | Z31: 0.92929293 | AA31: 1 | AC31: ABRIL | AD31: 2026
A32: =IF(C32="","",A31+1) -> 46124 | C32: 0 | AC32: ABRIL | AD32: 2026
A33: =IF(C33="","",A32+1) -> 46125 | B33: 0 | C33: 627 | D33: 0.58333333 | E33: 1.0208333 | F33: 630 | G33: 70 | H33: 60 | I33: 75.24 | J33: 10.5 | K33: 0 | L33: 66 | M33: 75.24 | N33: 59.714286 | O33: 0.0048 | P33: 0.022328549 | U33: 14 | V33: 1. Se registra parada debido a ajuste de personal (8) 2. e registra parada debido a novedad por fuga de amoniaco (44). 3.Se registra parada por novedad de impresora de identificación de canales (18) | W33: 0.11111111 | X33: 75.24 | Z33: 0.88888889 | AA33: 1 | AC33: ABRIL | AD33: 2026
A34: =IF(C34="","",A33+1) -> 46126 | B34: 0 | C34: 289 | D34: 0.58333333 | E34: 0.7875 | F34: 294 | G34: 29 | H34: 30 | I34: 73.787234 | J34: 4.9 | K34: 0 | L34: 65.681818 | M34: 73.787234 | N34: 58.979592 | O34: 0.0069 | P34: 0.038062284 | U34: 11 | V34: 1. Se registra parada sin animales en mangal (13) 2. Se registra parada por revisión y lubricacion de cuchillos neumáticos (6) 3.Se registra parada por falta de ganado en manga por novedad en bañadera (4) 4.Se registra parada por animal atascado en riel debido al péndulo que genera al subir (6). 5. Se evidencia indicador alto en cobertura grasa y piele rotas, novedad relacionada a cuchillos derecho, la cual se tuvo detener proceso para revisar y lubricar /en cuanto a velocidad tambien impacto la intermitencia de ingreso de ganado al box. | W34: 0.098639456 | X34: 75 | Z34: 0.90136054 | AA34: 0.98382979 | AC34: ABRIL | AD34: 2026
A35: =IF(C35="","",A34+1) -> 46127 | B35: 0 | C35: 483 | D35: 0.625 | E35: 0.91458333 | F35: 417 | G35: 46 | H35: 30 | I35: 84.985337 | J35: 6.95 | K35: 0 | L35: 74.883721 | M35: 84.985337 | N35: 69.496403 | O35: 0.0202 | P35: 0.01863354 | U35: 9 | V35: 1. Se registra parada sin animales en manga de ingreso a box (17) 2.Se registra parada para despejar acumulación de canales en fin de linea (5). 3. Se registra parada por lamina suelta de compuerta de descarga box (10). 4. Se registra parada por acumulación de canales en sierra canal debido a cambio de cinta (5) 5. Se registra parada por apartado, liberación y lavado de reses adicionales (9) 6. Se presentan desviaciones de proceso relacionada a los puestos anudado de esogafos y corte de esternon, debido a poca rotacion por el alto % de ausentismo | W35: 0.11031175 | X35: 84.985337 | Z35: 0.88968825 | AA35: 1 | AC35: ABRIL | AD35: 2026
A36: =IF(C36="","",A35+1) -> 46128 | B36: 0 | C36: 688 | D36: 0.58333333 | E36: 1.0583333 | F36: 684 | G36: 99 | H36: 65 | I36: 79.384615 | J36: 11.4 | K36: 0 | L36: 66.688207 | M36: 79.384615 | N36: 60.350877 | O36: 0.007 | P36: 0.018895349 | U36: 13 | V36: 1. Se registra parada debido a novedad con los dos tábanos que dejaron de funcionar y los animales no ingresaban a manga ingreso box (25) 2.Se registra parada debido a acumulación de canales por recambio de brazalestes por novedad de impresora (26). 3.Se registra parada por animal caído en manga ingreso a box (10) 4.Se registra parada por animal atascado en el riel de Izado, no encarra correctamente en el riel debido al péndulo que se genera al subir. (4) 5.Se registra parada por ajuste de personal. (3) 6.Se registra parada por acumulación de canales debido a la verificación de canales de cliente Olímpica con reporte de hallazgos (13) 7.Se registra parada por res caída en manga (10) 8.Se registra parada por res acalambrada en manga de ingreso corrales (8) | W36: 0.14473684 | X36: 79.384615 | Z36: 0.85526316 | AA36: 1 | AC36: ABRIL | AD36: 2026
A37: =IF(C37="","",A36+1) -> 46129 | B37: 0 | C37: 573 | D37: 0.58333333 | E37: 0.95763889 | F37: 539 | G37: 54 | H37: 30 | I37: 75.56044 | J37: 8.9833333 | K37: 0 | L37: 67.544204 | M37: 75.56044 | N37: 63.784787 | O37: 0.0039 | P37: 0.012216405 | U37: 7 | V37: 1. Se registra parada debido a guaya de freno manual de desolladora se sale de polea (6) 2.Se registra parada por el cambio de guaya en mal estaso de freno Manual de desolladora (8). 3. Se registra parada sin animales en la manga debido a corrales no tenía información de reses planilladas adicionales (10). 4.Se registra parada por 12 animales adicionales que no fueron apartados en corrales (30) | W37: 0.10018553 | X37: 75.56044 | Z37: 0.89981447 | AA37: 1 | AC37: ABRIL | AD37: 2026
A38: =IF(C38="","",A37+1) -> 46130 | B38: 0 | C38: 292 | D38: 0.625 | E38: 0.79861111 | F38: 250 | G38: =15+4+4 -> 23 | H38: 0 | I38: 77.180617 | J38: 4.1666667 | K38: 0 | L38: 70.08 | M38: 77.180617 | N38: 70.08 | O38: 0.0052 | P38: 0.017123288 | U38: 5 | V38: 1. Se registra parada por animal caído en manga (4) 2.Se registra parada debido animales volteados en manga ingreso corrales (4). 3. Se registra parada debido a revision y cambio de contactos de control de transferencia #1 (15). 4. Se evidencia impacto en indicador de corte en piernas asociado a la poca rotacion del personal por el alto % de ausentismo. | W38: 0.092 | X38: 77.180617 | Z38: 0.908 | AA38: 1 | AC38: ABRIL | AD38: 2026
A39: =IF(C39="","",A38+1) -> 46131 | C39: 0 | AC39: ABRIL | AD39: 2026
A40: =IF(C40="","",A39+1) -> 46132 | B40: 0 | C40: 610 | D40: 0.625 | E40: 1.0388889 | F40: 596 | G40: 84 | H40: 60 | I40: 80.973451 | J40: 9.9333333 | K40: 0 | L40: 68.283582 | M40: 80.973451 | N40: 61.409396 | O40: 0.0095 | P40: 0.013114754 | U40: 8 | V40: 1. Se registra parada debido a rompimiento de una de las manguera de tijeras neumática # 2 (27) 2.Se registra parada por acumulación de canales en zona limpia debido a paso de cliente institucional (5). 3. Se registra parada debido animal enredado en cadena de compuerta de manga ingreso corrale (37). 4.Se registra parada debido a gualla de freno manual de eviscerado de blanca que se sale de perro. (5) 5.Se registra parada debido a soldadura de compuerta de apretamiento de box (5) 6.Se registra parada debido a cilindro de box que se suelta (5) | W40: 0.1409396 | X40: 80.973451 | Z40: 0.8590604 | AA40: 1 | AC40: ABRIL | AD40: 2026
A41: =IF(C41="","",A40+1) -> 46133 | B41: 0 | C41: 496 | D41: 0.58333333 | E41: 0.89861111 | F41: 454 | G41: 18 | H41: 30 | I41: 73.300493 | J41: 7.5666667 | K41: 0 | L41: 70.188679 | M41: 73.300493 | N41: 65.550661 | O41: 0.0106 | P41: 0.026209677 | U41: 13 | V41: 1. Se registra parada por animal caído en manga ingreso a box (7) 2.Se registra parada debido a acumulación de canales por recambio de brazalestes por novedad de sirt. (11) 3. Se evidencia desminucion de velocidad debido a la limpieza y verificacion de canales institucionales. (colbeef. manzanares,olimpica). 4. Se evidencia el ingreso de mucho ganado sucio desde el inicio impactanto indicador de tolerancia cero. | W41: 0.039647577 | X41: 75 | Z41: 0.96035242 | AA41: 0.9773399 | AC41: ABRIL | AD41: 2026
A42: =IF(C42="","",A41+1) -> 46134 | B42: 0 | C42: 441 | D42: 0.625 | E42: 0.90069444 | F42: 397 | G42: 36 | H42: 30 | I42: 79.939577 | J42: 6.6166667 | K42: 0 | L42: 72.098093 | M42: 79.939577 | N42: 66.649874 | O42: 0.0113 | P42: 0.022675737 | U42: 10 | V42: 1. Se registra parada por novedad con impresora de identificación de canales (30) 2.Se registra parada debido animal que se sale vivo de box. (6) 3. Se evidencia impacto en indicador de sobrebarrigas rotas asociado a cansancio de personal y poca rotacion de zapata | W42: 0.090680101 | X42: 79.939577 | Z42: 0.9093199 | AA42: 1 | AC42: ABRIL | AD42: 2026
A43: =IF(C43="","",A42+1) -> 46135 | B43: 0 | C43: 496 | D43: 0.58333333 | E43: 0.88125 | F43: 429 | G43: 8 | H43: 30 | I43: 76.112532 | J43: 7.15 | K43: 0 | L43: 74.586466 | M43: 76.112532 | N43: 69.370629 | O43: 0.0061 | P43: 0.022177419 | U43: 11 | V43: 1. Se registra parada debido a cambio de sierra pecho y ajuste de cableado (8) 2. Se presenta accidente de trabajo al operario luis mantilla de linea debido al momento de cerrar compuerta de manga res le abre la compuerta causandole torciion de muneca | W43: 0.018648019 | X43: 76.112532 | Z43: 0.98135198 | AA43: 1 | AC43: ABRIL | AD43: 2026
A44: =IF(C44="","",A43+1) -> 46136 | B44: 0 | C44: 407 | D44: 0.625 | E44: 0.87361111 | F44: 358 | G44: 14 | H44: 30 | I44: 77.770701 | J44: 5.9666667 | K44: 0 | L44: 74.45122 | M44: 77.770701 | N44: 68.212291 | O44: 0.008 | P44: 0.034398034 | U44: 14 | V44: 1. e registra parada debido a cambio guaya de freno Manual de desolladora (14) 2. se evidencia impacto en pieles rotas asociado a personal sin rotacion por el ato % de ausentismo | W44: 0.039106145 | X44: 77.770701 | Z44: 0.96089385 | AA44: 1 | AC44: ABRIL | AD44: 2026
A45: =IF(C45="","",A44+1) -> 46137 | B45: 0 | C45: 303 | D45: 0.625 | E45: 0.81180556 | F45: 269 | G45: 0 | H45: 0 | I45: 67.583643 | J45: 4.4833333 | K45: 0 | L45: 67.583643 | M45: 67.583643 | N45: 67.583643 | O45: 0.0066 | P45: 0.02310231 | U45: 7 | V45: 1. Se evidencia disminucion de celocidad debido a paso de animales de olimpica, colbeef y mas por menos igualmente se tenia personal en entrenamiento en picado | W45: 0 | X45: 75 | Z45: 1 | AA45: 0.90111524 | AC45: ABRIL | AD45: 2026
A46: =IF(C46="","",A45+1) -> 46138 | C46: 0 | AC46: ABRIL | AD46: 2026
A47: =IF(C47="","",A46+1) -> 46139 | B47: 0 | C47: 452 | D47: 0.58333333 | E47: 0.84930556 | F47: 383 | G47: 8 | H47: 30 | I47: 78.608696 | J47: 6.3833333 | K47: 0 | L47: 76.827195 | M47: 78.608696 | N47: 70.809399 | O47: 0.0039 | P47: 0.019911504 | U47: 9 | V47: 1. Buenas tarde se registra parada debido a racor que se parte en cilindro nuevo tanque cañón de pieles (8) | W47: 0.020887728 | X47: 78.608696 | Z47: 0.97911227 | AA47: 1 | AC47: ABRIL | AD47: 2026
A48: =IF(C48="","",A47+1) -> 46140 | B48: 0 | C48: 557 | D48: 0.58333333 | E48: 0.93611111 | F48: 508 | G48: 8 | H48: 30 | I48: 71.106383 | J48: 8.4666667 | K48: 0 | L48: 69.916318 | M48: 71.106383 | N48: 65.787402 | O48: 0.0089 | P48: 0.028725314 | U48: 16 | V48: 1. Se registra parada por animal atascado en el riel de Izado, no encarra correctamente en el riel debido al péndulo que se genera al subir. (8) 2. Se evidencia reduccion de velocidad debido a personal en entrenamiento y el paso de ganado institucional. | W48: 0.015748031 | X48: 75 | Z48: 0.98425197 | AA48: 0.94808511 | AC48: ABRIL | AD48: 2026
A49: =IF(C49="","",A48+1) -> 46141 | B49: 0 | C49: 454 | D49: 0.58333333 | E49: 0.87222222 | F49: 416 | G49: 23 | H49: 30 | I49: 75.041322 | J49: 6.9333333 | K49: 0 | L49: 70.569948 | M49: 75.041322 | N49: 65.480769 | O49: 0.0111 | P49: 0.030837004 | U49: 14 | V49: 1. Se registra parada para ajuste de personal (5) 2. Se registra parada por animal atascado en el riel de Izado, no encarra correctamente en el riel debido al péndulo que se genera al subir( 5) 3. Se registra tardanza en inicio de parada programada debido a novedad con impresora de marcación de canales(7) 4. Se registra parada debido dos animales que ingresa volteado a manga de ingreso a box (6). 5. Se evidencia impacto en indicadores de tolerancia y pieles a asociado a personal en entrenamiento. | W49: 0.055288462 | X49: 75.041322 | Z49: 0.94471154 | AA49: 1 | AC49: ABRIL | AD49: 2026
A50: =IF(C50="","",A49+1) -> 46142 | B50: 0 | C50: 418 | D50: 0.58333333 | E50: 0.86388889 | F50: 404 | G50: =9+12+5+5+13 -> 44 | H50: 30 | I50: 76 | J50: 6.7333333 | K50: 0 | L50: 67.058824 | M50: 76 | N50: 62.079208 | O50: 0.0066 | P50: 0.033492823 | U50: 14 | V50: 1. Se registra parada debído a ajuste de personal (9) 2. Se registra parada debido a cambio de cuchillo neumático izquierdo (12) 3. Se registra parada por falta de poleas (23) | W50: 0.10891089 | X50: 76 | Z50: 0.89108911 | AA50: 1 | AC50: ABRIL | AD50: 2026
A51: =IF(C51="","",A50+1) -> 46143 | B51: 0.83814338 | C51: 325 | D51: 0.625 | E51: 0.83472222 | F51: 302 | G51: 45 | H51: 0 | I51: 75.875486 | J51: 5.0333333 | K51: 0 | L51: 64.569536 | M51: 75.875486 | N51: 64.569536 | O51: 0.01 | P51: 0.015384615 | Q51: 0.0043 | R51: 0 | S51: 0.0108 | T51: 0 | U51: 5 | V51: 1. Se registra parada debido al desplome de plataforma de sierra canal (45) | W51: 0.14900662 | X51: 75.875486 | Y51: 0.0151 | Z51: 0.85099338 | AA51: 1 | AB51: 0.9849 | AC51: MAYO | AD51: 2026
A52: =IF(C52="","",A51+1) -> 46144 | B52: 0.92479541 | C52: 328 | D52: 0.625 | E52: 0.81875 | F52: 279 | G52: 0 | H52: 0 | I52: 70.537634 | J52: 4.65 | K52: 0 | L52: 70.537634 | M52: 70.537634 | N52: 70.537634 | O52: 0.0084 | P52: 0.015243902 | Q52: 0.0061 | R52: 0.003 | S52: 0.0061 | T52: 0.0015 | U52: 5 | V52: 1. Evidencia desminucion de velocidad debido a verificacion de 117 canales de olimpica que pasaron al final. | W52: 0 | X52: 75 | Y52: 0.0167 | Z52: 1 | AA52: 0.94050179 | AB52: 0.9833 | AC52: MAYO | AD52: 2026
A53: =IF(C53="","",A52+1) -> 46145 | C53: 0 | AC53: MAYO | AD53: 2026
A54: =IF(C54="","",A53+1) -> 46146 | B54: 0.88559529 | C54: 617 | D54: 0.58333333 | E54: 0.98333333 | F54: 576 | G54: 39 | H54: 30 | I54: 73.017751 | J54: 9.6 | K54: 0 | L54: 67.802198 | M54: 73.017751 | N54: 64.270833 | O54: 0.0085 | P54: 0.022690438 | Q54: 0.0008 | R54: 0.0154 | S54: 0.0065 | T54: 0.0016 | U54: 14 | V54: 1. Se registra parada por novedad con válvula de tanque cañón de pieles (6) 2.Se registra parada debido a gualla de freno manual de Zapata que se suelta.(8) 3.Se registra parada debido a varias reses volteadas en manga de ingreso a box (7) 4.Se registra parada por ajuste de personal (9) 5.Se registra parada debido animal caído en manga ingreso a box (9) 6. Se evidencia desminucion de velocidad debido a agotamiento de personal por jornada extensa | W54: 0.067708333 | X54: 75 | Y54: 0.0243 | Z54: 0.93229167 | AA54: 0.97357002 | AB54: 0.9757 | AC54: MAYO | AD54: 2026
A55: =IF(C55="","",A54+1) -> 46147 | B55: 0.96797297 | C55: 533 | D55: 0.58333333 | E55: 0.91736111 | F55: 481 | G55: 6 | H55: 60 | I55: 77.060241 | J55: 8.0166667 | K55: 0 | L55: 75.961995 | M55: 77.060241 | N55: 66.486486 | O55: 0.0066 | P55: 0.015009381 | Q55: 0.0066 | R55: 0.0038 | S55: 0.0094 | T55: 0 | U55: 8 | V55: 1. Se registra parada sin animales en manga ingreso a box(6) | W55: 0.012474012 | X55: 77.060241 | Y55: 0.0198 | Z55: 0.98752599 | AA55: 1 | AB55: 0.9802 | AC55: MAYO | AD55: 2026
A56: =IF(C56="","",A55+1) -> 46148 | B56: 0.9208535 | C56: 362 | D56: 0.67638889 | E56: 0.91319444 | F56: 341 | G56: 0 | H56: 30 | I56: 69.839228 | J56: 5.6833333 | K56: 64 | L56: 69.839228 | M56: 69.839228 | N56: 63.695015 | O56: 0.0063 | P56: 0.013812155 | Q56: 0.0028 | R56: 0.0014 | S56: 0.0069 | T56: 0 | U56: 5 | V56: 1. Se presenta tardanza de inicio debido a falla con intenet al cierre de operacion no se habia restablecido, se trabajo local. 2. Se evidencia desminucion en velocidad debido a personal en entremaniento en los puestos (corte de manos, picado, y deguello) | W56: 0 | X56: 75 | Y56: 0.0111 | Z56: 1 | AA56: 0.93118971 | AB56: 0.9889 | AC56: MAYO | AD56: 2026
A57: =IF(C57="","",A56+1) -> 46149 | B57: 0.96337107 | C57: 563 | D57: 0.625 | E57: 0.95625 | F57: 477 | G57: 10 | H57: 35 | I57: 78.194444 | J57: 7.95 | K57: 0 | L57: 76.425339 | M57: 78.194444 | N57: 70.81761 | O57: 0.0053 | P57: 0.026642984 | Q57: 0.0018 | R57: 0.008 | S57: 0.0062 | T57: 0 | U57: 15 | V57: 1. Se registra parada por animal atascado en el riel de Izado, no encarra correctamente en el riel debido al péndulo que se genera al subir (5) 2. Se registra parada sin animales para continuar proceso (5) | W57: 0.020964361 | X57: 78.194444 | Y57: 0.016 | Z57: 0.97903564 | AA57: 1 | AB57: 0.984 | AC57: MAYO | AD57: 2026
A58: =IF(C58="","",A57+1) -> 46150 | B58: 0.84904639 | C58: 485 | D58: 0.67013889 | E58: 1.0069444 | F58: 485 | G58: 68 | H58: 30 | I58: 75.193798 | J58: 8.0833333 | K58: 125 | L58: 63.956044 | M58: 75.193798 | N58: 60 | O58: 0.0098 | P58: 0.01443299 | Q58: 0.0052 | R58: 0 | S58: 0.0052 | T58: 0.0021 | U58: 7 | V58: 1. Se registra Tardanza de inicio debido a taponamiento linea de drenajes de cava, zona intermedia y patas (125) 2. Se registra parada por novedad en cuchillo derecho y se realiza cambio (13) 3.Se registra parada por animal atascado en el riel de Izado, no encarra correctamente en el riel debido al péndulo que se genera al subir. (9) 4.Se registra parada debido a novedad con indicador de báscula pesaje fin de linea (memoria llena) técnico se demora en dar solución a la novedad (28) 5.Se registra parada debido animal caído en manga ingreso a box (18) | W58: 0.14020619 | X58: 75.193798 | Y58: 0.0125 | Z58: 0.85979381 | AA58: 1 | AB58: 0.9875 | AC58: MAYO | AD58: 2026
A59: =IF(C59="","",A58+1) -> 46151 | B59: 0.89996133 | C59: 377 | D59: 0.625 | E59: 0.87291667 | F59: 357 | G59: 14 | H59: 30 | I59: 72.268371 | J59: 5.95 | K59: 0 | L59: 69.174312 | M59: 72.268371 | N59: 63.361345 | O59: 0.0173 | P59: 0.021220159 | Q59: 0.0066 | R59: 0 | S59: 0.0186 | T59: 0.0027 | U59: 8 | V59: 1. Se registra parada debido animal atascado en box (14) 2. Se evidencia impacto en indicador de tolerancia cero asociado a personal en entrenamiento (picado, anudado de esofago) 3. Se evidencia reduccion de velocidad debido al paso de clientes institucionales y bufalos (olimpica, colbeef) | W59: 0.039215686 | X59: 75 | Y59: 0.0279 | Z59: 0.96078431 | AA59: 0.96357827 | AB59: 0.9721 | AC59: MAYO | AD59: 2026
A60: =IF(C60="","",A59+1) -> 46152 | C60: 0 | AC60: MAYO | AD60: 2026
A61: =IF(C61="","",A60+1) -> 46153 | B61: 0.93775471 | C61: 690 | D61: 0.58333333 | E61: 1.0034722 | F61: 605 | G61: 31 | H61: 60 | I61: 80.544747 | J61: 10.083333 | K61: 0 | L61: 75.963303 | M61: 80.544747 | N61: 68.429752 | O61: 0.0105 | P61: 0.013043478 | Q61: 0.0043 | R61: 0.0051 | S61: 0.0022 | T61: 0 | U61: 9 | V61: 1.Se registra parada debido a ajuste de personal (10) 2.Se registra parada por animal atascado en box (6) 3. Se registra parada debido a novedad en box (racor partido) (5) 4. Se registra parada debido a novedad con la unidad neumática de cuchillo izquierdo (10) 5. Se evidencia impacto en indicador de tolerancia cero asociado a personal en entrenamiento (anudado de esofago) | W61: 0.051239669 | X61: 80.544747 | Y61: 0.0116 | Z61: 0.94876033 | AA61: 1 | AB61: 0.9884 | AC61: MAYO | AD61: 2026
A62: =IF(C62="","",A61+1) -> 46154 | B62: 0.87454232 | C62: 622 | D62: 0.58333333 | E62: 0.99027778 | F62: 586 | G62: 60 | H62: 60 | I62: 80.085837 | J62: 9.7666667 | K62: 0 | L62: 70.95057 | M62: 80.085837 | N62: 63.686007 | O62: 0.0096 | P62: 0.028938907 | Q62: 0.0064 | R62: 0.0048 | S62: 0.0129 | T62: 0.0016 | U62: 18 | V62: 1.Se registra parada debido a ajuste de personal (7) 2.Se registra parada por acumulación de canales debido a la verificación de canales de cliente inversiones zuluaga con reporte de hallazgos (16) 3.Se registra parada por acumulación de canales en fin de linea debido a vefirificacion de cliente olímpica (20) 4.Se registra parada debido a la novedad con plataforma de limpieza superior (una de la guayas destempleada) (17) | W62: 0.10238908 | X62: 80.085837 | Y62: 0.0257 | Z62: 0.89761092 | AA62: 1 | AB62: 0.9743 | AC62: MAYO | AD62: 2026
A63: =IF(C63="","",A62+1) -> 46155 | B63: 0.9370613 | C63: 368 | D63: 0.625 | E63: 0.86111111 | F63: 340 | G63: 6 | H63: 30 | I63: 72.631579 | J63: 5.6666667 | K63: 0 | L63: 71.225806 | M63: 72.631579 | N63: 64.941176 | O63: 0.0096 | P63: 0.029891304 | Q63: 0.0027 | R63: 0.0014 | S63: 0.0082 | T63: 0.0027 | U63: 11 | V63: 1. Se presenta parada por ajuste de personal (6) | W63: 0.017647059 | X63: 75 | Y63: 0.015 | Z63: 0.98235294 | AA63: 0.96842105 | AB63: 0.985 | AC63: MAYO | AD63: 2026
A64: =IF(C64="","",A63+1) -> 46156 | B64: 0.92893132 | C64: 543 | D64: 0.58333333 | E64: 0.89375 | F64: 447 | G64: 26 | H64: 30 | I64: 83.324808 | J64: 7.45 | K64: 0 | L64: 78.129496 | M64: 83.324808 | N64: 72.885906 | O64: 0.0041 | P64: 0.022099448 | Q64: 0.0018 | R64: 0.0055 | S64: 0.0064 | T64: 0 | U64: 12 | V64: 1. Se registra parada por animal atascado en el riel de Izado, no encarra correctamente en el riel debido al péndulo que se genera al subir.(20) 2. Se registra parada por un animal faltante para finalizar el proceso (6) | W64: 0.058165548 | X64: 83.324808 | Y64: 0.0137 | Z64: 0.94183445 | AA64: 1 | AB64: 0.9863 | AC64: MAYO | AD64: 2026
A65: =IF(C65="","",A64+1) -> 46157 | B65: 0.77069079 | C65: 583 | D65: 0.58333333 | E65: 1.0131944 | F65: 619 | G65: 133 | H65: 30 | I65: 76.710526 | J65: 10.316667 | K65: 0 | L65: 59.388795 | M65: 76.710526 | N65: 56.510501 | O65: 0.009 | P65: 0.018867925 | Q65: 0.0043 | R65: 0.0051 | S65: 0.009 | T65: 0 | U65: 11 | V65: 1.Se registra parada debido a rutura de tubería de bomba lavado de canales.(126) 2.Se registra parada debido a animal caído en manga ingreso box (7) | W65: 0.21486268 | X65: 76.710526 | Y65: 0.0184 | Z65: 0.78513732 | AA65: 1 | AB65: 0.9816 | AC65: MAYO | AD65: 2026
A66: =IF(C66="","",A65+1) -> 46158 | B66: 0.90772407 | C66: 386 | D66: 0.625 | E66: 0.87777778 | F66: 364 | G66: 0 | H66: 30 | I66: 69.341317 | J66: 6.0666667 | K66: 0 | L66: 69.341317 | M66: 69.341317 | N66: 63.626374 | O66: 0.0058 | P66: 0.018134715 | Q66: 0.0065 | R66: 0.0078 | S66: 0.0039 | T66: 0 | U66: 7 | V66: 1. Se evidencia desminucion de velocidad debido a paso de clientes institucionales ( cyc, olimpica, colbeef )adicional se tenia personal en entrenamiento (desuello mecanico, corte de manos, eviscerado de blanca) | W66: 0 | X66: 75 | Y66: 0.0182 | Z66: 1 | AA66: 0.9245509 | AB66: 0.9818 | AC66: MAYO | AD66: 2026
A67: =IF(C67="","",A66+1) -> 46159 | C67: 0 | AC67: MAYO | AD67: 2026
A68: =IF(C68="","",A67+1) -> 46160 | B68: 0.9591279 | C68: 710 | D68: 0.54166667 | E68: 0.98472222 | F68: 638 | G68: 16 | H68: 60 | I68: 75.800712 | J68: 10.633333 | K68: 0 | L68: 73.702422 | M68: 75.800712 | N68: 66.77116 | O68: 0.0036 | P68: 0.014084507 | Q68: 0.0028 | R68: 0.0021 | S68: 0.0106 | T68: 0.0007 | U68: 10 | V68: 1. Se registra parada sin agua en planta benéficio (8) 2.Se registra parada por animal ( búfalo ) volteado en manga ingreso (8) | W68: 0.02507837 | X68: 75.800712 | Y68: 0.0162 | Z68: 0.97492163 | AA68: 1 | AB68: 0.9838 | AC68: MAYO | AD68: 2026
A69: =IF(C69="","",A68+1) -> 46161 | B69: 0.89529663 | C69: 441 | D69: 0.625 | E69: 0.91388889 | F69: 416 | G69: 38 | H69: 30 | I69: 76.034483 | J69: 6.9333333 | K69: 0 | L69: 68.549223 | M69: 76.034483 | N69: 63.605769 | O69: 0.0051 | P69: 0.01814059 | Q69: 0.0011 | R69: 0.0125 | S69: 0.0011 | T69: 0 | U69: 8 | V69: 1. Se registra parada por tiempo de ayuno de ultimos animales planillados (38) 2. Se evidencia impacto en indicador de sobrebarrigas rota asociado a entrenamiento en zapata derecha. | W69: 0.091346154 | X69: 76.034483 | Y69: 0.0147 | Z69: 0.90865385 | AA69: 1 | AB69: 0.9853 | AC69: MAYO | AD69: 2026
A70: =IF(C70="","",A69+1) -> 46162 | B70: 0.9141172 | C70: 477 | D70: 0.625 | E70: 0.93263889 | F70: 443 | G70: 23 | H70: 30 | I70: 73.384615 | J70: 7.3833333 | K70: 0 | L70: 69.297821 | M70: 73.384615 | N70: 64.604966 | O70: 0.0084 | P70: 0.020964361 | Q70: 0.0031 | R70: 0.0031 | S70: 0.0063 | T70: 0.0021 | U70: 10 | V70: 1. Se registra parada por animal se cae en primera plataforma debido a daño de polea (5) 2.Se registra parada para ajustes de los 2 contrapesos de tijeras neumáticas debido a que estaban dura para bajar y subir (8) 3.Se registra parada debido a cambio de sierra pecho por novedad con equipo titular (5) | W70: 0.051918736 | X70: 75 | Y70: 0.0146 | Z70: 0.94808126 | AA70: 0.97846154 | AB70: 0.9854 | AC70: MAYO | AD70: 2026
A71: =IF(C71="","",A70+1) -> 46163 | B71: 0.88967763 | C71: 484 | D71: 0.58333333 | E71: 0.8875 | F71: 438 | G71: 32 | H71: 30 | I71: 77.234043 | J71: 7.3 | K71: 0 | L71: 71.176471 | M71: 77.234043 | N71: 66.30137 | O71: 0.0082 | P71: 0.020661157 | Q71: 0.001 | R71: 0.0124 | S71: 0.0258 | T71: 0.001 | U71: 10 | V71: 1. Se registra parada debido a novedad con control de transferencia 1 (19) 2.Se registra parada debido a animal caído en manga de box (7) 3.Se registra parada debido animal que ingresa volteado en la manga ingreso al box (6) 4. Se evidencia impacto en sobrebarriga rotas asociado a personal sin descanso. | W71: 0.073059361 | X71: 77.234043 | Y71: 0.0402 | Z71: 0.92694064 | AA71: 1 | AB71: 0.9598 | AC71: MAYO | AD71: 2026
A72: =IF(C72="","",A71+1) -> 46164 | B72: 0.82981316 | C72: 549 | D72: 0.58333333 | E72: 0.92638889 | F72: 494 | G72: 73 | H72: 30 | I72: 84.245524 | J72: 8.2333333 | K72: 0 | L72: 70.991379 | M72: 84.245524 | N72: 66.680162 | O72: 0.0059 | P72: 0.029143898 | Q72: 0.0036 | R72: 0.0082 | S72: 0.0109 | T72: 0.0036 | U72: 16 | V72: 1.Se registra parada debido a compuerta que se cae en box de noqueo (19) 2.Se registra parada por acumulación de canales en fin de línea debido a verificación de canales de clientes olímpica (8) 3.Se registra parada debido cadera de la desolladora que se rompe (46) 4. Se cito personal 13:00 para capacitacion (seguridad vial) | W72: 0.14777328 | X72: 84.245524 | Y72: 0.0263 | Z72: 0.85222672 | AA72: 1 | AB72: 0.9737 | AC72: MAYO | AD72: 2026
A73: =IF(C73="","",A72+1) -> 46165 | B73: 0.93828011 | C73: 345 | D73: 0.625 | E73: 0.84791667 | F73: 321 | G73: 7 | H73: 30 | I73: 72.887324 | J73: 5.35 | K73: 0 | L73: 71.134021 | M73: 72.887324 | N73: 64.485981 | O73: 0.0058 | P73: 0.020289855 | Q73: 0.0043 | R73: 0 | S73: 0.0087 | T73: 0 | U73: 7 | V73: 1. Se registra parada debido a racores que se parten de sistema de aire del box (7) 2. Se evidencia de disminucion de velocidad debido a que se tuvo que trabajar desde las 15:00 hasta las 17:00 con pistolas de forminantes, ya que las dos pistolas de perno presentaron novedad, adicional una de las pistolas de forminantes se atasco debido a el recalentamiento por el uso contante a pesar de usarlas alternadas. | W73: 0.021806854 | X73: 75 | Y73: 0.013 | Z73: 0.97819315 | AA73: 0.97183099 | AB73: 0.987 | AC73: MAYO | AD73: 2026
A74: =IF(C74="","",A73+1) -> 46166 | C74: 0 | AC74: MAYO | AD74: 2026
A75: =IF(C75="","",A74+1) -> 46167 | B75: 0.92372713 | C75: 691 | D75: 0.54305556 | E75: 0.99097222 | F75: 645 | G75: 40 | H75: 60 | I75: 76.073394 | J75: 10.75 | K75: 2 | L75: 70.871795 | M75: 76.073394 | N75: 64.27907 | O75: 0.0055 | P75: 0.02170767 | Q75: 0.0007 | R75: 0.0065 | S75: 0.008 | T75: 0 | U75: 15 | V75: 1. Se registra para debido ajuste de personal (6) 2.Se registra parada por animal caído en manga de ingreso a box (15) 3.Se registra parada debido pin que se sale de cilindro de compuerta de descarga del box (14) 4.Se registra parada debido a novedad con cuchillo neumático izquierdo (unidad se le soltó el reservorio de aceite y manguera de sucion) (5) 5. Se desminuye velocidad al incio de proceso debido al benefico y verificacion de canales de cliente olimpica. | W75: 0.062015504 | X75: 76.073394 | Y75: 0.0152 | Z75: 0.9379845 | AA75: 1 | AB75: 0.9848 | AC75: MAYO | AD75: 2026
A76: =IF(C76="","",A75+1) -> 46168 | B76: 0.79468526 | C76: 455 | D76: 0.58333333 | E76: 0.90833333 | F76: 468 | G76: 89 | H76: 35 | I76: 79.360465 | J76: 7.8 | K76: 0 | L76: 63.048499 | M76: 79.360465 | N76: 58.333333 | O76: 0.0088 | P76: 0.030769231 | Q76: 0.0022 | R76: 0.0022 | S76: 0.0143 | T76: 0 | U76: 14 | V76: 1.Se registra parada debido a ajuste de personal (19) 2.Se registra parada debido a que el lander de izado se bloquea (12) 3.Se registra parada debido animal atascado en manga ingreso al box (12) 4.Se registra parada debido a tiempo de ayuno de último animales planillados (46) | W76: 0.19017094 | X76: 79.360465 | Y76: 0.0187 | Z76: 0.80982906 | AA76: 1 | AB76: 0.9813 | AC76: MAYO | AD76: 2026
A77: =IF(C77="","",A76+1) -> 46169 | B77: 0.8586 | C77: 600 | D77: 0.58333333 | E77: 0.99236111 | F77: 589 | G77: 76 | H77: 60 | I77: 79.470199 | J77: 9.8166667 | K77: 0 | L77: 68.05293 | M77: 79.470199 | N77: 61.120543 | O77: 0.0079 | P77: 0.021666667 | Q77: 0.0008 | R77: 0.0067 | S77: 0.0067 | T77: 0 | U77: 13 | V77: 1. Se registra parada debido animal atascado en box (11) 2.Se registra parada debido caída de animal que se le revienta el tendón (9) 3. Se registra parada por acumulación de canales en fin de línea debido a verificación y cliente olímpica (23) 4.Se registra parada debido a que la chumacera de brazo de desolladora se suelta (24) 5.Se registra parada debido animal caido en manga ingreso a box (9) | W77: 0.12903226 | X77: 79.470199 | Y77: 0.0142 | Z77: 0.87096774 | AA77: 1 | AB77: 0.9858 | AC77: MAYO | AD77: 2026
A78: =IF(C78="","",A77+1) -> 46170 | B78: 0.88444931 | C78: 530 | D78: 0.70833333 | E78: 1.0604167 | F78: 507 | G78: 53 | H78: 60 | I78: 80.71066 | J78: 8.45 | K78: 0 | L78: 71.14094 | M78: 80.71066 | N78: 62.721893 | O78: 0.0104 | P78: 0.041509434 | Q78: 0.0028 | R78: 0.0038 | S78: 0.0057 | T78: 0 | U78: 22 | V78: 1.Se registra parada debido a ajuste de personal (9) 2.Se registra parada debido a la compuerta de box que se parte las soldadura y se cae (44) 3. Se evidencia impacto en indicador asociado a ingreso de ganado sucio y personal en entrenamiento en corte de esternon. | W78: 0.10453649 | X78: 80.71066 | Y78: 0.0123 | Z78: 0.89546351 | AA78: 1 | AB78: 0.9877 | AC78: MAYO | AD78: 2026
A79: =IF(C79="","",A78+1) -> 46171 | B79: 0.84674219 | C79: 522 | D79: 0.70833333 | E79: 1.1 | F79: 564 | G79: 38 | H79: 70 | I79: 68.684211 | J79: 9.4 | K79: 0 | L79: 63.40081 | M79: 68.684211 | N79: 55.531915 | O79: 0.0143 | P79: 0.019157088 | Q79: 0.0029 | R79: 0.0038 | S79: 0.0019 | T79: 0 | U79: 10 | V79: 1.Buenas noches se registra parada debido 2 animales caídos en manga ingreso al box (27) 2.Se registra parada por acumulación de canales en fin de línea debido cumplimiento de ficha técnica de clientes carnes y carnes (11) 3. Se evidencia impacto en indicador de tolerancia debido al ingreso de ganado sucio. 4. El dia de hoy se presenta indicadores de ausentismo altos en las dos areas debido a incapacidades. | W79: 0.067375887 | X79: 75 | Y79: 0.0086 | Z79: 0.93262411 | AA79: 0.91578947 | AB79: 0.9914 | AC79: MAYO | AD79: 2026
A80: =IF(C80="","",A79+1) -> 46172 | B80: 0.81574275 | C80: 318 | D80: 0.72222222 | E80: 0.93472222 | F80: 306 | G80: 0 | H80: 0 | I80: 62.352941 | J80: 5.1 | K80: 20 | L80: 62.352941 | M80: 62.352941 | N80: 62.352941 | O80: 0.0142 | P80: 0.018867925 | Q80: 0.0047 | R80: 0.0031 | S80: 0.011 | T80: 0 | U80: 6 | V80: 1. Se presenta tardanza de incio debido a novedad con indicador de bascula de piso la cual retrazo por mas de 1 hora el acondicionamiento de las 131 visceras de olimpica afectando el inicio de proceso benefico se requierio apoyo de persona de linea para no extender retrazo. 2. Se demora en pasar la ultima canal por pesaje debido al paso de canles de cliente cyc y debido al alto ausentismo no se tenia personal para aplicar ficha tecnica de cliente. 3. Se evidencia impacto en indicador de tolerancia debido al ingreso de ganado sucio | W80: 0 | X80: 75 | Y80: 0.0188 | Z80: 1 | AA80: 0.83137255 | AB80: 0.9812 | AC80: MAYO | AD80: 2026
A81: =IF(C81="","",A80+1) -> 46173 | C81: 0 | AC81: MAYO | AD81: 2026
A82: =IF(C82="","",A81+1) -> 46174 | B82: 0.85440069 | C82: 555 | D82: 0.58333333 | E82: 0.98680556 | F82: 581 | G82: 71 | H82: 60 | I82: 74 | J82: 9.6833333 | K82: 0 | L82: 63.915547 | M82: 74 | N82: 57.314974 | O82: 0.0091 | P82: 0.025225225 | Q82: 0.0045 | R82: 0.0018 | S82: 0.0045 | T82: 0.0027 | U82: 14 | V82: 1.Se registra parada por animal que ingresa volteado a box (esto debido a que no se contaba con pistola de fulminantes disponible, según Sigma 3 estaba realizando mtto a la hora se requirió traer contingencia de sala de emergencia) (6) 2.Se registra parada sin animales para continuar proceso (29) 3.Se registra parada por animal atascado en riel de izado (6) 4.Se registra parada por animal caído en manga ingreso corrales (17) 5.Se registra parada por freno Manual de sangria que se sale de polea y se queda atascado (7) 6.Se registra parada por acumulación de canales en desolladora (6) | W82: 0.1222031 | X82: 75 | Y82: 0.0135 | Z82: 0.8777969 | AA82: 0.98666667 | AB82: 0.9865 | AC82: JUNIO | AD82: 2026
A83: =IF(C83="","",A82+1) -> 46175 | B83: 0.77144015 | C83: 507 | D83: 0.58333333 | E83: 0.96458333 | F83: 549 | G83: 112 | H83: 30 | I83: 74.742015 | J83: 9.15 | K83: 0 | L83: 58.612717 | M83: 74.742015 | N83: 55.409836 | O83: 0.0064 | P83: 0.025641026 | Q83: 0.0059 | R83: 0.0039 | S83: 0.0118 | T83: 0.0059 | U83: 13 | V83: 1.Se registra parada debido a que la compuerta de descarga box se parte soldadura y se cae (17) 2. Se registra parada por acumulación de productos en área de patas debido a novedad con máquina escaladora (39) 3.Se registra parada por novedad con fuido eléctrico en área de vísceras blanca debido a un carro perchero se llevó el apagador del pasillo (56) | W83: 0.20400729 | X83: 75 | Y83: 0.0275 | Z83: 0.79599271 | AA83: 0.9965602 | AB83: 0.9725 | AC83: JUNIO | AD83: 2026
A84: =IF(C84="","",A83+1) -> 46176 | B84: 0.91774675 | C84: 561 | D84: 0.58333333 | E84: 0.93541667 | F84: 507 | G84: 35 | H84: 30 | I84: 76.153846 | J84: 8.45 | K84: 0 | L84: 70.566038 | M84: 76.153846 | N84: 66.390533 | O84: 0.0031 | P84: 0.017825312 | Q84: 0.0027 | R84: 0.0053 | S84: 0.0062 | T84: 0 | U84: 10 | V84: 1. Se registra parada debido a novedad con control de transferencia 2 (7) 2.Se registra paradas por animales que no ingresan a box debido a daños de tabano (28) | W84: 0.069033531 | X84: 76.153846 | Y84: 0.0142 | Z84: 0.93096647 | AA84: 1 | AB84: 0.9858 | AC84: JUNIO | AD84: 2026
A85: =IF(C85="","",A84+1) -> 46177 | B85: 0.9756 | C85: 617 | D85: 0.58333333 | E85: 0.92916667 | F85: 498 | G85: 0 | H85: 30 | I85: 79.102564 | J85: 8.3 | K85: 0 | L85: 79.102564 | M85: 79.102564 | N85: 74.337349 | O85: 0.0045 | P85: 0.022690438 | Q85: 0.0057 | R85: 0.0041 | S85: 0.0122 | T85: 0.0024 | U85: 14 | W85: 0 | X85: 79.102564 | Y85: 0.0244 | Z85: 1 | AA85: 1 | AB85: 0.9756 | AC85: JUNIO | AD85: 2026
A86: =IF(C86="","",A85+1) -> 46178 | B86: 0.77087087 | C86: 350 | D86: 0.625 | E86: 0.85625 | F86: 333 | G86: 31 | H86: 30 | I86: 77.205882 | J86: 5.55 | K86: 0 | L86: 69.306931 | M86: 77.205882 | N86: 63.063063 | O86: 0.0043 | P86: 0.022857143 | Q86: 0.0043 | R86: 0 | S86: 0.0057 | T86: 0.14 | U86: 8 | V86: 1.Se registra parada por transferencia 1 que se queda bloqueada (31) | W86: 0.093093093 | X86: 77.205882 | Y86: 0.15 | Z86: 0.90690691 | AA86: 1 | AB86: 0.85 | AC86: JUNIO | AD86: 2026
A87: =IF(C87="","",A86+1) -> 46179 | B87: 0.95641648 | C87: 393 | D87: 0.625 | E87: 0.87013889 | F87: 353 | G87: 6 | H87: 30 | I87: 74.384858 | J87: 5.8833333 | K87: 0 | L87: 73.003096 | M87: 74.384858 | N87: 66.798867 | O87: 0.0019 | P87: 0.061068702 | Q87: 0.0038 | R87: 0.0127 | S87: 0.0025 | T87: 0 | U87: 24 | V87: 1. Se evidencia impacto en indicador de pieles rotas y sobrebarrigas rota asociados a entrenamiento en Zapata derecha y novedad con cuchillo izquierdo 2. Se registra parada por acumulación de canales en desolladora debido a cambio de cuchillas neumáticas (6) | W87: 0.016997167 | X87: 75 | Y87: 0.019 | Z87: 0.98300283 | AA87: 0.99179811 | AB87: 0.981 | AC87: JUNIO | AD87: 2026
A88: =IF(C88="","",A87+1) -> 46180 | C88: 0 | AC88: JUNIO | AD88: 2026
A89: =IF(C89="","",A88+1) -> 46181 | B89: 0.93980841 | C89: 658 | D89: 0.54166667 | E89: 0.96944444 | F89: 616 | G89: =7+6+10 -> 23 | H89: 60 | I89: 74.071295 | J89: 10.266667 | K89: 0 | L89: 71.007194 | M89: 74.071295 | N89: 64.090909 | O89: 0.0065 | P89: 0.025835866 | Q89: 0.0008 | R89: 0.0015 | S89: 0.0084 | T89: 0.0008 | U89: 17 | V89: 1. Se registra parada por falta de agua en la línea de beneficio (7) 2. Se registra parada por animal caído en manga ingreso a box (16) | W89: 0.037337662 | X89: 75 | Y89: 0.0115 | Z89: 0.96266234 | AA89: 0.98761726 | AB89: 0.9885 | AC89: JUNIO | AD89: 2026
A90: =IF(C90="","",A89+1) -> 46182 | B90: 0.87749823 | C90: 459 | D90: 0.625 | E90: 0.93194444 | F90: 442 | G90: 36 | H90: 30 | I90: 73.244681 | J90: 7.3666667 | K90: 5 | L90: 66.84466 | M90: 73.244681 | N90: 62.307692 | O90: 0.0115 | P90: 0.026143791 | Q90: 0.0098 | R90: 0 | S90: 0.0033 | T90: 0.0087 | U90: 12 | V90: 1. Se evidencia impacto en indicador de tolerancia cero debido a el ingreso de ganado muy sucio. 2. Se registra tardaza de incio de proceso debido a sin animales en manga para iniciar. (5) 3.Se registra parada por cambio de cuchillas neumáticas debido a que no cortaban (4) 4.Se registra parada debido animal caído en manga ingreso al box (8) 5.Se registra parada sin animales para continuar proceso (9) 6.Se registra parada por freno manual primera plataforma debido a guaya que se suelta del perro (10) | W90: 0.081447964 | X90: 75 | Y90: 0.0218 | Z90: 0.91855204 | AA90: 0.97659574 | AB90: 0.9782 | AC90: JUNIO | AD90: 2026
A91: =IF(C91="","",A90+1) -> 46183 | B91: 0.92483017 | C91: 519 | D91: 0.58333333 | E91: 0.91041667 | F91: 471 | G91: 11 | H91: 30 | I91: 72.418605 | J91: 7.85 | K91: 0 | L91: 70.612245 | M91: 72.418605 | N91: 66.11465 | O91: 0.0086 | P91: 0.044315992 | Q91: 0.0029 | R91: 0.0106 | S91: 0.0058 | T91: 0 | U91: 23 | V91: 1.Se registra parada por búfalo que queda atascado en cajón (5) 2.Se registra parada por acumulación en sierra canal debido a fallo en espernancador (6) 3. Se evidencia impacto en indicador de sobrebarrigas rotas y pieles debido a entrenamiento de zapata derecha | W91: 0.023354565 | X91: 75 | Y91: 0.0193 | Z91: 0.97664544 | AA91: 0.9655814 | AB91: 0.9807 | AC91: JUNIO | AD91: 2026
A92: =IF(C92="","",A91+1) -> 46184 | B92: 0.91680446 | C92: 609 | D92: 0.58333333 | E92: 0.96875 | F92: 555 | G92: 10 | H92: 30 | I92: 70.951456 | J92: 9.25 | K92: 0 | L92: 69.6 | M92: 70.951456 | N92: 65.837838 | O92: 0.007 | P92: 0.019704433 | Q92: 0.0057 | R92: 0.0033 | S92: 0.0041 | T92: 0 | U92: 12 | V92: 1.Se registra parada por desensor de grilletes (5) 2.Se registra parada por animal que se caen de transferencia 1 (5) 3, Se evidencia no cumpliento de velocidad debido a la desminucion de velocidad por el paso de cliente olimpica. | W92: 0.018018018 | X92: 75 | Y92: 0.0131 | Z92: 0.98198198 | AA92: 0.94601942 | AB92: 0.9869 | AC92: JUNIO | AD92: 2026
A93: =IF(C93="","",A92+1) -> 46185 | B93: 0.97847794 | C93: 411 | D93: 0.625 | E93: 0.86736111 | F93: 349 | G93: 5 | H93: 30 | I93: 78.535032 | J93: 5.8166667 | K93: 0 | L93: 77.304075 | M93: 78.535032 | N93: 70.659026 | O93: 0.0042 | P93: 0.0243309 | Q93: 0.0049 | R93: 0 | S93: 0.0024 | T93: 0 | U93: 10 | V93: 1.Se registra parada por acumulación de canales en sierra canal debido a novedad con espernancador (5) | W93: 0.014326648 | X93: 78.535032 | Y93: 0.0073 | Z93: 0.98567335 | AA93: 1 | AB93: 0.9927 | AC93: JUNIO | AD93: 2026
A94: =IF(C94="","",A93+1) -> 46186 | B94: 0.92279595 | C94: 367 | D94: 0.625 | E94: 0.84444444 | F94: 316 | G94: 13 | H94: 0 | I94: 72.673267 | J94: 5.2666667 | K94: 0 | L94: 69.683544 | M94: 72.673267 | N94: 69.683544 | O94: 0.0076 | P94: 0.054495913 | Q94: 0 | R94: 0.0054 | S94: 0.0014 | T94: 0 | U94: 20 | V94: 1.Se registra parada por ajuste de personal (5) 2.Se registra parada por acumulación en Zapata debido a novedad con operario ZD (8) 3, Se evidencia impacto en indicador de pieles rotas debido a entrenamiento en ZD. | W94: 0.041139241 | X94: 75 | Y94: 0.0068 | Z94: 0.95886076 | AA94: 0.9689769 | AB94: 0.9932 | AC94: JUNIO | AD94: 2026
A95: =IF(C95="","",A94+1) -> 46187 | C95: 0 | AC95: JUNIO | AD95: 2026
A96: =IF(C96="","",A95+1) -> 46188 | B96: 0.89997942 | C96: 607 | D96: 0.54166667 | E96: 0.95416667 | F96: 594 | G96: 15 | H96: 60 | I96: 70.17341 | J96: 9.9 | K96: 0 | L96: 68.202247 | M96: 70.17341 | N96: 61.313131 | O96: 0.0063 | P96: 0.019769357 | Q96: 0.0025 | R96: 0.0041 | S96: 0.0058 | T96: 0.0008 | U96: 12 | V96: 1. Se registra parada por novedad con control transferencia 1 (cambios de contactos averiados) y novedad con freno manual de desuello primera pierna (soporte de gualla se cae) (15) 2. Se baja velocidad debido a la paso de 72 canales de cliente olimpica la cual impacta indicador de velocidad. | W96: 0.025252525 | X96: 75 | Y96: 0.0132 | Z96: 0.97474747 | AA96: 0.93564547 | AB96: 0.9868 | AC96: JUNIO | AD96: 2026
A97: =IF(C97="","",A96+1) -> 46189 | B97: 0.89955876 | C97: 492 | D97: 0.58333333 | E97: 0.90625 | F97: 465 | G97: 39 | H97: 30 | I97: 74.545455 | J97: 7.75 | K97: 0 | L97: 67.862069 | M97: 74.545455 | N97: 63.483871 | O97: 0.0229 | P97: 0.042682927 | Q97: 0.0071 | R97: 0.003 | S97: 0.002 | T97: 0 | U97: 21 | V97: 1. Se registra parada por cambio de gualla de sierra canal debido a desilache de gualla (34) 2.Se registra parada sin animales para continuar proceso (5) 3. Se evidencia impacto en indicador de tolerancia cero debido al ingreso de gando sucio todo el proceso. 4. Se evidencia impacto en indicador de piele rotas debido a entrenamiento en desuello costal profundo derecho. | W97: 0.083870968 | X97: 75 | Y97: 0.0121 | Z97: 0.91612903 | AA97: 0.99393939 | AB97: 0.9879 | AC97: JUNIO | AD97: 2026
A98: =IF(C98="","",A97+1) -> 46190 | B98: 0.848392 | C98: 417 | D98: 0.625 | E98: 0.90277778 | F98: 400 | G98: =13+28+13 -> 54 | H98: 30 | I98: 79.177215 | J98: 6.6666667 | K98: 0 | L98: 67.621622 | M98: 79.177215 | N98: 62.55 | O98: 0.012 | P98: 0.016786571 | Q98: 0.0048 | R98: 0.0012 | S98: 0.012 | T98: 0.0012 | U98: 7 | V98: 1. Se registra parada por acumulación de canales en fin de línea debido a novedad con pistola de ácido láctico (13) 2.Se registra parada por falla en fuido eléctrico (28) 3. Se registra parada por novedad con protección de equipos Izado, transferencia 1 y 2, máquina de libros y Pandos (13) 4. Se evidencia impacto en indicar de tolerancia cero debido a personal en entrenamiento en eviscerado de blanca. | W98: 0.135 | X98: 79.177215 | Y98: 0.0192 | Z98: 0.865 | AA98: 1 | AB98: 0.9808 | AC98: JUNIO | AD98: 2026
A99: =IF(C99="","",A98+1) -> 46191 | B99: 0.94552657 | C99: 644 | D99: 0.58333333 | E99: 0.99722222 | F99: 596 | G99: 0 | H99: 60 | I99: 72.089552 | J99: 9.9333333 | K99: 0 | L99: 72.089552 | M99: 72.089552 | N99: 64.832215 | O99: 0.0133 | P99: 0.01863354 | Q99: 0.0031 | R99: 0.0062 | S99: 0.007 | T99: 0 | U99: 12 | V99: 1. Se eviencia impacto en indicador tolerancia cero debido mas que todo por el ingreso de ganado muy sucio al proceso y tambien se tenia personal en entrenamiento en rayado de pecho y corte de manos 2. Se evidencia incumpliento en velocidad debido al paso de 91 reses de cliente olimpica | W99: 0 | X99: 75 | Y99: 0.0163 | Z99: 1 | AA99: 0.96119403 | AB99: 0.9837 | AC99: JUNIO | AD99: 2026
A100: =IF(C100="","",A99+1) -> 46192 | B100: 0.85317647 | C100: 405 | D100: 0.70833333 | E100: 0.99027778 | F100: 406 | G100: 12 | H100: 30 | I100: 66.758242 | J100: 6.7666667 | K100: 0 | L100: 64.62766 | M100: 66.758242 | N100: 59.852217 | O100: 0.0043 | P100: 0.014814815 | Q100: 0.0086 | R100: 0.0025 | S100: 0.0012 | T100: 0 | U100: 6 | V100: 1. Se registra parada por novedad desensor de grilletes que se queda pegado (5) 2. Se registra parada por animal atascado en box (7) | W100: 0.02955665 | X100: 75 | Y100: 0.0123 | Z100: 0.97044335 | AA100: 0.89010989 | AB100: 0.9877 | AC100: JUNIO | AD100: 2026
...

Sheet CONSOLIDADO DE CIERRE
A1: FECHA | B1: TOTAL DE BENEFICO | C1: HORA INICIO CABEZAS | D1: HORA ULTIMA VISCERA AMARRADA | E1: TOTAL PAROS | F1: DURACIÓN PROCESO (Hrs) | G1: RENDIMIENTO BRUTO (visceras/hora) | H1: RENDIMIENTO NETO (visceras/hora) | I1: RENDIMIENTO (visceras/hr/hombre) | J1: MINUTOS PAROS PROGRAMADOS | K1: MINUTOS PAROS NO PROGRAMADOS | L1: NOVEDADES: | M1: =IFERROR(__xludf.DUMMYFUNCTION("TRANSPOSE(IMPORTRANGE(""https://docs.google.com/spreadsheets/d/1CNeKSHTeNNJnfn5EymHwGg5Mkuk6EcepW7_9QkJxalc/edit#gid=1218471306"",""ENERO 2024!E2:AJ21""))"),"PERSONAL ASIGNADO") -> PERSONAL ASIGNADO | N1: =IFERROR(__xludf.DUMMYFUNCTION("""COMPUTED_VALUE"""),"PERSONAL CONTRATADO") -> PERSONAL CONTRATADO | O1: =IFERROR(__xludf.DUMMYFUNCTION("""COMPUTED_VALUE"""),"COMPENSATORIO") -> COMPENSATORIO | P1: =IFERROR(__xludf.DUMMYFUNCTION("""COMPUTED_VALUE"""),"PERMISO") -> PERMISO | Q1: =IFERROR(__xludf.DUMMYFUNCTION("""COMPUTED_VALUE"""),"AUSENTISMO") -> AUSENTISMO | R1: =IFERROR(__xludf.DUMMYFUNCTION("""COMPUTED_VALUE"""),"RENUNCIA") -> RENUNCIA | S1: =IFERROR(__xludf.DUMMYFUNCTION("""COMPUTED_VALUE"""),"INCAPACIDAD") -> INCAPACIDAD | T1: =IFERROR(__xludf.DUMMYFUNCTION("""COMPUTED_VALUE"""),"CALAMIDAD") -> CALAMIDAD | U1: =IFERROR(__xludf.DUMMYFUNCTION("""COMPUTED_VALUE"""),"PDTE POR CONTRATAR") -> PDTE POR CONTRATAR | V1: =IFERROR(__xludf.DUMMYFUNCTION("""COMPUTED_VALUE"""),"VACACIONES") -> VACACIONES | W1: =IFERROR(__xludf.DUMMYFUNCTION("""COMPUTED_VALUE"""),"SUSPENSION") -> SUSPENSION | X1: =IFERROR(__xludf.DUMMYFUNCTION("""COMPUTED_VALUE"""),"REUBICADO") -> REUBICADO | Y1: =IFERROR(__xludf.DUMMYFUNCTION("""COMPUTED_VALUE"""),"LICENCIA") -> LICENCIA | Z1: =IFERROR(__xludf.DUMMYFUNCTION("""COMPUTED_VALUE"""),"AMORTIZAR EXTRAS") -> AMORTIZAR EXTRAS | AA1: =IFERROR(__xludf.DUMMYFUNCTION("""COMPUTED_VALUE"""),"DIA DE CERO ACCIDENTE") -> DIA DE CERO ACCIDENTE | AB1: =IFERROR(__xludf.DUMMYFUNCTION("""COMPUTED_VALUE"""),"INDUCCION") -> INDUCCION | AC1: =IFERROR(__xludf.DUMMYFUNCTION("""COMPUTED_VALUE"""),"DIA DE LA FAMILIA") -> DIA DE LA FAMILIA | AD1: =IFERROR(__xludf.DUMMYFUNCTION("""COMPUTED_VALUE"""),"PERSONAL PRESENTE") -> PERSONAL PRESENTE | AE1: =IFERROR(__xludf.DUMMYFUNCTION("""COMPUTED_VALUE"""),"PERSONAL AUSENTE") -> PERSONAL AUSENTE | AF1: =IFERROR(__xludf.DUMMYFUNCTION("""COMPUTED_VALUE"""),"PENDIENTES POR CONTRATAR") -> PENDIENTES POR CONTRATAR | AG1: MES | AH1: AÑO | AI1: SEBO | AJ1: CYC
A2: 45292 | B2: 0 | E2: {=IF(B2=0,"",(J2+K2)/60)} | F2: =IF(B2=0,"",HOUR(D2-C2)+(MINUTE(D2-C2)/60)) | G2: =IF(B2=0,"",B2/F2) | H2: =IF(B2=0,"",B2/(F2-E2)) | I2: =IF(B2=0,"",B2/F2/AD2) | M2: =IFERROR(__xludf.DUMMYFUNCTION("""COMPUTED_VALUE"""),57.0) -> 57 | N2: =IFERROR(__xludf.DUMMYFUNCTION("""COMPUTED_VALUE"""),49.0) -> 49 | O2: =IFERROR(__xludf.DUMMYFUNCTION("""COMPUTED_VALUE"""),0.0) -> 0 | P2: =IFERROR(__xludf.DUMMYFUNCTION("""COMPUTED_VALUE"""),0.0) -> 0 | Q2: =IFERROR(__xludf.DUMMYFUNCTION("""COMPUTED_VALUE"""),0.0) -> 0 | R2: =IFERROR(__xludf.DUMMYFUNCTION("""COMPUTED_VALUE"""),0.0) -> 0 | S2: =IFERROR(__xludf.DUMMYFUNCTION("""COMPUTED_VALUE"""),0.0) -> 0 | T2: =IFERROR(__xludf.DUMMYFUNCTION("""COMPUTED_VALUE"""),0.0) -> 0 | U2: =IFERROR(__xludf.DUMMYFUNCTION("""COMPUTED_VALUE"""),6.0) -> 6 | V2: =IFERROR(__xludf.DUMMYFUNCTION("""COMPUTED_VALUE"""),0.0) -> 0 | W2: =IFERROR(__xludf.DUMMYFUNCTION("""COMPUTED_VALUE"""),0.0) -> 0 | X2: =IFERROR(__xludf.DUMMYFUNCTION("""COMPUTED_VALUE"""),0.0) -> 0 | Y2: =IFERROR(__xludf.DUMMYFUNCTION("""COMPUTED_VALUE"""),0.0) -> 0 | Z2: =IFERROR(__xludf.DUMMYFUNCTION("""COMPUTED_VALUE"""),0.0) -> 0 | AA2: =IFERROR(__xludf.DUMMYFUNCTION("""COMPUTED_VALUE"""),0.0) -> 0 | AB2: =IFERROR(__xludf.DUMMYFUNCTION("""COMPUTED_VALUE"""),0.0) -> 0 | AC2: =IFERROR(__xludf.DUMMYFUNCTION("""COMPUTED_VALUE"""),0.0) -> 0 | AD2: =IFERROR(__xludf.DUMMYFUNCTION("""COMPUTED_VALUE"""),0.0) -> 0 | AE2: =IFERROR(__xludf.DUMMYFUNCTION("""COMPUTED_VALUE"""),8.0) -> 8 | AF2: =IFERROR(__xludf.DUMMYFUNCTION("""COMPUTED_VALUE"""),8.0) -> 8 | AG2: {=UPPER(TEXT(A2:A1366,"MMMM"))} -> ENERO | AH2: {=UPPER(TEXT(A2:A1366,"YYY"))} -> 2024
A3: =IF(B3="","",A2+1) -> 45293 | B3: 309 | C3: 0.51597222 | D3: 0.75694444 | E3: {=IF(B3=0,"",(J3+K3)/60)} -> 0.25 | F3: =IF(B3=0,"",HOUR(D3-C3)+(MINUTE(D3-C3)/60)) -> 5.7833333 | G3: =IF(B3=0,"",B3/F3) -> 53.429395 | H3: =IF(B3=0,"",B3/(F3-E3)) -> 55.843373 | I3: =IF(B3=0,"",B3/F3/AD3) -> 1.3699845 | J3: 15 | M3: =IFERROR(__xludf.DUMMYFUNCTION("""COMPUTED_VALUE"""),57.0) -> 57 | N3: =IFERROR(__xludf.DUMMYFUNCTION("""COMPUTED_VALUE"""),49.0) -> 49 | O3: =IFERROR(__xludf.DUMMYFUNCTION("""COMPUTED_VALUE"""),0.0) -> 0 | P3: =IFERROR(__xludf.DUMMYFUNCTION("""COMPUTED_VALUE"""),0.0) -> 0 | Q3: =IFERROR(__xludf.DUMMYFUNCTION("""COMPUTED_VALUE"""),3.0) -> 3 | R3: =IFERROR(__xludf.DUMMYFUNCTION("""COMPUTED_VALUE"""),0.0) -> 0 | S3: =IFERROR(__xludf.DUMMYFUNCTION("""COMPUTED_VALUE"""),3.0) -> 3 | T3: =IFERROR(__xludf.DUMMYFUNCTION("""COMPUTED_VALUE"""),0.0) -> 0 | U3: =IFERROR(__xludf.DUMMYFUNCTION("""COMPUTED_VALUE"""),6.0) -> 6 | V3: =IFERROR(__xludf.DUMMYFUNCTION("""COMPUTED_VALUE"""),4.0) -> 4 | W3: =IFERROR(__xludf.DUMMYFUNCTION("""COMPUTED_VALUE"""),0.0) -> 0 | X3: =IFERROR(__xludf.DUMMYFUNCTION("""COMPUTED_VALUE"""),0.0) -> 0 | Y3: =IFERROR(__xludf.DUMMYFUNCTION("""COMPUTED_VALUE"""),0.0) -> 0 | Z3: =IFERROR(__xludf.DUMMYFUNCTION("""COMPUTED_VALUE"""),2.0) -> 2 | AA3: =IFERROR(__xludf.DUMMYFUNCTION("""COMPUTED_VALUE"""),0.0) -> 0 | AB3: =IFERROR(__xludf.DUMMYFUNCTION("""COMPUTED_VALUE"""),0.0) -> 0 | AC3: =IFERROR(__xludf.DUMMYFUNCTION("""COMPUTED_VALUE"""),0.0) -> 0 | AD3: =IFERROR(__xludf.DUMMYFUNCTION("""COMPUTED_VALUE"""),39.0) -> 39 | AE3: =IFERROR(__xludf.DUMMYFUNCTION("""COMPUTED_VALUE"""),20.0) -> 20 | AF3: =IFERROR(__xludf.DUMMYFUNCTION("""COMPUTED_VALUE"""),8.0) -> 8 | AG3: ENERO | AH3: 2024
A4: =IF(B4="","",A3+1) -> 45294 | B4: 595 | C4: 0.55833333 | D4: 1.0208333 | E4: {=IF(B4=0,"",(J4+K4)/60)} -> 1.1 | F4: =IF(B4=0,"",HOUR(D4-C4)+(MINUTE(D4-C4)/60)) -> 11.1 | G4: =IF(B4=0,"",B4/F4) -> 53.603604 | H4: =IF(B4=0,"",B4/(F4-E4)) -> 59.5 | I4: =IF(B4=0,"",B4/F4/AD4) -> 1.2762763 | J4: 60 | K4: 6 | M4: =IFERROR(__xludf.DUMMYFUNCTION("""COMPUTED_VALUE"""),57.0) -> 57 | N4: =IFERROR(__xludf.DUMMYFUNCTION("""COMPUTED_VALUE"""),48.0) -> 48 | O4: =IFERROR(__xludf.DUMMYFUNCTION("""COMPUTED_VALUE"""),0.0) -> 0 | P4: =IFERROR(__xludf.DUMMYFUNCTION("""COMPUTED_VALUE"""),0.0) -> 0 | Q4: =IFERROR(__xludf.DUMMYFUNCTION("""COMPUTED_VALUE"""),0.0) -> 0 | R4: =IFERROR(__xludf.DUMMYFUNCTION("""COMPUTED_VALUE"""),0.0) -> 0 | S4: =IFERROR(__xludf.DUMMYFUNCTION("""COMPUTED_VALUE"""),4.0) -> 4 | T4: =IFERROR(__xludf.DUMMYFUNCTION("""COMPUTED_VALUE"""),0.0) -> 0 | U4: =IFERROR(__xludf.DUMMYFUNCTION("""COMPUTED_VALUE"""),7.0) -> 7 | V4: =IFERROR(__xludf.DUMMYFUNCTION("""COMPUTED_VALUE"""),4.0) -> 4 | W4: =IFERROR(__xludf.DUMMYFUNCTION("""COMPUTED_VALUE"""),0.0) -> 0 | X4: =IFERROR(__xludf.DUMMYFUNCTION("""COMPUTED_VALUE"""),0.0) -> 0 | Y4: =IFERROR(__xludf.DUMMYFUNCTION("""COMPUTED_VALUE"""),0.0) -> 0 | Z4: =IFERROR(__xludf.DUMMYFUNCTION("""COMPUTED_VALUE"""),0.0) -> 0 | AA4: =IFERROR(__xludf.DUMMYFUNCTION("""COMPUTED_VALUE"""),0.0) -> 0 | AB4: =IFERROR(__xludf.DUMMYFUNCTION("""COMPUTED_VALUE"""),0.0) -> 0 | AC4: =IFERROR(__xludf.DUMMYFUNCTION("""COMPUTED_VALUE"""),0.0) -> 0 | AD4: =IFERROR(__xludf.DUMMYFUNCTION("""COMPUTED_VALUE"""),42.0) -> 42 | AE4: =IFERROR(__xludf.DUMMYFUNCTION("""COMPUTED_VALUE"""),17.0) -> 17 | AF4: =IFERROR(__xludf.DUMMYFUNCTION("""COMPUTED_VALUE"""),9.0) -> 9 | AG4: ENERO | AH4: 2024
A5: =IF(B5="","",A4+1) -> 45295 | B5: 538 | C5: 0.51666667 | D5: 0.92222222 | E5: {=IF(B5=0,"",(J5+K5)/60)} -> 1.25 | F5: =IF(B5=0,"",HOUR(D5-C5)+(MINUTE(D5-C5)/60)) -> 9.7333333 | G5: =IF(B5=0,"",B5/F5) -> 55.273973 | H5: =IF(B5=0,"",B5/(F5-E5)) -> 63.418468 | I5: =IF(B5=0,"",B5/F5/AD5) -> 1.2283105 | J5: 15 | K5: 60 | M5: =IFERROR(__xludf.DUMMYFUNCTION("""COMPUTED_VALUE"""),57.0) -> 57 | N5: =IFERROR(__xludf.DUMMYFUNCTION("""COMPUTED_VALUE"""),49.0) -> 49 | O5: =IFERROR(__xludf.DUMMYFUNCTION("""COMPUTED_VALUE"""),0.0) -> 0 | P5: =IFERROR(__xludf.DUMMYFUNCTION("""COMPUTED_VALUE"""),0.0) -> 0 | Q5: =IFERROR(__xludf.DUMMYFUNCTION("""COMPUTED_VALUE"""),0.0) -> 0 | R5: =IFERROR(__xludf.DUMMYFUNCTION("""COMPUTED_VALUE"""),0.0) -> 0 | S5: =IFERROR(__xludf.DUMMYFUNCTION("""COMPUTED_VALUE"""),2.0) -> 2 | T5: =IFERROR(__xludf.DUMMYFUNCTION("""COMPUTED_VALUE"""),0.0) -> 0 | U5: =IFERROR(__xludf.DUMMYFUNCTION("""COMPUTED_VALUE"""),6.0) -> 6 | V5: =IFERROR(__xludf.DUMMYFUNCTION("""COMPUTED_VALUE"""),4.0) -> 4 | W5: =IFERROR(__xludf.DUMMYFUNCTION("""COMPUTED_VALUE"""),0.0) -> 0 | X5: =IFERROR(__xludf.DUMMYFUNCTION("""COMPUTED_VALUE"""),0.0) -> 0 | Y5: =IFERROR(__xludf.DUMMYFUNCTION("""COMPUTED_VALUE"""),0.0) -> 0 | Z5: =IFERROR(__xludf.DUMMYFUNCTION("""COMPUTED_VALUE"""),0.0) -> 0 | AA5: =IFERROR(__xludf.DUMMYFUNCTION("""COMPUTED_VALUE"""),0.0) -> 0 | AB5: =IFERROR(__xludf.DUMMYFUNCTION("""COMPUTED_VALUE"""),0.0) -> 0 | AC5: =IFERROR(__xludf.DUMMYFUNCTION("""COMPUTED_VALUE"""),0.0) -> 0 | AD5: =IFERROR(__xludf.DUMMYFUNCTION("""COMPUTED_VALUE"""),45.0) -> 45 | AE5: =IFERROR(__xludf.DUMMYFUNCTION("""COMPUTED_VALUE"""),14.0) -> 14 | AF5: =IFERROR(__xludf.DUMMYFUNCTION("""COMPUTED_VALUE"""),8.0) -> 8 | AG5: ENERO | AH5: 2024
A6: =IF(B6="","",A5+1) -> 45296 | B6: 464 | C6: 0.51597222 | D6: 0.86666667 | E6: {=IF(B6=0,"",(J6+K6)/60)} -> 0.25 | F6: =IF(B6=0,"",HOUR(D6-C6)+(MINUTE(D6-C6)/60)) -> 8.4166667 | G6: =IF(B6=0,"",B6/F6) -> 55.128713 | H6: =IF(B6=0,"",B6/(F6-E6)) -> 56.816327 | I6: =IF(B6=0,"",B6/F6/AD6) -> 1.2820631 | J6: 15 | M6: =IFERROR(__xludf.DUMMYFUNCTION("""COMPUTED_VALUE"""),57.0) -> 57 | N6: =IFERROR(__xludf.DUMMYFUNCTION("""COMPUTED_VALUE"""),49.0) -> 49 | O6: =IFERROR(__xludf.DUMMYFUNCTION("""COMPUTED_VALUE"""),0.0) -> 0 | P6: =IFERROR(__xludf.DUMMYFUNCTION("""COMPUTED_VALUE"""),2.0) -> 2 | Q6: =IFERROR(__xludf.DUMMYFUNCTION("""COMPUTED_VALUE"""),0.0) -> 0 | R6: =IFERROR(__xludf.DUMMYFUNCTION("""COMPUTED_VALUE"""),0.0) -> 0 | S6: =IFERROR(__xludf.DUMMYFUNCTION("""COMPUTED_VALUE"""),2.0) -> 2 | T6: =IFERROR(__xludf.DUMMYFUNCTION("""COMPUTED_VALUE"""),0.0) -> 0 | U6: =IFERROR(__xludf.DUMMYFUNCTION("""COMPUTED_VALUE"""),6.0) -> 6 | V6: =IFERROR(__xludf.DUMMYFUNCTION("""COMPUTED_VALUE"""),4.0) -> 4 | W6: =IFERROR(__xludf.DUMMYFUNCTION("""COMPUTED_VALUE"""),0.0) -> 0 | X6: =IFERROR(__xludf.DUMMYFUNCTION("""COMPUTED_VALUE"""),0.0) -> 0 | Y6: =IFERROR(__xludf.DUMMYFUNCTION("""COMPUTED_VALUE"""),0.0) -> 0 | Z6: =IFERROR(__xludf.DUMMYFUNCTION("""COMPUTED_VALUE"""),0.0) -> 0 | AA6: =IFERROR(__xludf.DUMMYFUNCTION("""COMPUTED_VALUE"""),0.0) -> 0 | AB6: =IFERROR(__xludf.DUMMYFUNCTION("""COMPUTED_VALUE"""),0.0) -> 0 | AC6: =IFERROR(__xludf.DUMMYFUNCTION("""COMPUTED_VALUE"""),0.0) -> 0 | AD6: =IFERROR(__xludf.DUMMYFUNCTION("""COMPUTED_VALUE"""),43.0) -> 43 | AE6: =IFERROR(__xludf.DUMMYFUNCTION("""COMPUTED_VALUE"""),16.0) -> 16 | AF6: =IFERROR(__xludf.DUMMYFUNCTION("""COMPUTED_VALUE"""),8.0) -> 8 | AG6: ENERO | AH6: 2024
A7: =IF(B7="","",A6+1) -> 45297 | B7: 445 | C7: 0.51666667 | D7: 0.83888889 | E7: {=IF(B7=0,"",(J7+K7)/60)} -> 0.25 | F7: =IF(B7=0,"",HOUR(D7-C7)+(MINUTE(D7-C7)/60)) -> 7.7333333 | G7: =IF(B7=0,"",B7/F7) -> 57.543103 | H7: =IF(B7=0,"",B7/(F7-E7)) -> 59.465479 | I7: =IF(B7=0,"",B7/F7/AD7) -> 1.4034903 | J7: 15 | M7: =IFERROR(__xludf.DUMMYFUNCTION("""COMPUTED_VALUE"""),57.0) -> 57 | N7: =IFERROR(__xludf.DUMMYFUNCTION("""COMPUTED_VALUE"""),49.0) -> 49 | O7: =IFERROR(__xludf.DUMMYFUNCTION("""COMPUTED_VALUE"""),0.0) -> 0 | P7: =IFERROR(__xludf.DUMMYFUNCTION("""COMPUTED_VALUE"""),1.0) -> 1 | Q7: =IFERROR(__xludf.DUMMYFUNCTION("""COMPUTED_VALUE"""),0.0) -> 0 | R7: =IFERROR(__xludf.DUMMYFUNCTION("""COMPUTED_VALUE"""),0.0) -> 0 | S7: =IFERROR(__xludf.DUMMYFUNCTION("""COMPUTED_VALUE"""),3.0) -> 3 | T7: =IFERROR(__xludf.DUMMYFUNCTION("""COMPUTED_VALUE"""),0.0) -> 0 | U7: =IFERROR(__xludf.DUMMYFUNCTION("""COMPUTED_VALUE"""),6.0) -> 6 | V7: =IFERROR(__xludf.DUMMYFUNCTION("""COMPUTED_VALUE"""),4.0) -> 4 | W7: =IFERROR(__xludf.DUMMYFUNCTION("""COMPUTED_VALUE"""),0.0) -> 0 | X7: =IFERROR(__xludf.DUMMYFUNCTION("""COMPUTED_VALUE"""),0.0) -> 0 | Y7: =IFERROR(__xludf.DUMMYFUNCTION("""COMPUTED_VALUE"""),0.0) -> 0 | Z7: =IFERROR(__xludf.DUMMYFUNCTION("""COMPUTED_VALUE"""),2.0) -> 2 | AA7: =IFERROR(__xludf.DUMMYFUNCTION("""COMPUTED_VALUE"""),0.0) -> 0 | AB7: =IFERROR(__xludf.DUMMYFUNCTION("""COMPUTED_VALUE"""),0.0) -> 0 | AC7: =IFERROR(__xludf.DUMMYFUNCTION("""COMPUTED_VALUE"""),0.0) -> 0 | AD7: =IFERROR(__xludf.DUMMYFUNCTION("""COMPUTED_VALUE"""),41.0) -> 41 | AE7: =IFERROR(__xludf.DUMMYFUNCTION("""COMPUTED_VALUE"""),18.0) -> 18 | AF7: =IFERROR(__xludf.DUMMYFUNCTION("""COMPUTED_VALUE"""),8.0) -> 8 | AG7: ENERO | AH7: 2024
A8: =IF(B8="","",A7+1) -> 45298 | B8: 0 | E8: {=IF(B8=0,"",(J8+K8)/60)} | F8: =IF(B8=0,"",HOUR(D8-C8)+(MINUTE(D8-C8)/60)) | G8: =IF(B8=0,"",B8/F8) | H8: =IF(B8=0,"",B8/(F8-E8)) | I8: =IF(B8=0,"",B8/F8/AD8) | M8: =IFERROR(__xludf.DUMMYFUNCTION("""COMPUTED_VALUE"""),57.0) -> 57 | N8: =IFERROR(__xludf.DUMMYFUNCTION("""COMPUTED_VALUE"""),49.0) -> 49 | O8: =IFERROR(__xludf.DUMMYFUNCTION("""COMPUTED_VALUE"""),0.0) -> 0 | P8: =IFERROR(__xludf.DUMMYFUNCTION("""COMPUTED_VALUE"""),0.0) -> 0 | Q8: =IFERROR(__xludf.DUMMYFUNCTION("""COMPUTED_VALUE"""),0.0) -> 0 | R8: =IFERROR(__xludf.DUMMYFUNCTION("""COMPUTED_VALUE"""),0.0) -> 0 | S8: =IFERROR(__xludf.DUMMYFUNCTION("""COMPUTED_VALUE"""),0.0) -> 0 | T8: =IFERROR(__xludf.DUMMYFUNCTION("""COMPUTED_VALUE"""),0.0) -> 0 | U8: =IFERROR(__xludf.DUMMYFUNCTION("""COMPUTED_VALUE"""),6.0) -> 6 | V8: =IFERROR(__xludf.DUMMYFUNCTION("""COMPUTED_VALUE"""),0.0) -> 0 | W8: =IFERROR(__xludf.DUMMYFUNCTION("""COMPUTED_VALUE"""),0.0) -> 0 | X8: =IFERROR(__xludf.DUMMYFUNCTION("""COMPUTED_VALUE"""),0.0) -> 0 | Y8: =IFERROR(__xludf.DUMMYFUNCTION("""COMPUTED_VALUE"""),0.0) -> 0 | Z8: =IFERROR(__xludf.DUMMYFUNCTION("""COMPUTED_VALUE"""),0.0) -> 0 | AA8: =IFERROR(__xludf.DUMMYFUNCTION("""COMPUTED_VALUE"""),0.0) -> 0 | AB8: =IFERROR(__xludf.DUMMYFUNCTION("""COMPUTED_VALUE"""),0.0) -> 0 | AC8: =IFERROR(__xludf.DUMMYFUNCTION("""COMPUTED_VALUE"""),0.0) -> 0 | AD8: =IFERROR(__xludf.DUMMYFUNCTION("""COMPUTED_VALUE"""),0.0) -> 0 | AE8: =IFERROR(__xludf.DUMMYFUNCTION("""COMPUTED_VALUE"""),8.0) -> 8 | AF8: =IFERROR(__xludf.DUMMYFUNCTION("""COMPUTED_VALUE"""),8.0) -> 8 | AG8: ENERO | AH8: 2024
A9: =IF(B9="","",A8+1) -> 45299 | B9: 442 | C9: 0.51597222 | D9: 0.86458333 | E9: {=IF(B9=0,"",(J9+K9)/60)} -> 0.25 | F9: =IF(B9=0,"",HOUR(D9-C9)+(MINUTE(D9-C9)/60)) -> 8.3666667 | G9: =IF(B9=0,"",B9/F9) -> 52.828685 | H9: =IF(B9=0,"",B9/(F9-E9)) -> 54.455852 | I9: =IF(B9=0,"",B9/F9/AD9) -> 1.2285741 | J9: 15 | M9: =IFERROR(__xludf.DUMMYFUNCTION("""COMPUTED_VALUE"""),57.0) -> 57 | N9: =IFERROR(__xludf.DUMMYFUNCTION("""COMPUTED_VALUE"""),49.0) -> 49 | O9: =IFERROR(__xludf.DUMMYFUNCTION("""COMPUTED_VALUE"""),0.0) -> 0 | P9: =IFERROR(__xludf.DUMMYFUNCTION("""COMPUTED_VALUE"""),1.0) -> 1 | Q9: =IFERROR(__xludf.DUMMYFUNCTION("""COMPUTED_VALUE"""),1.0) -> 1 | R9: =IFERROR(__xludf.DUMMYFUNCTION("""COMPUTED_VALUE"""),0.0) -> 0 | S9: =IFERROR(__xludf.DUMMYFUNCTION("""COMPUTED_VALUE"""),1.0) -> 1 | T9: =IFERROR(__xludf.DUMMYFUNCTION("""COMPUTED_VALUE"""),0.0) -> 0 | U9: =IFERROR(__xludf.DUMMYFUNCTION("""COMPUTED_VALUE"""),6.0) -> 6 | V9: =IFERROR(__xludf.DUMMYFUNCTION("""COMPUTED_VALUE"""),4.0) -> 4 | W9: =IFERROR(__xludf.DUMMYFUNCTION("""COMPUTED_VALUE"""),0.0) -> 0 | X9: =IFERROR(__xludf.DUMMYFUNCTION("""COMPUTED_VALUE"""),0.0) -> 0 | Y9: =IFERROR(__xludf.DUMMYFUNCTION("""COMPUTED_VALUE"""),0.0) -> 0 | Z9: =IFERROR(__xludf.DUMMYFUNCTION("""COMPUTED_VALUE"""),1.0) -> 1 | AA9: =IFERROR(__xludf.DUMMYFUNCTION("""COMPUTED_VALUE"""),0.0) -> 0 | AB9: =IFERROR(__xludf.DUMMYFUNCTION("""COMPUTED_VALUE"""),0.0) -> 0 | AC9: =IFERROR(__xludf.DUMMYFUNCTION("""COMPUTED_VALUE"""),0.0) -> 0 | AD9: =IFERROR(__xludf.DUMMYFUNCTION("""COMPUTED_VALUE"""),43.0) -> 43 | AE9: =IFERROR(__xludf.DUMMYFUNCTION("""COMPUTED_VALUE"""),16.0) -> 16 | AF9: =IFERROR(__xludf.DUMMYFUNCTION("""COMPUTED_VALUE"""),8.0) -> 8 | AG9: ENERO | AH9: 2024
A10: =IF(B10="","",A9+1) -> 45300 | B10: 289 | C10: 0.51666667 | D10: 0.75 | E10: {=IF(B10=0,"",(J10+K10)/60)} -> 0.25 | F10: =IF(B10=0,"",HOUR(D10-C10)+(MINUTE(D10-C10)/60)) -> 5.6 | G10: =IF(B10=0,"",B10/F10) -> 51.607143 | H10: =IF(B10=0,"",B10/(F10-E10)) -> 54.018692 | I10: =IF(B10=0,"",B10/F10/AD10) -> 1.1218944 | J10: 15 | M10: =IFERROR(__xludf.DUMMYFUNCTION("""COMPUTED_VALUE"""),57.0) -> 57 | N10: =IFERROR(__xludf.DUMMYFUNCTION("""COMPUTED_VALUE"""),49.0) -> 49 | O10: =IFERROR(__xludf.DUMMYFUNCTION("""COMPUTED_VALUE"""),0.0) -> 0 | P10: =IFERROR(__xludf.DUMMYFUNCTION("""COMPUTED_VALUE"""),0.0) -> 0 | Q10: =IFERROR(__xludf.DUMMYFUNCTION("""COMPUTED_VALUE"""),0.0) -> 0 | R10: =IFERROR(__xludf.DUMMYFUNCTION("""COMPUTED_VALUE"""),0.0) -> 0 | S10: =IFERROR(__xludf.DUMMYFUNCTION("""COMPUTED_VALUE"""),1.0) -> 1 | T10: =IFERROR(__xludf.DUMMYFUNCTION("""COMPUTED_VALUE"""),0.0) -> 0 | U10: =IFERROR(__xludf.DUMMYFUNCTION("""COMPUTED_VALUE"""),6.0) -> 6 | V10: =IFERROR(__xludf.DUMMYFUNCTION("""COMPUTED_VALUE"""),4.0) -> 4 | W10: =IFERROR(__xludf.DUMMYFUNCTION("""COMPUTED_VALUE"""),0.0) -> 0 | X10: =IFERROR(__xludf.DUMMYFUNCTION("""COMPUTED_VALUE"""),0.0) -> 0 | Y10: =IFERROR(__xludf.DUMMYFUNCTION("""COMPUTED_VALUE"""),0.0) -> 0 | Z10: =IFERROR(__xludf.DUMMYFUNCTION("""COMPUTED_VALUE"""),0.0) -> 0 | AA10: =IFERROR(__xludf.DUMMYFUNCTION("""COMPUTED_VALUE"""),0.0) -> 0 | AB10: =IFERROR(__xludf.DUMMYFUNCTION("""COMPUTED_VALUE"""),0.0) -> 0 | AC10: =IFERROR(__xludf.DUMMYFUNCTION("""COMPUTED_VALUE"""),0.0) -> 0 | AD10: =IFERROR(__xludf.DUMMYFUNCTION("""COMPUTED_VALUE"""),46.0) -> 46 | AE10: =IFERROR(__xludf.DUMMYFUNCTION("""COMPUTED_VALUE"""),13.0) -> 13 | AF10: =IFERROR(__xludf.DUMMYFUNCTION("""COMPUTED_VALUE"""),8.0) -> 8 | AG10: ENERO | AH10: 2024
A11: =IF(B11="","",A10+1) -> 45301 | B11: 396 | C11: 0.55763889 | D11: 0.86666667 | E11: {=IF(B11=0,"",(J11+K11)/60)} -> 0.25 | F11: =IF(B11=0,"",HOUR(D11-C11)+(MINUTE(D11-C11)/60)) -> 7.4166667 | G11: =IF(B11=0,"",B11/F11) -> 53.393258 | H11: =IF(B11=0,"",B11/(F11-E11)) -> 55.255814 | I11: =IF(B11=0,"",B11/F11/AD11) -> 1.160723 | J11: 15 | M11: =IFERROR(__xludf.DUMMYFUNCTION("""COMPUTED_VALUE"""),57.0) -> 57 | N11: =IFERROR(__xludf.DUMMYFUNCTION("""COMPUTED_VALUE"""),49.0) -> 49 | O11: =IFERROR(__xludf.DUMMYFUNCTION("""COMPUTED_VALUE"""),0.0) -> 0 | P11: =IFERROR(__xludf.DUMMYFUNCTION("""COMPUTED_VALUE"""),0.0) -> 0 | Q11: =IFERROR(__xludf.DUMMYFUNCTION("""COMPUTED_VALUE"""),1.0) -> 1 | R11: =IFERROR(__xludf.DUMMYFUNCTION("""COMPUTED_VALUE"""),0.0) -> 0 | S11: =IFERROR(__xludf.DUMMYFUNCTION("""COMPUTED_VALUE"""),0.0) -> 0 | T11: =IFERROR(__xludf.DUMMYFUNCTION("""COMPUTED_VALUE"""),0.0) -> 0 | U11: =IFERROR(__xludf.DUMMYFUNCTION("""COMPUTED_VALUE"""),6.0) -> 6 | V11: =IFERROR(__xludf.DUMMYFUNCTION("""COMPUTED_VALUE"""),3.0) -> 3 | W11: =IFERROR(__xludf.DUMMYFUNCTION("""COMPUTED_VALUE"""),0.0) -> 0 | X11: =IFERROR(__xludf.DUMMYFUNCTION("""COMPUTED_VALUE"""),0.0) -> 0 | Y11: =IFERROR(__xludf.DUMMYFUNCTION("""COMPUTED_VALUE"""),0.0) -> 0 | Z11: =IFERROR(__xludf.DUMMYFUNCTION("""COMPUTED_VALUE"""),1.0) -> 1 | AA11: =IFERROR(__xludf.DUMMYFUNCTION("""COMPUTED_VALUE"""),0.0) -> 0 | AB11: =IFERROR(__xludf.DUMMYFUNCTION("""COMPUTED_VALUE"""),0.0) -> 0 | AC11: =IFERROR(__xludf.DUMMYFUNCTION("""COMPUTED_VALUE"""),0.0) -> 0 | AD11: =IFERROR(__xludf.DUMMYFUNCTION("""COMPUTED_VALUE"""),46.0) -> 46 | AE11: =IFERROR(__xludf.DUMMYFUNCTION("""COMPUTED_VALUE"""),13.0) -> 13 | AF11: =IFERROR(__xludf.DUMMYFUNCTION("""COMPUTED_VALUE"""),8.0) -> 8 | AG11: ENERO | AH11: 2024
A12: =IF(B12="","",A11+1) -> 45302 | B12: 531 | C12: 0.55833333 | D12: 0.95833333 | E12: {=IF(B12=0,"",(J12+K12)/60)} -> 0.25 | F12: =IF(B12=0,"",HOUR(D12-C12)+(MINUTE(D12-C12)/60)) -> 9.6 | G12: =IF(B12=0,"",B12/F12) -> 55.3125 | H12: =IF(B12=0,"",B12/(F12-E12)) -> 56.791444 | I12: =IF(B12=0,"",B12/F12/AD12) -> 1.2024457 | J12: 15 | M12: =IFERROR(__xludf.DUMMYFUNCTION("""COMPUTED_VALUE"""),57.0) -> 57 | N12: =IFERROR(__xludf.DUMMYFUNCTION("""COMPUTED_VALUE"""),50.0) -> 50 | O12: =IFERROR(__xludf.DUMMYFUNCTION("""COMPUTED_VALUE"""),0.0) -> 0 | P12: =IFERROR(__xludf.DUMMYFUNCTION("""COMPUTED_VALUE"""),1.0) -> 1 | Q12: =IFERROR(__xludf.DUMMYFUNCTION("""COMPUTED_VALUE"""),1.0) -> 1 | R12: =IFERROR(__xludf.DUMMYFUNCTION("""COMPUTED_VALUE"""),0.0) -> 0 | S12: =IFERROR(__xludf.DUMMYFUNCTION("""COMPUTED_VALUE"""),1.0) -> 1 | T12: =IFERROR(__xludf.DUMMYFUNCTION("""COMPUTED_VALUE"""),0.0) -> 0 | U12: =IFERROR(__xludf.DUMMYFUNCTION("""COMPUTED_VALUE"""),5.0) -> 5 | V12: =IFERROR(__xludf.DUMMYFUNCTION("""COMPUTED_VALUE"""),3.0) -> 3 | W12: =IFERROR(__xludf.DUMMYFUNCTION("""COMPUTED_VALUE"""),0.0) -> 0 | X12: =IFERROR(__xludf.DUMMYFUNCTION("""COMPUTED_VALUE"""),0.0) -> 0 | Y12: =IFERROR(__xludf.DUMMYFUNCTION("""COMPUTED_VALUE"""),0.0) -> 0 | Z12: =IFERROR(__xludf.DUMMYFUNCTION("""COMPUTED_VALUE"""),0.0) -> 0 | AA12: =IFERROR(__xludf.DUMMYFUNCTION("""COMPUTED_VALUE"""),0.0) -> 0 | AB12: =IFERROR(__xludf.DUMMYFUNCTION("""COMPUTED_VALUE"""),0.0) -> 0 | AC12: =IFERROR(__xludf.DUMMYFUNCTION("""COMPUTED_VALUE"""),0.0) -> 0 | AD12: =IFERROR(__xludf.DUMMYFUNCTION("""COMPUTED_VALUE"""),46.0) -> 46 | AE12: =IFERROR(__xludf.DUMMYFUNCTION("""COMPUTED_VALUE"""),13.0) -> 13 | AF12: =IFERROR(__xludf.DUMMYFUNCTION("""COMPUTED_VALUE"""),7.0) -> 7 | AG12: ENERO | AH12: 2024
A13: =IF(B13="","",A12+1) -> 45303 | B13: 463 | C13: 0.53125 | D13: 0.8875 | E13: {=IF(B13=0,"",(J13+K13)/60)} -> 0.25 | F13: =IF(B13=0,"",HOUR(D13-C13)+(MINUTE(D13-C13)/60)) -> 8.55 | G13: =IF(B13=0,"",B13/F13) -> 54.152047 | H13: =IF(B13=0,"",B13/(F13-E13)) -> 55.783133 | I13: =IF(B13=0,"",B13/F13/AD13) -> 1.1521712 | J13: 15 | M13: =IFERROR(__xludf.DUMMYFUNCTION("""COMPUTED_VALUE"""),57.0) -> 57 | N13: =IFERROR(__xludf.DUMMYFUNCTION("""COMPUTED_VALUE"""),49.0) -> 49 | O13: =IFERROR(__xludf.DUMMYFUNCTION("""COMPUTED_VALUE"""),0.0) -> 0 | P13: =IFERROR(__xludf.DUMMYFUNCTION("""COMPUTED_VALUE"""),0.0) -> 0 | Q13: =IFERROR(__xludf.DUMMYFUNCTION("""COMPUTED_VALUE"""),0.0) -> 0 | R13: =IFERROR(__xludf.DUMMYFUNCTION("""COMPUTED_VALUE"""),0.0) -> 0 | S13: =IFERROR(__xludf.DUMMYFUNCTION("""COMPUTED_VALUE"""),1.0) -> 1 | T13: =IFERROR(__xludf.DUMMYFUNCTION("""COMPUTED_VALUE"""),0.0) -> 0 | U13: =IFERROR(__xludf.DUMMYFUNCTION("""COMPUTED_VALUE"""),6.0) -> 6 | V13: =IFERROR(__xludf.DUMMYFUNCTION("""COMPUTED_VALUE"""),3.0) -> 3 | W13: =IFERROR(__xludf.DUMMYFUNCTION("""COMPUTED_VALUE"""),0.0) -> 0 | X13: =IFERROR(__xludf.DUMMYFUNCTION("""COMPUTED_VALUE"""),0.0) -> 0 | Y13: =IFERROR(__xludf.DUMMYFUNCTION("""COMPUTED_VALUE"""),0.0) -> 0 | Z13: =IFERROR(__xludf.DUMMYFUNCTION("""COMPUTED_VALUE"""),0.0) -> 0 | AA13: =IFERROR(__xludf.DUMMYFUNCTION("""COMPUTED_VALUE"""),0.0) -> 0 | AB13: =IFERROR(__xludf.DUMMYFUNCTION("""COMPUTED_VALUE"""),0.0) -> 0 | AC13: =IFERROR(__xludf.DUMMYFUNCTION("""COMPUTED_VALUE"""),0.0) -> 0 | AD13: =IFERROR(__xludf.DUMMYFUNCTION("""COMPUTED_VALUE"""),47.0) -> 47 | AE13: =IFERROR(__xludf.DUMMYFUNCTION("""COMPUTED_VALUE"""),12.0) -> 12 | AF13: =IFERROR(__xludf.DUMMYFUNCTION("""COMPUTED_VALUE"""),8.0) -> 8 | AG13: ENERO | AH13: 2024
A14: =IF(B14="","",A13+1) -> 45304 | B14: 463 | C14: 0.51666667 | D14: 0.86805556 | E14: {=IF(B14=0,"",(J14+K14)/60)} -> 0.25 | F14: =IF(B14=0,"",HOUR(D14-C14)+(MINUTE(D14-C14)/60)) -> 8.4333333 | G14: =IF(B14=0,"",B14/F14) -> 54.901186 | H14: =IF(B14=0,"",B14/(F14-E14)) -> 56.578411 | I14: =IF(B14=0,"",B14/F14/AD14) -> 1.193504 | J14: 15 | M14: =IFERROR(__xludf.DUMMYFUNCTION("""COMPUTED_VALUE"""),57.0) -> 57 | N14: =IFERROR(__xludf.DUMMYFUNCTION("""COMPUTED_VALUE"""),49.0) -> 49 | O14: =IFERROR(__xludf.DUMMYFUNCTION("""COMPUTED_VALUE"""),0.0) -> 0 | P14: =IFERROR(__xludf.DUMMYFUNCTION("""COMPUTED_VALUE"""),1.0) -> 1 | Q14: =IFERROR(__xludf.DUMMYFUNCTION("""COMPUTED_VALUE"""),0.0) -> 0 | R14: =IFERROR(__xludf.DUMMYFUNCTION("""COMPUTED_VALUE"""),0.0) -> 0 | S14: =IFERROR(__xludf.DUMMYFUNCTION("""COMPUTED_VALUE"""),1.0) -> 1 | T14: =IFERROR(__xludf.DUMMYFUNCTION("""COMPUTED_VALUE"""),0.0) -> 0 | U14: =IFERROR(__xludf.DUMMYFUNCTION("""COMPUTED_VALUE"""),6.0) -> 6 | V14: =IFERROR(__xludf.DUMMYFUNCTION("""COMPUTED_VALUE"""),3.0) -> 3 | W14: =IFERROR(__xludf.DUMMYFUNCTION("""COMPUTED_VALUE"""),0.0) -> 0 | X14: =IFERROR(__xludf.DUMMYFUNCTION("""COMPUTED_VALUE"""),0.0) -> 0 | Y14: =IFERROR(__xludf.DUMMYFUNCTION("""COMPUTED_VALUE"""),0.0) -> 0 | Z14: =IFERROR(__xludf.DUMMYFUNCTION("""COMPUTED_VALUE"""),0.0) -> 0 | AA14: =IFERROR(__xludf.DUMMYFUNCTION("""COMPUTED_VALUE"""),0.0) -> 0 | AB14: =IFERROR(__xludf.DUMMYFUNCTION("""COMPUTED_VALUE"""),0.0) -> 0 | AC14: =IFERROR(__xludf.DUMMYFUNCTION("""COMPUTED_VALUE"""),0.0) -> 0 | AD14: =IFERROR(__xludf.DUMMYFUNCTION("""COMPUTED_VALUE"""),46.0) -> 46 | AE14: =IFERROR(__xludf.DUMMYFUNCTION("""COMPUTED_VALUE"""),13.0) -> 13 | AF14: =IFERROR(__xludf.DUMMYFUNCTION("""COMPUTED_VALUE"""),8.0) -> 8 | AG14: ENERO | AH14: 2024
A15: =IF(B15="","",A14+1) -> 45305 | B15: 0 | E15: {=IF(B15=0,"",(J15+K15)/60)} | F15: =IF(B15=0,"",HOUR(D15-C15)+(MINUTE(D15-C15)/60)) | G15: =IF(B15=0,"",B15/F15) | H15: =IF(B15=0,"",B15/(F15-E15)) | I15: =IF(B15=0,"",B15/F15/AD15) | M15: =IFERROR(__xludf.DUMMYFUNCTION("""COMPUTED_VALUE"""),57.0) -> 57 | N15: =IFERROR(__xludf.DUMMYFUNCTION("""COMPUTED_VALUE"""),49.0) -> 49 | O15: =IFERROR(__xludf.DUMMYFUNCTION("""COMPUTED_VALUE"""),0.0) -> 0 | P15: =IFERROR(__xludf.DUMMYFUNCTION("""COMPUTED_VALUE"""),0.0) -> 0 | Q15: =IFERROR(__xludf.DUMMYFUNCTION("""COMPUTED_VALUE"""),0.0) -> 0 | R15: =IFERROR(__xludf.DUMMYFUNCTION("""COMPUTED_VALUE"""),0.0) -> 0 | S15: =IFERROR(__xludf.DUMMYFUNCTION("""COMPUTED_VALUE"""),0.0) -> 0 | T15: =IFERROR(__xludf.DUMMYFUNCTION("""COMPUTED_VALUE"""),0.0) -> 0 | U15: =IFERROR(__xludf.DUMMYFUNCTION("""COMPUTED_VALUE"""),6.0) -> 6 | V15: =IFERROR(__xludf.DUMMYFUNCTION("""COMPUTED_VALUE"""),0.0) -> 0 | W15: =IFERROR(__xludf.DUMMYFUNCTION("""COMPUTED_VALUE"""),0.0) -> 0 | X15: =IFERROR(__xludf.DUMMYFUNCTION("""COMPUTED_VALUE"""),0.0) -> 0 | Y15: =IFERROR(__xludf.DUMMYFUNCTION("""COMPUTED_VALUE"""),0.0) -> 0 | Z15: =IFERROR(__xludf.DUMMYFUNCTION("""COMPUTED_VALUE"""),0.0) -> 0 | AA15: =IFERROR(__xludf.DUMMYFUNCTION("""COMPUTED_VALUE"""),0.0) -> 0 | AB15: =IFERROR(__xludf.DUMMYFUNCTION("""COMPUTED_VALUE"""),0.0) -> 0 | AC15: =IFERROR(__xludf.DUMMYFUNCTION("""COMPUTED_VALUE"""),0.0) -> 0 | AD15: =IFERROR(__xludf.DUMMYFUNCTION("""COMPUTED_VALUE"""),0.0) -> 0 | AE15: =IFERROR(__xludf.DUMMYFUNCTION("""COMPUTED_VALUE"""),8.0) -> 8 | AF15: =IFERROR(__xludf.DUMMYFUNCTION("""COMPUTED_VALUE"""),8.0) -> 8 | AG15: ENERO | AH15: 2024
A16: =IF(B16="","",A15+1) -> 45306 | B16: 392 | C16: 0.51666667 | D16: 0.82291667 | E16: {=IF(B16=0,"",(J16+K16)/60)} -> 0.25 | F16: =IF(B16=0,"",HOUR(D16-C16)+(MINUTE(D16-C16)/60)) -> 7.35 | G16: =IF(B16=0,"",B16/F16) -> 53.333333 | H16: =IF(B16=0,"",B16/(F16-E16)) -> 55.211268 | I16: =IF(B16=0,"",B16/F16/AD16) -> 1.1111111 | J16: 15 | M16: =IFERROR(__xludf.DUMMYFUNCTION("""COMPUTED_VALUE"""),57.0) -> 57 | N16: =IFERROR(__xludf.DUMMYFUNCTION("""COMPUTED_VALUE"""),49.0) -> 49 | O16: =IFERROR(__xludf.DUMMYFUNCTION("""COMPUTED_VALUE"""),0.0) -> 0 | P16: =IFERROR(__xludf.DUMMYFUNCTION("""COMPUTED_VALUE"""),0.0) -> 0 | Q16: =IFERROR(__xludf.DUMMYFUNCTION("""COMPUTED_VALUE"""),0.0) -> 0 | R16: =IFERROR(__xludf.DUMMYFUNCTION("""COMPUTED_VALUE"""),0.0) -> 0 | S16: =IFERROR(__xludf.DUMMYFUNCTION("""COMPUTED_VALUE"""),0.0) -> 0 | T16: =IFERROR(__xludf.DUMMYFUNCTION("""COMPUTED_VALUE"""),0.0) -> 0 | U16: =IFERROR(__xludf.DUMMYFUNCTION("""COMPUTED_VALUE"""),6.0) -> 6 | V16: =IFERROR(__xludf.DUMMYFUNCTION("""COMPUTED_VALUE"""),3.0) -> 3 | W16: =IFERROR(__xludf.DUMMYFUNCTION("""COMPUTED_VALUE"""),0.0) -> 0 | X16: =IFERROR(__xludf.DUMMYFUNCTION("""COMPUTED_VALUE"""),0.0) -> 0 | Y16: =IFERROR(__xludf.DUMMYFUNCTION("""COMPUTED_VALUE"""),0.0) -> 0 | Z16: =IFERROR(__xludf.DUMMYFUNCTION("""COMPUTED_VALUE"""),0.0) -> 0 | AA16: =IFERROR(__xludf.DUMMYFUNCTION("""COMPUTED_VALUE"""),0.0) -> 0 | AB16: =IFERROR(__xludf.DUMMYFUNCTION("""COMPUTED_VALUE"""),0.0) -> 0 | AC16: =IFERROR(__xludf.DUMMYFUNCTION("""COMPUTED_VALUE"""),0.0) -> 0 | AD16: =IFERROR(__xludf.DUMMYFUNCTION("""COMPUTED_VALUE"""),48.0) -> 48 | AE16: =IFERROR(__xludf.DUMMYFUNCTION("""COMPUTED_VALUE"""),11.0) -> 11 | AF16: =IFERROR(__xludf.DUMMYFUNCTION("""COMPUTED_VALUE"""),8.0) -> 8 | AG16: ENERO | AH16: 2024
A17: =IF(B17="","",A16+1) -> 45307 | B17: 421 | C17: 0.51597222 | D17: 0.85625 | E17: {=IF(B17=0,"",(J17+K17)/60)} -> 0.25 | F17: =IF(B17=0,"",HOUR(D17-C17)+(MINUTE(D17-C17)/60)) -> 8.1666667 | G17: =IF(B17=0,"",B17/F17) -> 51.55102 | H17: =IF(B17=0,"",B17/(F17-E17)) -> 53.178947 | I17: =IF(B17=0,"",B17/F17/AD17) -> 1.0968302 | J17: 15 | M17: =IFERROR(__xludf.DUMMYFUNCTION("""COMPUTED_VALUE"""),57.0) -> 57 | N17: =IFERROR(__xludf.DUMMYFUNCTION("""COMPUTED_VALUE"""),49.0) -> 49 | O17: =IFERROR(__xludf.DUMMYFUNCTION("""COMPUTED_VALUE"""),0.0) -> 0 | P17: =IFERROR(__xludf.DUMMYFUNCTION("""COMPUTED_VALUE"""),0.0) -> 0 | Q17: =IFERROR(__xludf.DUMMYFUNCTION("""COMPUTED_VALUE"""),0.0) -> 0 | R17: =IFERROR(__xludf.DUMMYFUNCTION("""COMPUTED_VALUE"""),0.0) -> 0 | S17: =IFERROR(__xludf.DUMMYFUNCTION("""COMPUTED_VALUE"""),0.0) -> 0 | T17: =IFERROR(__xludf.DUMMYFUNCTION("""COMPUTED_VALUE"""),0.0) -> 0 | U17: =IFERROR(__xludf.DUMMYFUNCTION("""COMPUTED_VALUE"""),6.0) -> 6 | V17: =IFERROR(__xludf.DUMMYFUNCTION("""COMPUTED_VALUE"""),3.0) -> 3 | W17: =IFERROR(__xludf.DUMMYFUNCTION("""COMPUTED_VALUE"""),0.0) -> 0 | X17: =IFERROR(__xludf.DUMMYFUNCTION("""COMPUTED_VALUE"""),0.0) -> 0 | Y17: =IFERROR(__xludf.DUMMYFUNCTION("""COMPUTED_VALUE"""),0.0) -> 0 | Z17: =IFERROR(__xludf.DUMMYFUNCTION("""COMPUTED_VALUE"""),1.0) -> 1 | AA17: =IFERROR(__xludf.DUMMYFUNCTION("""COMPUTED_VALUE"""),0.0) -> 0 | AB17: =IFERROR(__xludf.DUMMYFUNCTION("""COMPUTED_VALUE"""),0.0) -> 0 | AC17: =IFERROR(__xludf.DUMMYFUNCTION("""COMPUTED_VALUE"""),0.0) -> 0 | AD17: =IFERROR(__xludf.DUMMYFUNCTION("""COMPUTED_VALUE"""),47.0) -> 47 | AE17: =IFERROR(__xludf.DUMMYFUNCTION("""COMPUTED_VALUE"""),12.0) -> 12 | AF17: =IFERROR(__xludf.DUMMYFUNCTION("""COMPUTED_VALUE"""),8.0) -> 8 | AG17: ENERO | AH17: 2024
A18: =IF(B18="","",A17+1) -> 45308 | B18: 482 | C18: 0.51666667 | D18: 0.88402778 | E18: {=IF(B18=0,"",(J18+K18)/60)} -> 0.25 | F18: =IF(B18=0,"",HOUR(D18-C18)+(MINUTE(D18-C18)/60)) -> 8.8166667 | G18: =IF(B18=0,"",B18/F18) -> 54.669187 | H18: =IF(B18=0,"",B18/(F18-E18)) -> 56.264591 | I18: =IF(B18=0,"",B18/F18/AD18) -> 1.1156977 | J18: 15 | M18: =IFERROR(__xludf.DUMMYFUNCTION("""COMPUTED_VALUE"""),57.0) -> 57 | N18: =IFERROR(__xludf.DUMMYFUNCTION("""COMPUTED_VALUE"""),51.0) -> 51 | O18: =IFERROR(__xludf.DUMMYFUNCTION("""COMPUTED_VALUE"""),0.0) -> 0 | P18: =IFERROR(__xludf.DUMMYFUNCTION("""COMPUTED_VALUE"""),0.0) -> 0 | Q18: =IFERROR(__xludf.DUMMYFUNCTION("""COMPUTED_VALUE"""),0.0) -> 0 | R18: =IFERROR(__xludf.DUMMYFUNCTION("""COMPUTED_VALUE"""),0.0) -> 0 | S18: =IFERROR(__xludf.DUMMYFUNCTION("""COMPUTED_VALUE"""),0.0) -> 0 | T18: =IFERROR(__xludf.DUMMYFUNCTION("""COMPUTED_VALUE"""),0.0) -> 0 | U18: =IFERROR(__xludf.DUMMYFUNCTION("""COMPUTED_VALUE"""),4.0) -> 4 | V18: =IFERROR(__xludf.DUMMYFUNCTION("""COMPUTED_VALUE"""),3.0) -> 3 | W18: =IFERROR(__xludf.DUMMYFUNCTION("""COMPUTED_VALUE"""),1.0) -> 1 | X18: =IFERROR(__xludf.DUMMYFUNCTION("""COMPUTED_VALUE"""),0.0) -> 0 | Y18: =IFERROR(__xludf.DUMMYFUNCTION("""COMPUTED_VALUE"""),0.0) -> 0 | Z18: =IFERROR(__xludf.DUMMYFUNCTION("""COMPUTED_VALUE"""),0.0) -> 0 | AA18: =IFERROR(__xludf.DUMMYFUNCTION("""COMPUTED_VALUE"""),0.0) -> 0 | AB18: =IFERROR(__xludf.DUMMYFUNCTION("""COMPUTED_VALUE"""),0.0) -> 0 | AC18: =IFERROR(__xludf.DUMMYFUNCTION("""COMPUTED_VALUE"""),0.0) -> 0 | AD18: =IFERROR(__xludf.DUMMYFUNCTION("""COMPUTED_VALUE"""),49.0) -> 49 | AE18: =IFERROR(__xludf.DUMMYFUNCTION("""COMPUTED_VALUE"""),10.0) -> 10 | AF18: =IFERROR(__xludf.DUMMYFUNCTION("""COMPUTED_VALUE"""),6.0) -> 6 | AG18: ENERO | AH18: 2024
A19: =IF(B19="","",A18+1) -> 45309 | B19: 484 | C19: 0.51597222 | D19: 0.89930556 | E19: {=IF(B19=0,"",(J19+K19)/60)} -> 0.25 | F19: =IF(B19=0,"",HOUR(D19-C19)+(MINUTE(D19-C19)/60)) -> 9.2 | G19: =IF(B19=0,"",B19/F19) -> 52.608696 | H19: =IF(B19=0,"",B19/(F19-E19)) -> 54.078212 | I19: =IF(B19=0,"",B19/F19/AD19) -> 1.0736469 | J19: 15 | M19: =IFERROR(__xludf.DUMMYFUNCTION("""COMPUTED_VALUE"""),57.0) -> 57 | N19: =IFERROR(__xludf.DUMMYFUNCTION("""COMPUTED_VALUE"""),51.0) -> 51 | O19: =IFERROR(__xludf.DUMMYFUNCTION("""COMPUTED_VALUE"""),0.0) -> 0 | P19: =IFERROR(__xludf.DUMMYFUNCTION("""COMPUTED_VALUE"""),0.0) -> 0 | Q19: =IFERROR(__xludf.DUMMYFUNCTION("""COMPUTED_VALUE"""),0.0) -> 0 | R19: =IFERROR(__xludf.DUMMYFUNCTION("""COMPUTED_VALUE"""),0.0) -> 0 | S19: =IFERROR(__xludf.DUMMYFUNCTION("""COMPUTED_VALUE"""),0.0) -> 0 | T19: =IFERROR(__xludf.DUMMYFUNCTION("""COMPUTED_VALUE"""),0.0) -> 0 | U19: =IFERROR(__xludf.DUMMYFUNCTION("""COMPUTED_VALUE"""),4.0) -> 4 | V19: =IFERROR(__xludf.DUMMYFUNCTION("""COMPUTED_VALUE"""),3.0) -> 3 | W19: =IFERROR(__xludf.DUMMYFUNCTION("""COMPUTED_VALUE"""),1.0) -> 1 | X19: =IFERROR(__xludf.DUMMYFUNCTION("""COMPUTED_VALUE"""),0.0) -> 0 | Y19: =IFERROR(__xludf.DUMMYFUNCTION("""COMPUTED_VALUE"""),0.0) -> 0 | Z19: =IFERROR(__xludf.DUMMYFUNCTION("""COMPUTED_VALUE"""),0.0) -> 0 | AA19: =IFERROR(__xludf.DUMMYFUNCTION("""COMPUTED_VALUE"""),0.0) -> 0 | AB19: =IFERROR(__xludf.DUMMYFUNCTION("""COMPUTED_VALUE"""),0.0) -> 0 | AC19: =IFERROR(__xludf.DUMMYFUNCTION("""COMPUTED_VALUE"""),0.0) -> 0 | AD19: =IFERROR(__xludf.DUMMYFUNCTION("""COMPUTED_VALUE"""),49.0) -> 49 | AE19: =IFERROR(__xludf.DUMMYFUNCTION("""COMPUTED_VALUE"""),10.0) -> 10 | AF19: =IFERROR(__xludf.DUMMYFUNCTION("""COMPUTED_VALUE"""),6.0) -> 6 | AG19: ENERO | AH19: 2024
A20: =IF(B20="","",A19+1) -> 45310 | B20: 464 | C20: 0.43333333 | D20: 0.80416667 | E20: {=IF(B20=0,"",(J20+K20)/60)} -> 1 | F20: =IF(B20=0,"",HOUR(D20-C20)+(MINUTE(D20-C20)/60)) -> 8.9 | G20: =IF(B20=0,"",B20/F20) -> 52.134831 | H20: =IF(B20=0,"",B20/(F20-E20)) -> 58.734177 | I20: =IF(B20=0,"",B20/F20/AD20) -> 1.0426966 | J20: 60 | M20: =IFERROR(__xludf.DUMMYFUNCTION("""COMPUTED_VALUE"""),57.0) -> 57 | N20: =IFERROR(__xludf.DUMMYFUNCTION("""COMPUTED_VALUE"""),51.0) -> 51 | O20: =IFERROR(__xludf.DUMMYFUNCTION("""COMPUTED_VALUE"""),0.0) -> 0 | P20: =IFERROR(__xludf.DUMMYFUNCTION("""COMPUTED_VALUE"""),0.0) -> 0 | Q20: =IFERROR(__xludf.DUMMYFUNCTION("""COMPUTED_VALUE"""),0.0) -> 0 | R20: =IFERROR(__xludf.DUMMYFUNCTION("""COMPUTED_VALUE"""),0.0) -> 0 | S20: =IFERROR(__xludf.DUMMYFUNCTION("""COMPUTED_VALUE"""),0.0) -> 0 | T20: =IFERROR(__xludf.DUMMYFUNCTION("""COMPUTED_VALUE"""),0.0) -> 0 | U20: =IFERROR(__xludf.DUMMYFUNCTION("""COMPUTED_VALUE"""),4.0) -> 4 | V20: =IFERROR(__xludf.DUMMYFUNCTION("""COMPUTED_VALUE"""),3.0) -> 3 | W20: =IFERROR(__xludf.DUMMYFUNCTION("""COMPUTED_VALUE"""),0.0) -> 0 | X20: =IFERROR(__xludf.DUMMYFUNCTION("""COMPUTED_VALUE"""),0.0) -> 0 | Y20: =IFERROR(__xludf.DUMMYFUNCTION("""COMPUTED_VALUE"""),0.0) -> 0 | Z20: =IFERROR(__xludf.DUMMYFUNCTION("""COMPUTED_VALUE"""),0.0) -> 0 | AA20: =IFERROR(__xludf.DUMMYFUNCTION("""COMPUTED_VALUE"""),0.0) -> 0 | AB20: =IFERROR(__xludf.DUMMYFUNCTION("""COMPUTED_VALUE"""),0.0) -> 0 | AC20: =IFERROR(__xludf.DUMMYFUNCTION("""COMPUTED_VALUE"""),0.0) -> 0 | AD20: =IFERROR(__xludf.DUMMYFUNCTION("""COMPUTED_VALUE"""),50.0) -> 50 | AE20: =IFERROR(__xludf.DUMMYFUNCTION("""COMPUTED_VALUE"""),9.0) -> 9 | AF20: =IFERROR(__xludf.DUMMYFUNCTION("""COMPUTED_VALUE"""),6.0) -> 6 | AG20: ENERO | AH20: 2024
A21: =IF(B21="","",A20+1) -> 45311 | B21: 427 | C21: 0.43263889 | D21: 0.77430556 | E21: {=IF(B21=0,"",(J21+K21)/60)} -> 1 | F21: =IF(B21=0,"",HOUR(D21-C21)+(MINUTE(D21-C21)/60)) -> 8.2 | G21: =IF(B21=0,"",B21/F21) -> 52.073171 | H21: =IF(B21=0,"",B21/(F21-E21)) -> 59.305556 | I21: =IF(B21=0,"",B21/F21/AD21) -> 1.0414634 | J21: 60 | M21: =IFERROR(__xludf.DUMMYFUNCTION("""COMPUTED_VALUE"""),57.0) -> 57 | N21: =IFERROR(__xludf.DUMMYFUNCTION("""COMPUTED_VALUE"""),51.0) -> 51 | O21: =IFERROR(__xludf.DUMMYFUNCTION("""COMPUTED_VALUE"""),0.0) -> 0 | P21: =IFERROR(__xludf.DUMMYFUNCTION("""COMPUTED_VALUE"""),0.0) -> 0 | Q21: =IFERROR(__xludf.DUMMYFUNCTION("""COMPUTED_VALUE"""),0.0) -> 0 | R21: =IFERROR(__xludf.DUMMYFUNCTION("""COMPUTED_VALUE"""),0.0) -> 0 | S21: =IFERROR(__xludf.DUMMYFUNCTION("""COMPUTED_VALUE"""),0.0) -> 0 | T21: =IFERROR(__xludf.DUMMYFUNCTION("""COMPUTED_VALUE"""),0.0) -> 0 | U21: =IFERROR(__xludf.DUMMYFUNCTION("""COMPUTED_VALUE"""),4.0) -> 4 | V21: =IFERROR(__xludf.DUMMYFUNCTION("""COMPUTED_VALUE"""),0.0) -> 0 | W21: =IFERROR(__xludf.DUMMYFUNCTION("""COMPUTED_VALUE"""),0.0) -> 0 | X21: =IFERROR(__xludf.DUMMYFUNCTION("""COMPUTED_VALUE"""),0.0) -> 0 | Y21: =IFERROR(__xludf.DUMMYFUNCTION("""COMPUTED_VALUE"""),0.0) -> 0 | Z21: =IFERROR(__xludf.DUMMYFUNCTION("""COMPUTED_VALUE"""),0.0) -> 0 | AA21: =IFERROR(__xludf.DUMMYFUNCTION("""COMPUTED_VALUE"""),2.0) -> 2 | AB21: =IFERROR(__xludf.DUMMYFUNCTION("""COMPUTED_VALUE"""),0.0) -> 0 | AC21: =IFERROR(__xludf.DUMMYFUNCTION("""COMPUTED_VALUE"""),0.0) -> 0 | AD21: =IFERROR(__xludf.DUMMYFUNCTION("""COMPUTED_VALUE"""),50.0) -> 50 | AE21: =IFERROR(__xludf.DUMMYFUNCTION("""COMPUTED_VALUE"""),8.0) -> 8 | AF21: =IFERROR(__xludf.DUMMYFUNCTION("""COMPUTED_VALUE"""),6.0) -> 6 | AG21: ENERO | AH21: 2024
A22: =IF(B22="","",A21+1) -> 45312 | B22: 0 | E22: {=IF(B22=0,"",(J22+K22)/60)} | F22: =IF(B22=0,"",HOUR(D22-C22)+(MINUTE(D22-C22)/60)) | G22: =IF(B22=0,"",B22/F22) | H22: =IF(B22=0,"",B22/(F22-E22)) | I22: =IF(B22=0,"",B22/F22/AD22) | M22: =IFERROR(__xludf.DUMMYFUNCTION("""COMPUTED_VALUE"""),57.0) -> 57 | N22: =IFERROR(__xludf.DUMMYFUNCTION("""COMPUTED_VALUE"""),51.0) -> 51 | O22: =IFERROR(__xludf.DUMMYFUNCTION("""COMPUTED_VALUE"""),0.0) -> 0 | P22: =IFERROR(__xludf.DUMMYFUNCTION("""COMPUTED_VALUE"""),0.0) -> 0 | Q22: =IFERROR(__xludf.DUMMYFUNCTION("""COMPUTED_VALUE"""),0.0) -> 0 | R22: =IFERROR(__xludf.DUMMYFUNCTION("""COMPUTED_VALUE"""),0.0) -> 0 | S22: =IFERROR(__xludf.DUMMYFUNCTION("""COMPUTED_VALUE"""),0.0) -> 0 | T22: =IFERROR(__xludf.DUMMYFUNCTION("""COMPUTED_VALUE"""),0.0) -> 0 | U22: =IFERROR(__xludf.DUMMYFUNCTION("""COMPUTED_VALUE"""),4.0) -> 4 | V22: =IFERROR(__xludf.DUMMYFUNCTION("""COMPUTED_VALUE"""),0.0) -> 0 | W22: =IFERROR(__xludf.DUMMYFUNCTION("""COMPUTED_VALUE"""),0.0) -> 0 | X22: =IFERROR(__xludf.DUMMYFUNCTION("""COMPUTED_VALUE"""),0.0) -> 0 | Y22: =IFERROR(__xludf.DUMMYFUNCTION("""COMPUTED_VALUE"""),0.0) -> 0 | Z22: =IFERROR(__xludf.DUMMYFUNCTION("""COMPUTED_VALUE"""),0.0) -> 0 | AA22: =IFERROR(__xludf.DUMMYFUNCTION("""COMPUTED_VALUE"""),0.0) -> 0 | AB22: =IFERROR(__xludf.DUMMYFUNCTION("""COMPUTED_VALUE"""),0.0) -> 0 | AC22: =IFERROR(__xludf.DUMMYFUNCTION("""COMPUTED_VALUE"""),0.0) -> 0 | AD22: =IFERROR(__xludf.DUMMYFUNCTION("""COMPUTED_VALUE"""),0.0) -> 0 | AE22: =IFERROR(__xludf.DUMMYFUNCTION("""COMPUTED_VALUE"""),6.0) -> 6 | AF22: =IFERROR(__xludf.DUMMYFUNCTION("""COMPUTED_VALUE"""),6.0) -> 6 | AG22: ENERO | AH22: 2024
A23: =IF(B23="","",A22+1) -> 45313 | B23: 391 | C23: 0.51597222 | D23: 0.83055556 | E23: {=IF(B23=0,"",(J23+K23)/60)} -> 0.25 | F23: =IF(B23=0,"",HOUR(D23-C23)+(MINUTE(D23-C23)/60)) -> 7.55 | G23: =IF(B23=0,"",B23/F23) -> 51.788079 | H23: =IF(B23=0,"",B23/(F23-E23)) -> 53.561644 | I23: =IF(B23=0,"",B23/F23/AD23) -> 1.0789183 | J23: 15 | M23: =IFERROR(__xludf.DUMMYFUNCTION("""COMPUTED_VALUE"""),57.0) -> 57 | N23: =IFERROR(__xludf.DUMMYFUNCTION("""COMPUTED_VALUE"""),51.0) -> 51 | O23: =IFERROR(__xludf.DUMMYFUNCTION("""COMPUTED_VALUE"""),1.0) -> 1 | P23: =IFERROR(__xludf.DUMMYFUNCTION("""COMPUTED_VALUE"""),0.0) -> 0 | Q23: =IFERROR(__xludf.DUMMYFUNCTION("""COMPUTED_VALUE"""),0.0) -> 0 | R23: =IFERROR(__xludf.DUMMYFUNCTION("""COMPUTED_VALUE"""),0.0) -> 0 | S23: =IFERROR(__xludf.DUMMYFUNCTION("""COMPUTED_VALUE"""),0.0) -> 0 | T23: =IFERROR(__xludf.DUMMYFUNCTION("""COMPUTED_VALUE"""),0.0) -> 0 | U23: =IFERROR(__xludf.DUMMYFUNCTION("""COMPUTED_VALUE"""),4.0) -> 4 | V23: =IFERROR(__xludf.DUMMYFUNCTION("""COMPUTED_VALUE"""),3.0) -> 3 | W23: =IFERROR(__xludf.DUMMYFUNCTION("""COMPUTED_VALUE"""),0.0) -> 0 | X23: =IFERROR(__xludf.DUMMYFUNCTION("""COMPUTED_VALUE"""),0.0) -> 0 | Y23: =IFERROR(__xludf.DUMMYFUNCTION("""COMPUTED_VALUE"""),0.0) -> 0 | Z23: =IFERROR(__xludf.DUMMYFUNCTION("""COMPUTED_VALUE"""),0.0) -> 0 | AA23: =IFERROR(__xludf.DUMMYFUNCTION("""COMPUTED_VALUE"""),0.0) -> 0 | AB23: =IFERROR(__xludf.DUMMYFUNCTION("""COMPUTED_VALUE"""),0.0) -> 0 | AC23: =IFERROR(__xludf.DUMMYFUNCTION("""COMPUTED_VALUE"""),0.0) -> 0 | AD23: =IFERROR(__xludf.DUMMYFUNCTION("""COMPUTED_VALUE"""),48.0) -> 48 | AE23: =IFERROR(__xludf.DUMMYFUNCTION("""COMPUTED_VALUE"""),10.0) -> 10 | AF23: =IFERROR(__xludf.DUMMYFUNCTION("""COMPUTED_VALUE"""),6.0) -> 6 | AG23: ENERO | AH23: 2024
A24: =IF(B24="","",A23+1) -> 45314 | B24: 533 | C24: 0.51666667 | D24: 0.91666667 | E24: {=IF(B24=0,"",(J24+K24)/60)} -> 0.25 | F24: =IF(B24=0,"",HOUR(D24-C24)+(MINUTE(D24-C24)/60)) -> 9.6 | G24: =IF(B24=0,"",B24/F24) -> 55.520833 | H24: =IF(B24=0,"",B24/(F24-E24)) -> 57.005348 | I24: =IF(B24=0,"",B24/F24/AD24) -> 1.1330782 | J24: 15 | M24: =IFERROR(__xludf.DUMMYFUNCTION("""COMPUTED_VALUE"""),57.0) -> 57 | N24: =IFERROR(__xludf.DUMMYFUNCTION("""COMPUTED_VALUE"""),54.0) -> 54 | O24: =IFERROR(__xludf.DUMMYFUNCTION("""COMPUTED_VALUE"""),0.0) -> 0 | P24: =IFERROR(__xludf.DUMMYFUNCTION("""COMPUTED_VALUE"""),1.0) -> 1 | Q24: =IFERROR(__xludf.DUMMYFUNCTION("""COMPUTED_VALUE"""),0.0) -> 0 | R24: =IFERROR(__xludf.DUMMYFUNCTION("""COMPUTED_VALUE"""),0.0) -> 0 | S24: =IFERROR(__xludf.DUMMYFUNCTION("""COMPUTED_VALUE"""),0.0) -> 0 | T24: =IFERROR(__xludf.DUMMYFUNCTION("""COMPUTED_VALUE"""),0.0) -> 0 | U24: =IFERROR(__xludf.DUMMYFUNCTION("""COMPUTED_VALUE"""),1.0) -> 1 | V24: =IFERROR(__xludf.DUMMYFUNCTION("""COMPUTED_VALUE"""),3.0) -> 3 | W24: =IFERROR(__xludf.DUMMYFUNCTION("""COMPUTED_VALUE"""),0.0) -> 0 | X24: =IFERROR(__xludf.DUMMYFUNCTION("""COMPUTED_VALUE"""),0.0) -> 0 | Y24: =IFERROR(__xludf.DUMMYFUNCTION("""COMPUTED_VALUE"""),0.0) -> 0 | Z24: =IFERROR(__xludf.DUMMYFUNCTION("""COMPUTED_VALUE"""),0.0) -> 0 | AA24: =IFERROR(__xludf.DUMMYFUNCTION("""COMPUTED_VALUE"""),0.0) -> 0 | AB24: =IFERROR(__xludf.DUMMYFUNCTION("""COMPUTED_VALUE"""),2.0) -> 2 | AC24: =IFERROR(__xludf.DUMMYFUNCTION("""COMPUTED_VALUE"""),0.0) -> 0 | AD24: =IFERROR(__xludf.DUMMYFUNCTION("""COMPUTED_VALUE"""),49.0) -> 49 | AE24: =IFERROR(__xludf.DUMMYFUNCTION("""COMPUTED_VALUE"""),7.0) -> 7 | AF24: =IFERROR(__xludf.DUMMYFUNCTION("""COMPUTED_VALUE"""),3.0) -> 3 | AG24: ENERO | AH24: 2024
A25: =IF(B25="","",A24+1) -> 45315 | B25: 516 | C25: 0.6 | D25: 0.96388889 | E25: {=IF(B25=0,"",(J25+K25)/60)} -> 0.25 | F25: =IF(B25=0,"",HOUR(D25-C25)+(MINUTE(D25-C25)/60)) -> 8.7333333 | G25: =IF(B25=0,"",B25/F25) -> 59.083969 | H25: =IF(B25=0,"",B25/(F25-E25)) -> 60.825147 | I25: =IF(B25=0,"",B25/F25/AD25) -> 1.1585092 | J25: 15 | M25: =IFERROR(__xludf.DUMMYFUNCTION("""COMPUTED_VALUE"""),57.0) -> 57 | N25: =IFERROR(__xludf.DUMMYFUNCTION("""COMPUTED_VALUE"""),54.0) -> 54 | O25: =IFERROR(__xludf.DUMMYFUNCTION("""COMPUTED_VALUE"""),1.0) -> 1 | P25: =IFERROR(__xludf.DUMMYFUNCTION("""COMPUTED_VALUE"""),0.0) -> 0 | Q25: =IFERROR(__xludf.DUMMYFUNCTION("""COMPUTED_VALUE"""),0.0) -> 0 | R25: =IFERROR(__xludf.DUMMYFUNCTION("""COMPUTED_VALUE"""),0.0) -> 0 | S25: =IFERROR(__xludf.DUMMYFUNCTION("""COMPUTED_VALUE"""),0.0) -> 0 | T25: =IFERROR(__xludf.DUMMYFUNCTION("""COMPUTED_VALUE"""),0.0) -> 0 | U25: =IFERROR(__xludf.DUMMYFUNCTION("""COMPUTED_VALUE"""),1.0) -> 1 | V25: =IFERROR(__xludf.DUMMYFUNCTION("""COMPUTED_VALUE"""),3.0) -> 3 | W25: =IFERROR(__xludf.DUMMYFUNCTION("""COMPUTED_VALUE"""),0.0) -> 0 | X25: =IFERROR(__xludf.DUMMYFUNCTION("""COMPUTED_VALUE"""),0.0) -> 0 | Y25: =IFERROR(__xludf.DUMMYFUNCTION("""COMPUTED_VALUE"""),0.0) -> 0 | Z25: =IFERROR(__xludf.DUMMYFUNCTION("""COMPUTED_VALUE"""),0.0) -> 0 | AA25: =IFERROR(__xludf.DUMMYFUNCTION("""COMPUTED_VALUE"""),0.0) -> 0 | AB25: =IFERROR(__xludf.DUMMYFUNCTION("""COMPUTED_VALUE"""),0.0) -> 0 | AC25: =IFERROR(__xludf.DUMMYFUNCTION("""COMPUTED_VALUE"""),0.0) -> 0 | AD25: =IFERROR(__xludf.DUMMYFUNCTION("""COMPUTED_VALUE"""),51.0) -> 51 | AE25: =IFERROR(__xludf.DUMMYFUNCTION("""COMPUTED_VALUE"""),7.0) -> 7 | AF25: =IFERROR(__xludf.DUMMYFUNCTION("""COMPUTED_VALUE"""),3.0) -> 3 | AG25: ENERO | AH25: 2024
A26: =IF(B26="","",A25+1) -> 45316 | B26: 526 | C26: 0.59930556 | D26: 0.98125 | E26: {=IF(B26=0,"",(J26+K26)/60)} -> 0.25 | F26: =IF(B26=0,"",HOUR(D26-C26)+(MINUTE(D26-C26)/60)) -> 9.1666667 | G26: =IF(B26=0,"",B26/F26) -> 57.381818 | H26: =IF(B26=0,"",B26/(F26-E26)) -> 58.990654 | I26: =IF(B26=0,"",B26/F26/AD26) -> 1.1476364 | J26: 15 | M26: =IFERROR(__xludf.DUMMYFUNCTION("""COMPUTED_VALUE"""),57.0) -> 57 | N26: =IFERROR(__xludf.DUMMYFUNCTION("""COMPUTED_VALUE"""),54.0) -> 54 | O26: =IFERROR(__xludf.DUMMYFUNCTION("""COMPUTED_VALUE"""),1.0) -> 1 | P26: =IFERROR(__xludf.DUMMYFUNCTION("""COMPUTED_VALUE"""),0.0) -> 0 | Q26: =IFERROR(__xludf.DUMMYFUNCTION("""COMPUTED_VALUE"""),0.0) -> 0 | R26: =IFERROR(__xludf.DUMMYFUNCTION("""COMPUTED_VALUE"""),0.0) -> 0 | S26: =IFERROR(__xludf.DUMMYFUNCTION("""COMPUTED_VALUE"""),1.0) -> 1 | T26: =IFERROR(__xludf.DUMMYFUNCTION("""COMPUTED_VALUE"""),0.0) -> 0 | U26: =IFERROR(__xludf.DUMMYFUNCTION("""COMPUTED_VALUE"""),1.0) -> 1 | V26: =IFERROR(__xludf.DUMMYFUNCTION("""COMPUTED_VALUE"""),3.0) -> 3 | W26: =IFERROR(__xludf.DUMMYFUNCTION("""COMPUTED_VALUE"""),0.0) -> 0 | X26: =IFERROR(__xludf.DUMMYFUNCTION("""COMPUTED_VALUE"""),0.0) -> 0 | Y26: =IFERROR(__xludf.DUMMYFUNCTION("""COMPUTED_VALUE"""),0.0) -> 0 | Z26: =IFERROR(__xludf.DUMMYFUNCTION("""COMPUTED_VALUE"""),0.0) -> 0 | AA26: =IFERROR(__xludf.DUMMYFUNCTION("""COMPUTED_VALUE"""),0.0) -> 0 | AB26: =IFERROR(__xludf.DUMMYFUNCTION("""COMPUTED_VALUE"""),0.0) -> 0 | AC26: =IFERROR(__xludf.DUMMYFUNCTION("""COMPUTED_VALUE"""),0.0) -> 0 | AD26: =IFERROR(__xludf.DUMMYFUNCTION("""COMPUTED_VALUE"""),50.0) -> 50 | AE26: =IFERROR(__xludf.DUMMYFUNCTION("""COMPUTED_VALUE"""),8.0) -> 8 | AF26: =IFERROR(__xludf.DUMMYFUNCTION("""COMPUTED_VALUE"""),3.0) -> 3 | AG26: ENERO | AH26: 2024
A27: =IF(B27="","",A26+1) -> 45317 | B27: 476 | C27: 0.6 | D27: 0.96527778 | E27: {=IF(B27=0,"",(J27+K27)/60)} -> 0.25 | F27: =IF(B27=0,"",HOUR(D27-C27)+(MINUTE(D27-C27)/60)) -> 8.7666667 | G27: =IF(B27=0,"",B27/F27) -> 54.296578 | H27: =IF(B27=0,"",B27/(F27-E27)) -> 55.890411 | I27: =IF(B27=0,"",B27/F27/AD27) -> 1.0646388 | J27: 15 | M27: =IFERROR(__xludf.DUMMYFUNCTION("""COMPUTED_VALUE"""),57.0) -> 57 | N27: =IFERROR(__xludf.DUMMYFUNCTION("""COMPUTED_VALUE"""),54.0) -> 54 | O27: =IFERROR(__xludf.DUMMYFUNCTION("""COMPUTED_VALUE"""),0.0) -> 0 | P27: =IFERROR(__xludf.DUMMYFUNCTION("""COMPUTED_VALUE"""),0.0) -> 0 | Q27: =IFERROR(__xludf.DUMMYFUNCTION("""COMPUTED_VALUE"""),0.0) -> 0 | R27: =IFERROR(__xludf.DUMMYFUNCTION("""COMPUTED_VALUE"""),0.0) -> 0 | S27: =IFERROR(__xludf.DUMMYFUNCTION("""COMPUTED_VALUE"""),1.0) -> 1 | T27: =IFERROR(__xludf.DUMMYFUNCTION("""COMPUTED_VALUE"""),0.0) -> 0 | U27: =IFERROR(__xludf.DUMMYFUNCTION("""COMPUTED_VALUE"""),1.0) -> 1 | V27: =IFERROR(__xludf.DUMMYFUNCTION("""COMPUTED_VALUE"""),3.0) -> 3 | W27: =IFERROR(__xludf.DUMMYFUNCTION("""COMPUTED_VALUE"""),0.0) -> 0 | X27: =IFERROR(__xludf.DUMMYFUNCTION("""COMPUTED_VALUE"""),0.0) -> 0 | Y27: =IFERROR(__xludf.DUMMYFUNCTION("""COMPUTED_VALUE"""),0.0) -> 0 | Z27: =IFERROR(__xludf.DUMMYFUNCTION("""COMPUTED_VALUE"""),0.0) -> 0 | AA27: =IFERROR(__xludf.DUMMYFUNCTION("""COMPUTED_VALUE"""),0.0) -> 0 | AB27: =IFERROR(__xludf.DUMMYFUNCTION("""COMPUTED_VALUE"""),0.0) -> 0 | AC27: =IFERROR(__xludf.DUMMYFUNCTION("""COMPUTED_VALUE"""),0.0) -> 0 | AD27: =IFERROR(__xludf.DUMMYFUNCTION("""COMPUTED_VALUE"""),51.0) -> 51 | AE27: =IFERROR(__xludf.DUMMYFUNCTION("""COMPUTED_VALUE"""),7.0) -> 7 | AF27: =IFERROR(__xludf.DUMMYFUNCTION("""COMPUTED_VALUE"""),3.0) -> 3 | AG27: ENERO | AH27: 2024
A28: =IF(B28="","",A27+1) -> 45318 | B28: 346 | C28: 0.6 | D28: 0.875 | E28: {=IF(B28=0,"",(J28+K28)/60)} -> 0.75 | F28: =IF(B28=0,"",HOUR(D28-C28)+(MINUTE(D28-C28)/60)) -> 6.6 | G28: =IF(B28=0,"",B28/F28) -> 52.424242 | H28: =IF(B28=0,"",B28/(F28-E28)) -> 59.145299 | I28: =IF(B28=0,"",B28/F28/AD28) -> 1.0698825 | J28: 0 | K28: 45 | M28: =IFERROR(__xludf.DUMMYFUNCTION("""COMPUTED_VALUE"""),57.0) -> 57 | N28: =IFERROR(__xludf.DUMMYFUNCTION("""COMPUTED_VALUE"""),54.0) -> 54 | O28: =IFERROR(__xludf.DUMMYFUNCTION("""COMPUTED_VALUE"""),1.0) -> 1 | P28: =IFERROR(__xludf.DUMMYFUNCTION("""COMPUTED_VALUE"""),1.0) -> 1 | Q28: =IFERROR(__xludf.DUMMYFUNCTION("""COMPUTED_VALUE"""),0.0) -> 0 | R28: =IFERROR(__xludf.DUMMYFUNCTION("""COMPUTED_VALUE"""),0.0) -> 0 | S28: =IFERROR(__xludf.DUMMYFUNCTION("""COMPUTED_VALUE"""),1.0) -> 1 | T28: =IFERROR(__xludf.DUMMYFUNCTION("""COMPUTED_VALUE"""),0.0) -> 0 | U28: =IFERROR(__xludf.DUMMYFUNCTION("""COMPUTED_VALUE"""),1.0) -> 1 | V28: =IFERROR(__xludf.DUMMYFUNCTION("""COMPUTED_VALUE"""),3.0) -> 3 | W28: =IFERROR(__xludf.DUMMYFUNCTION("""COMPUTED_VALUE"""),0.0) -> 0 | X28: =IFERROR(__xludf.DUMMYFUNCTION("""COMPUTED_VALUE"""),0.0) -> 0 | Y28: =IFERROR(__xludf.DUMMYFUNCTION("""COMPUTED_VALUE"""),0.0) -> 0 | Z28: =IFERROR(__xludf.DUMMYFUNCTION("""COMPUTED_VALUE"""),0.0) -> 0 | AA28: =IFERROR(__xludf.DUMMYFUNCTION("""COMPUTED_VALUE"""),0.0) -> 0 | AB28: =IFERROR(__xludf.DUMMYFUNCTION("""COMPUTED_VALUE"""),0.0) -> 0 | AC28: =IFERROR(__xludf.DUMMYFUNCTION("""COMPUTED_VALUE"""),0.0) -> 0 | AD28: =IFERROR(__xludf.DUMMYFUNCTION("""COMPUTED_VALUE"""),49.0) -> 49 | AE28: =IFERROR(__xludf.DUMMYFUNCTION("""COMPUTED_VALUE"""),9.0) -> 9 | AF28: =IFERROR(__xludf.DUMMYFUNCTION("""COMPUTED_VALUE"""),3.0) -> 3 | AG28: ENERO | AH28: 2024
A29: =IF(B29="","",A28+1) -> 45319 | B29: 0 | E29: {=IF(B29=0,"",(J29+K29)/60)} | F29: =IF(B29=0,"",HOUR(D29-C29)+(MINUTE(D29-C29)/60)) | G29: =IF(B29=0,"",B29/F29) | H29: =IF(B29=0,"",B29/(F29-E29)) | I29: =IF(B29=0,"",B29/F29/AD29) | M29: =IFERROR(__xludf.DUMMYFUNCTION("""COMPUTED_VALUE"""),57.0) -> 57 | N29: =IFERROR(__xludf.DUMMYFUNCTION("""COMPUTED_VALUE"""),54.0) -> 54 | O29: =IFERROR(__xludf.DUMMYFUNCTION("""COMPUTED_VALUE"""),0.0) -> 0 | P29: =IFERROR(__xludf.DUMMYFUNCTION("""COMPUTED_VALUE"""),0.0) -> 0 | Q29: =IFERROR(__xludf.DUMMYFUNCTION("""COMPUTED_VALUE"""),0.0) -> 0 | R29: =IFERROR(__xludf.DUMMYFUNCTION("""COMPUTED_VALUE"""),0.0) -> 0 | S29: =IFERROR(__xludf.DUMMYFUNCTION("""COMPUTED_VALUE"""),0.0) -> 0 | T29: =IFERROR(__xludf.DUMMYFUNCTION("""COMPUTED_VALUE"""),0.0) -> 0 | U29: =IFERROR(__xludf.DUMMYFUNCTION("""COMPUTED_VALUE"""),1.0) -> 1 | V29: =IFERROR(__xludf.DUMMYFUNCTION("""COMPUTED_VALUE"""),0.0) -> 0 | W29: =IFERROR(__xludf.DUMMYFUNCTION("""COMPUTED_VALUE"""),0.0) -> 0 | X29: =IFERROR(__xludf.DUMMYFUNCTION("""COMPUTED_VALUE"""),0.0) -> 0 | Y29: =IFERROR(__xludf.DUMMYFUNCTION("""COMPUTED_VALUE"""),0.0) -> 0 | Z29: =IFERROR(__xludf.DUMMYFUNCTION("""COMPUTED_VALUE"""),0.0) -> 0 | AA29: =IFERROR(__xludf.DUMMYFUNCTION("""COMPUTED_VALUE"""),0.0) -> 0 | AB29: =IFERROR(__xludf.DUMMYFUNCTION("""COMPUTED_VALUE"""),0.0) -> 0 | AC29: =IFERROR(__xludf.DUMMYFUNCTION("""COMPUTED_VALUE"""),0.0) -> 0 | AD29: =IFERROR(__xludf.DUMMYFUNCTION("""COMPUTED_VALUE"""),0.0) -> 0 | AE29: =IFERROR(__xludf.DUMMYFUNCTION("""COMPUTED_VALUE"""),3.0) -> 3 | AF29: =IFERROR(__xludf.DUMMYFUNCTION("""COMPUTED_VALUE"""),3.0) -> 3 | AG29: ENERO | AH29: 2024
A30: =IF(B30="","",A29+1) -> 45320 | B30: 270 | C30: 0.6 | D30: 0.81875 | E30: {=IF(B30=0,"",(J30+K30)/60)} -> 0.25 | F30: =IF(B30=0,"",HOUR(D30-C30)+(MINUTE(D30-C30)/60)) -> 5.25 | G30: =IF(B30=0,"",B30/F30) -> 51.428571 | H30: =IF(B30=0,"",B30/(F30-E30)) -> 54 | I30: =IF(B30=0,"",B30/F30/AD30) -> 0.98901099 | J30: 15 | M30: =IFERROR(__xludf.DUMMYFUNCTION("""COMPUTED_VALUE"""),57.0) -> 57 | N30: =IFERROR(__xludf.DUMMYFUNCTION("""COMPUTED_VALUE"""),54.0) -> 54 | O30: =IFERROR(__xludf.DUMMYFUNCTION("""COMPUTED_VALUE"""),0.0) -> 0 | P30: =IFERROR(__xludf.DUMMYFUNCTION("""COMPUTED_VALUE"""),0.0) -> 0 | Q30: =IFERROR(__xludf.DUMMYFUNCTION("""COMPUTED_VALUE"""),0.0) -> 0 | R30: =IFERROR(__xludf.DUMMYFUNCTION("""COMPUTED_VALUE"""),0.0) -> 0 | S30: =IFERROR(__xludf.DUMMYFUNCTION("""COMPUTED_VALUE"""),0.0) -> 0 | T30: =IFERROR(__xludf.DUMMYFUNCTION("""COMPUTED_VALUE"""),0.0) -> 0 | U30: =IFERROR(__xludf.DUMMYFUNCTION("""COMPUTED_VALUE"""),1.0) -> 1 | V30: =IFERROR(__xludf.DUMMYFUNCTION("""COMPUTED_VALUE"""),3.0) -> 3 | W30: =IFERROR(__xludf.DUMMYFUNCTION("""COMPUTED_VALUE"""),0.0) -> 0 | X30: =IFERROR(__xludf.DUMMYFUNCTION("""COMPUTED_VALUE"""),0.0) -> 0 | Y30: =IFERROR(__xludf.DUMMYFUNCTION("""COMPUTED_VALUE"""),0.0) -> 0 | Z30: =IFERROR(__xludf.DUMMYFUNCTION("""COMPUTED_VALUE"""),0.0) -> 0 | AA30: =IFERROR(__xludf.DUMMYFUNCTION("""COMPUTED_VALUE"""),0.0) -> 0 | AB30: =IFERROR(__xludf.DUMMYFUNCTION("""COMPUTED_VALUE"""),0.0) -> 0 | AC30: =IFERROR(__xludf.DUMMYFUNCTION("""COMPUTED_VALUE"""),0.0) -> 0 | AD30: =IFERROR(__xludf.DUMMYFUNCTION("""COMPUTED_VALUE"""),52.0) -> 52 | AE30: =IFERROR(__xludf.DUMMYFUNCTION("""COMPUTED_VALUE"""),6.0) -> 6 | AF30: =IFERROR(__xludf.DUMMYFUNCTION("""COMPUTED_VALUE"""),3.0) -> 3 | AG30: ENERO | AH30: 2024
A31: =IF(B31="","",A30+1) -> 45321 | B31: 390 | C31: 0.6 | D31: 0.89583333 | E31: {=IF(B31=0,"",(J31+K31)/60)} -> 0.25 | F31: =IF(B31=0,"",HOUR(D31-C31)+(MINUTE(D31-C31)/60)) -> 7.1 | G31: =IF(B31=0,"",B31/F31) -> 54.929577 | H31: =IF(B31=0,"",B31/(F31-E31)) -> 56.934307 | I31: =IF(B31=0,"",B31/F31/AD31) -> 1.0770505 | J31: 15 | M31: =IFERROR(__xludf.DUMMYFUNCTION("""COMPUTED_VALUE"""),57.0) -> 57 | N31: =IFERROR(__xludf.DUMMYFUNCTION("""COMPUTED_VALUE"""),54.0) -> 54 | O31: =IFERROR(__xludf.DUMMYFUNCTION("""COMPUTED_VALUE"""),0.0) -> 0 | P31: =IFERROR(__xludf.DUMMYFUNCTION("""COMPUTED_VALUE"""),0.0) -> 0 | Q31: =IFERROR(__xludf.DUMMYFUNCTION("""COMPUTED_VALUE"""),0.0) -> 0 | R31: =IFERROR(__xludf.DUMMYFUNCTION("""COMPUTED_VALUE"""),0.0) -> 0 | S31: =IFERROR(__xludf.DUMMYFUNCTION("""COMPUTED_VALUE"""),1.0) -> 1 | T31: =IFERROR(__xludf.DUMMYFUNCTION("""COMPUTED_VALUE"""),0.0) -> 0 | U31: =IFERROR(__xludf.DUMMYFUNCTION("""COMPUTED_VALUE"""),1.0) -> 1 | V31: =IFERROR(__xludf.DUMMYFUNCTION("""COMPUTED_VALUE"""),3.0) -> 3 | W31: =IFERROR(__xludf.DUMMYFUNCTION("""COMPUTED_VALUE"""),0.0) -> 0 | X31: =IFERROR(__xludf.DUMMYFUNCTION("""COMPUTED_VALUE"""),0.0) -> 0 | Y31: =IFERROR(__xludf.DUMMYFUNCTION("""COMPUTED_VALUE"""),0.0) -> 0 | Z31: =IFERROR(__xludf.DUMMYFUNCTION("""COMPUTED_VALUE"""),0.0) -> 0 | AA31: =IFERROR(__xludf.DUMMYFUNCTION("""COMPUTED_VALUE"""),0.0) -> 0 | AB31: =IFERROR(__xludf.DUMMYFUNCTION("""COMPUTED_VALUE"""),0.0) -> 0 | AC31: =IFERROR(__xludf.DUMMYFUNCTION("""COMPUTED_VALUE"""),0.0) -> 0 | AD31: =IFERROR(__xludf.DUMMYFUNCTION("""COMPUTED_VALUE"""),51.0) -> 51 | AE31: =IFERROR(__xludf.DUMMYFUNCTION("""COMPUTED_VALUE"""),7.0) -> 7 | AF31: =IFERROR(__xludf.DUMMYFUNCTION("""COMPUTED_VALUE"""),3.0) -> 3 | AG31: ENERO | AH31: 2024
A32: =IF(B32="","",A31+1) -> 45322 | B32: 518 | C32: 0.55833333 | D32: 0.92222222 | E32: {=IF(B32=0,"",(J32+K32)/60)} -> 0.25 | F32: =IF(B32=0,"",HOUR(D32-C32)+(MINUTE(D32-C32)/60)) -> 8.7333333 | G32: =IF(B32=0,"",B32/F32) -> 59.312977 | H32: =IF(B32=0,"",B32/(F32-E32)) -> 61.060904 | I32: =IF(B32=0,"",B32/F32/AD32) -> 1.1629996 | J32: 15 | M32: =IFERROR(__xludf.DUMMYFUNCTION("""COMPUTED_VALUE"""),57.0) -> 57 | N32: =IFERROR(__xludf.DUMMYFUNCTION("""COMPUTED_VALUE"""),54.0) -> 54 | O32: =IFERROR(__xludf.DUMMYFUNCTION("""COMPUTED_VALUE"""),0.0) -> 0 | P32: =IFERROR(__xludf.DUMMYFUNCTION("""COMPUTED_VALUE"""),0.0) -> 0 | Q32: =IFERROR(__xludf.DUMMYFUNCTION("""COMPUTED_VALUE"""),0.0) -> 0 | R32: =IFERROR(__xludf.DUMMYFUNCTION("""COMPUTED_VALUE"""),0.0) -> 0 | S32: =IFERROR(__xludf.DUMMYFUNCTION("""COMPUTED_VALUE"""),1.0) -> 1 | T32: =IFERROR(__xludf.DUMMYFUNCTION("""COMPUTED_VALUE"""),0.0) -> 0 | U32: =IFERROR(__xludf.DUMMYFUNCTION("""COMPUTED_VALUE"""),1.0) -> 1 | V32: =IFERROR(__xludf.DUMMYFUNCTION("""COMPUTED_VALUE"""),3.0) -> 3 | W32: =IFERROR(__xludf.DUMMYFUNCTION("""COMPUTED_VALUE"""),0.0) -> 0 | X32: =IFERROR(__xludf.DUMMYFUNCTION("""COMPUTED_VALUE"""),0.0) -> 0 | Y32: =IFERROR(__xludf.DUMMYFUNCTION("""COMPUTED_VALUE"""),0.0) -> 0 | Z32: =IFERROR(__xludf.DUMMYFUNCTION("""COMPUTED_VALUE"""),0.0) -> 0 | AA32: =IFERROR(__xludf.DUMMYFUNCTION("""COMPUTED_VALUE"""),0.0) -> 0 | AB32: =IFERROR(__xludf.DUMMYFUNCTION("""COMPUTED_VALUE"""),0.0) -> 0 | AC32: =IFERROR(__xludf.DUMMYFUNCTION("""COMPUTED_VALUE"""),0.0) -> 0 | AD32: =IFERROR(__xludf.DUMMYFUNCTION("""COMPUTED_VALUE"""),51.0) -> 51 | AE32: =IFERROR(__xludf.DUMMYFUNCTION("""COMPUTED_VALUE"""),7.0) -> 7 | AF32: =IFERROR(__xludf.DUMMYFUNCTION("""COMPUTED_VALUE"""),3.0) -> 3 | AG32: ENERO | AH32: 2024
A33: =IF(B33="","",A32+1) -> 45323 | B33: 518 | C33: 0.56527778 | D33: 0.91666667 | E33: {=IF(B33=0,"",(J33+K33)/60)} -> 0.5 | F33: =IF(B33=0,"",HOUR(D33-C33)+(MINUTE(D33-C33)/60)) -> 8.4333333 | G33: =IF(B33=0,"",B33/F33) -> 61.422925 | H33: =IF(B33=0,"",B33/(F33-E33)) -> 65.294118 | I33: =IF(B33=0,"",B33/F33/AD33) -> 1.335281 | J33: 15 | K33: 15 | M33: =IFERROR(__xludf.DUMMYFUNCTION("TRANSPOSE(IMPORTRANGE(""https://docs.google.com/spreadsheets/d/1CNeKSHTeNNJnfn5EymHwGg5Mkuk6EcepW7_9QkJxalc/edit#gid=1218471306"",""FEBRERO 2024!F2:AH21""))"),57.0) -> 57 | N33: =IFERROR(__xludf.DUMMYFUNCTION("""COMPUTED_VALUE"""),54.0) -> 54 | O33: =IFERROR(__xludf.DUMMYFUNCTION("""COMPUTED_VALUE"""),1.0) -> 1 | P33: =IFERROR(__xludf.DUMMYFUNCTION("""COMPUTED_VALUE"""),1.0) -> 1 | Q33: =IFERROR(__xludf.DUMMYFUNCTION("""COMPUTED_VALUE"""),0.0) -> 0 | R33: =IFERROR(__xludf.DUMMYFUNCTION("""COMPUTED_VALUE"""),0.0) -> 0 | S33: =IFERROR(__xludf.DUMMYFUNCTION("""COMPUTED_VALUE"""),4.0) -> 4 | T33: =IFERROR(__xludf.DUMMYFUNCTION("""COMPUTED_VALUE"""),0.0) -> 0 | U33: =IFERROR(__xludf.DUMMYFUNCTION("""COMPUTED_VALUE"""),1.0) -> 1 | V33: =IFERROR(__xludf.DUMMYFUNCTION("""COMPUTED_VALUE"""),2.0) -> 2 | W33: =IFERROR(__xludf.DUMMYFUNCTION("""COMPUTED_VALUE"""),0.0) -> 0 | X33: =IFERROR(__xludf.DUMMYFUNCTION("""COMPUTED_VALUE"""),0.0) -> 0 | Y33: =IFERROR(__xludf.DUMMYFUNCTION("""COMPUTED_VALUE"""),0.0) -> 0 | Z33: =IFERROR(__xludf.DUMMYFUNCTION("""COMPUTED_VALUE"""),0.0) -> 0 | AA33: =IFERROR(__xludf.DUMMYFUNCTION("""COMPUTED_VALUE"""),0.0) -> 0 | AB33: =IFERROR(__xludf.DUMMYFUNCTION("""COMPUTED_VALUE"""),1.0) -> 1 | AC33: =IFERROR(__xludf.DUMMYFUNCTION("""COMPUTED_VALUE"""),0.0) -> 0 | AD33: =IFERROR(__xludf.DUMMYFUNCTION("""COMPUTED_VALUE"""),46.0) -> 46 | AE33: =IFERROR(__xludf.DUMMYFUNCTION("""COMPUTED_VALUE"""),11.0) -> 11 | AF33: =IFERROR(__xludf.DUMMYFUNCTION("""COMPUTED_VALUE"""),3.0) -> 3 | AG33: FEBRERO | AH33: 2024
A34: =IF(B34="","",A33+1) -> 45324 | B34: 423 | C34: 0.6 | D34: 0.91666667 | E34: {=IF(B34=0,"",(J34+K34)/60)} -> 0.25 | F34: =IF(B34=0,"",HOUR(D34-C34)+(MINUTE(D34-C34)/60)) -> 7.6 | G34: =IF(B34=0,"",B34/F34) -> 55.657895 | H34: =IF(B34=0,"",B34/(F34-E34)) -> 57.55102 | I34: =IF(B34=0,"",B34/F34/AD34) -> 1.1595395 | J34: 15 | M34: =IFERROR(__xludf.DUMMYFUNCTION("""COMPUTED_VALUE"""),57.0) -> 57 | N34: =IFERROR(__xludf.DUMMYFUNCTION("""COMPUTED_VALUE"""),54.0) -> 54 | O34: =IFERROR(__xludf.DUMMYFUNCTION("""COMPUTED_VALUE"""),0.0) -> 0 | P34: =IFERROR(__xludf.DUMMYFUNCTION("""COMPUTED_VALUE"""),0.0) -> 0 | Q34: =IFERROR(__xludf.DUMMYFUNCTION("""COMPUTED_VALUE"""),2.0) -> 2 | R34: =IFERROR(__xludf.DUMMYFUNCTION("""COMPUTED_VALUE"""),0.0) -> 0 | S34: =IFERROR(__xludf.DUMMYFUNCTION("""COMPUTED_VALUE"""),3.0) -> 3 | T34: =IFERROR(__xludf.DUMMYFUNCTION("""COMPUTED_VALUE"""),0.0) -> 0 | U34: =IFERROR(__xludf.DUMMYFUNCTION("""COMPUTED_VALUE"""),1.0) -> 1 | V34: =IFERROR(__xludf.DUMMYFUNCTION("""COMPUTED_VALUE"""),2.0) -> 2 | W34: =IFERROR(__xludf.DUMMYFUNCTION("""COMPUTED_VALUE"""),0.0) -> 0 | X34: =IFERROR(__xludf.DUMMYFUNCTION("""COMPUTED_VALUE"""),0.0) -> 0 | Y34: =IFERROR(__xludf.DUMMYFUNCTION("""COMPUTED_VALUE"""),0.0) -> 0 | Z34: =IFERROR(__xludf.DUMMYFUNCTION("""COMPUTED_VALUE"""),0.0) -> 0 | AA34: =IFERROR(__xludf.DUMMYFUNCTION("""COMPUTED_VALUE"""),0.0) -> 0 | AB34: =IFERROR(__xludf.DUMMYFUNCTION("""COMPUTED_VALUE"""),0.0) -> 0 | AC34: =IFERROR(__xludf.DUMMYFUNCTION("""COMPUTED_VALUE"""),0.0) -> 0 | AD34: =IFERROR(__xludf.DUMMYFUNCTION("""COMPUTED_VALUE"""),48.0) -> 48 | AE34: =IFERROR(__xludf.DUMMYFUNCTION("""COMPUTED_VALUE"""),10.0) -> 10 | AF34: =IFERROR(__xludf.DUMMYFUNCTION("""COMPUTED_VALUE"""),3.0) -> 3 | AG34: FEBRERO | AH34: 2024
A35: =IF(B35="","",A34+1) -> 45325 | B35: 382 | C35: 0.51666667 | D35: 0.80555556 | E35: {=IF(B35=0,"",(J35+K35)/60)} -> 0.25 | F35: =IF(B35=0,"",HOUR(D35-C35)+(MINUTE(D35-C35)/60)) -> 6.9333333 | G35: =IF(B35=0,"",B35/F35) -> 55.096154 | H35: =IF(B35=0,"",B35/(F35-E35)) -> 57.157107 | I35: =IF(B35=0,"",B35/F35/AD35) -> 1.1019231 | J35: 15 | M35: =IFERROR(__xludf.DUMMYFUNCTION("""COMPUTED_VALUE"""),57.0) -> 57 | N35: =IFERROR(__xludf.DUMMYFUNCTION("""COMPUTED_VALUE"""),54.0) -> 54 | O35: =IFERROR(__xludf.DUMMYFUNCTION("""COMPUTED_VALUE"""),0.0) -> 0 | P35: =IFERROR(__xludf.DUMMYFUNCTION("""COMPUTED_VALUE"""),1.0) -> 1 | Q35: =IFERROR(__xludf.DUMMYFUNCTION("""COMPUTED_VALUE"""),1.0) -> 1 | R35: =IFERROR(__xludf.DUMMYFUNCTION("""COMPUTED_VALUE"""),0.0) -> 0 | S35: =IFERROR(__xludf.DUMMYFUNCTION("""COMPUTED_VALUE"""),1.0) -> 1 | T35: =IFERROR(__xludf.DUMMYFUNCTION("""COMPUTED_VALUE"""),0.0) -> 0 | U35: =IFERROR(__xludf.DUMMYFUNCTION("""COMPUTED_VALUE"""),1.0) -> 1 | V35: =IFERROR(__xludf.DUMMYFUNCTION("""COMPUTED_VALUE"""),2.0) -> 2 | W35: =IFERROR(__xludf.DUMMYFUNCTION("""COMPUTED_VALUE"""),0.0) -> 0 | X35: =IFERROR(__xludf.DUMMYFUNCTION("""COMPUTED_VALUE"""),0.0) -> 0 | Y35: =IFERROR(__xludf.DUMMYFUNCTION("""COMPUTED_VALUE"""),0.0) -> 0 | Z35: =IFERROR(__xludf.DUMMYFUNCTION("""COMPUTED_VALUE"""),0.0) -> 0 | AA35: =IFERROR(__xludf.DUMMYFUNCTION("""COMPUTED_VALUE"""),0.0) -> 0 | AB35: =IFERROR(__xludf.DUMMYFUNCTION("""COMPUTED_VALUE"""),0.0) -> 0 | AC35: =IFERROR(__xludf.DUMMYFUNCTION("""COMPUTED_VALUE"""),0.0) -> 0 | AD35: =IFERROR(__xludf.DUMMYFUNCTION("""COMPUTED_VALUE"""),50.0) -> 50 | AE35: =IFERROR(__xludf.DUMMYFUNCTION("""COMPUTED_VALUE"""),8.0) -> 8 | AF35: =IFERROR(__xludf.DUMMYFUNCTION("""COMPUTED_VALUE"""),3.0) -> 3 | AG35: FEBRERO | AH35: 2024
A36: =IF(B36="","",A35+1) -> 45326 | B36: 0 | E36: {=IF(B36=0,"",(J36+K36)/60)} | F36: =IF(B36=0,"",HOUR(D36-C36)+(MINUTE(D36-C36)/60)) | G36: =IF(B36=0,"",B36/F36) | H36: =IF(B36=0,"",B36/(F36-E36)) | I36: =IF(B36=0,"",B36/F36/AD36) | M36: =IFERROR(__xludf.DUMMYFUNCTION("""COMPUTED_VALUE"""),57.0) -> 57 | N36: =IFERROR(__xludf.DUMMYFUNCTION("""COMPUTED_VALUE"""),55.0) -> 55 | O36: =IFERROR(__xludf.DUMMYFUNCTION("""COMPUTED_VALUE"""),0.0) -> 0 | P36: =IFERROR(__xludf.DUMMYFUNCTION("""COMPUTED_VALUE"""),0.0) -> 0 | Q36: =IFERROR(__xludf.DUMMYFUNCTION("""COMPUTED_VALUE"""),0.0) -> 0 | R36: =IFERROR(__xludf.DUMMYFUNCTION("""COMPUTED_VALUE"""),0.0) -> 0 | S36: =IFERROR(__xludf.DUMMYFUNCTION("""COMPUTED_VALUE"""),0.0) -> 0 | T36: =IFERROR(__xludf.DUMMYFUNCTION("""COMPUTED_VALUE"""),0.0) -> 0 | U36: =IFERROR(__xludf.DUMMYFUNCTION("""COMPUTED_VALUE"""),0.0) -> 0 | V36: =IFERROR(__xludf.DUMMYFUNCTION("""COMPUTED_VALUE"""),0.0) -> 0 | ... AD36: =IFERROR(__xludf.DUMMYFUNCTION("""COMPUTED_VALUE"""),0.0) -> 0 | AE36: =IFERROR(__xludf.DUMMYFUNCTION("""COMPUTED_VALUE"""),2.0) -> 2 | AF36: =IFERROR(__xludf.DUMMYFUNCTION("""COMPUTED_VALUE"""),2.0) -> 2 | AG36: FEBRERO | AH36: 2024
A37: =IF(B37="","",A36+1) -> 45327 | B37: 503 | C37: 0.51666667 | D37: 0.89930556 | E37: {=IF(B37=0,"",(J37+K37)/60)} -> 0.25 | F37: =IF(B37=0,"",HOUR(D37-C37)+(MINUTE(D37-C37)/60)) -> 9.1833333 | G37: =IF(B37=0,"",B37/F37) -> 54.77314 | H37: =IF(B37=0,"",B37/(F37-E37)) -> 56.30597 | I37: =IF(B37=0,"",B37/F37/AD37) -> 1.165386 | J37: 15 | M37: =IFERROR(__xludf.DUMMYFUNCTION("""COMPUTED_VALUE"""),57.0) -> 57 | N37: =IFERROR(__xludf.DUMMYFUNCTION("""COMPUTED_VALUE"""),54.0) -> 54 | O37: =IFERROR(__xludf.DUMMYFUNCTION("""COMPUTED_VALUE"""),0.0) -> 0 | P37: =IFERROR(__xludf.DUMMYFUNCTION("""COMPUTED_VALUE"""),0.0) -> 0 | Q37: =IFERROR(__xludf.DUMMYFUNCTION("""COMPUTED_VALUE"""),2.0) -> 2 | R37: =IFERROR(__xludf.DUMMYFUNCTION("""COMPUTED_VALUE"""),0.0) -> 0 | S37: =IFERROR(__xludf.DUMMYFUNCTION("""COMPUTED_VALUE"""),2.0) -> 2 | T37: =IFERROR(__xludf.DUMMYFUNCTION("""COMPUTED_VALUE"""),0.0) -> 0 | U37: =IFERROR(__xludf.DUMMYFUNCTION("""COMPUTED_VALUE"""),1.0) -> 1 | V37: =IFERROR(__xludf.DUMMYFUNCTION("""COMPUTED_VALUE"""),2.0) -> 2 | W37: =IFERROR(__xludf.DUMMYFUNCTION("""COMPUTED_VALUE"""),1.0) -> 1 | X37: =IFERROR(__xludf.DUMMYFUNCTION("""COMPUTED_VALUE"""),0.0) -> 0 | Y37: =IFERROR(__xludf.DUMMYFUNCTION("""COMPUTED_VALUE"""),0.0) -> 0 | Z37: =IFERROR(__xludf.DUMMYFUNCTION("""COMPUTED_VALUE"""),0.0) -> 0 | AA37: =IFERROR(__xludf.DUMMYFUNCTION("""COMPUTED_VALUE"""),0.0) -> 0 | AB37: =IFERROR(__xludf.DUMMYFUNCTION("""COMPUTED_VALUE"""),0.0) -> 0 | AC37: =IFERROR(__xludf.DUMMYFUNCTION("""COMPUTED_VALUE"""),0.0) -> 0 | AD37: =IFERROR(__xludf.DUMMYFUNCTION("""COMPUTED_VALUE"""),47.0) -> 47 | AE37: =IFERROR(__xludf.DUMMYFUNCTION("""COMPUTED_VALUE"""),10.0) -> 10 | AF37: =IFERROR(__xludf.DUMMYFUNCTION("""COMPUTED_VALUE"""),3.0) -> 3 | AG37: FEBRERO | AH37: 2024
A38: =IF(B38="","",A37+1) -> 45328 | B38: 567 | C38: 0.43333333 | D38: 0.85416667 | E38: {=IF(B38=0,"",(J38+K38)/60)} -> 1 | F38: =IF(B38=0,"",HOUR(D38-C38)+(MINUTE(D38-C38)/60)) -> 10.1 | G38: =IF(B38=0,"",B38/F38) -> 56.138614 | H38: =IF(B38=0,"",B38/(F38-E38)) -> 62.307692 | I38: =IF(B38=0,"",B38/F38/AD38) -> 1.145686 | J38: 60 | M38: =IFERROR(__xludf.DUMMYFUNCTION("""COMPUTED_VALUE"""),57.0) -> 57 | N38: =IFERROR(__xludf.DUMMYFUNCTION("""COMPUTED_VALUE"""),53.0) -> 53 | O38: =IFERROR(__xludf.DUMMYFUNCTION("""COMPUTED_VALUE"""),0.0) -> 0 | P38: =IFERROR(__xludf.DUMMYFUNCTION("""COMPUTED_VALUE"""),0.0) -> 0 | Q38: =IFERROR(__xludf.DUMMYFUNCTION("""COMPUTED_VALUE"""),0.0) -> 0 | R38: =IFERROR(__xludf.DUMMYFUNCTION("""COMPUTED_VALUE"""),0.0) -> 0 | S38: =IFERROR(__xludf.DUMMYFUNCTION("""COMPUTED_VALUE"""),2.0) -> 2 | T38: =IFERROR(__xludf.DUMMYFUNCTION("""COMPUTED_VALUE"""),0.0) -> 0 | U38: =IFERROR(__xludf.DUMMYFUNCTION("""COMPUTED_VALUE"""),2.0) -> 2 | V38: =IFERROR(__xludf.DUMMYFUNCTION("""COMPUTED_VALUE"""),2.0) -> 2 | W38: =IFERROR(__xludf.DUMMYFUNCTION("""COMPUTED_VALUE"""),0.0) -> 0 | X38: =IFERROR(__xludf.DUMMYFUNCTION("""COMPUTED_VALUE"""),0.0) -> 0 | Y38: =IFERROR(__xludf.DUMMYFUNCTION("""COMPUTED_VALUE"""),0.0) -> 0 | Z38: =IFERROR(__xludf.DUMMYFUNCTION("""COMPUTED_VALUE"""),0.0) -> 0 | AA38: =IFERROR(__xludf.DUMMYFUNCTION("""COMPUTED_VALUE"""),0.0) -> 0 | AB38: =IFERROR(__xludf.DUMMYFUNCTION("""COMPUTED_VALUE"""),0.0) -> 0 | AC38: =IFERROR(__xludf.DUMMYFUNCTION("""COMPUTED_VALUE"""),0.0) -> 0 | AD38: =IFERROR(__xludf.DUMMYFUNCTION("""COMPUTED_VALUE"""),49.0) -> 49 | AE38: =IFERROR(__xludf.DUMMYFUNCTION("""COMPUTED_VALUE"""),8.0) -> 8 | AF38: =IFERROR(__xludf.DUMMYFUNCTION("""COMPUTED_VALUE"""),4.0) -> 4 | AG38: FEBRERO | AH38: 2024
A39: =IF(B39="","",A38+1) -> 45329 | B39: 479 | C39: 0.51666667 | D39: 0.92013889 | E39: {=IF(B39=0,"",(J39+K39)/60)} -> 2.5 | F39: =IF(B39=0,"",HOUR(D39-C39)+(MINUTE(D39-C39)/60)) -> 9.6833333 | G39: =IF(B39=0,"",B39/F39) -> 49.466437 | H39: =IF(B39=0,"",B39/(F39-E39)) -> 66.682135 | I39: =IF(B39=0,"",B39/F39/AD39) -> 1.0305508 | J39: 15 | K39: 135 | M39: =IFERROR(__xludf.DUMMYFUNCTION("""COMPUTED_VALUE"""),57.0) -> 57 | N39: =IFERROR(__xludf.DUMMYFUNCTION("""COMPUTED_VALUE"""),52.0) -> 52 | O39: =IFERROR(__xludf.DUMMYFUNCTION("""COMPUTED_VALUE"""),0.0) -> 0 | P39: =IFERROR(__xludf.DUMMYFUNCTION("""COMPUTED_VALUE"""),0.0) -> 0 | Q39: =IFERROR(__xludf.DUMMYFUNCTION("""COMPUTED_VALUE"""),0.0) -> 0 | R39: =IFERROR(__xludf.DUMMYFUNCTION("""COMPUTED_VALUE"""),1.0) -> 1 | S39: =IFERROR(__xludf.DUMMYFUNCTION("""COMPUTED_VALUE"""),2.0) -> 2 | T39: =IFERROR(__xludf.DUMMYFUNCTION("""COMPUTED_VALUE"""),0.0) -> 0 | U39: =IFERROR(__xludf.DUMMYFUNCTION("""COMPUTED_VALUE"""),2.0) -> 2 | V39: =IFERROR(__xludf.DUMMYFUNCTION("""COMPUTED_VALUE"""),2.0) -> 2 | W39: =IFERROR(__xludf.DUMMYFUNCTION("""COMPUTED_VALUE"""),0.0) -> 0 | X39: =IFERROR(__xludf.DUMMYFUNCTION("""COMPUTED_VALUE"""),0.0) -> 0 | Y39: =IFERROR(__xludf.DUMMYFUNCTION("""COMPUTED_VALUE"""),0.0) -> 0 | Z39: =IFERROR(__xludf.DUMMYFUNCTION("""COMPUTED_VALUE"""),0.0) -> 0 | AA39: =IFERROR(__xludf.DUMMYFUNCTION("""COMPUTED_VALUE"""),0.0) -> 0 | AB39: =IFERROR(__xludf.DUMMYFUNCTION("""COMPUTED_VALUE"""),0.0) -> 0 | AC39: =IFERROR(__xludf.DUMMYFUNCTION("""COMPUTED_VALUE"""),0.0) -> 0 | AD39: =IFERROR(__xludf.DUMMYFUNCTION("""COMPUTED_VALUE"""),48.0) -> 48 | AE39: =IFERROR(__xludf.DUMMYFUNCTION("""COMPUTED_VALUE"""),8.0) -> 8 | AF39: =IFERROR(__xludf.DUMMYFUNCTION("""COMPUTED_VALUE"""),5.0) -> 5 | AG39: FEBRERO | AH39: 2024
A40: =IF(B40="","",A39+1) -> 45330 | B40: 480 | C40: 0.6 | D40: 0.97152778 | E40: {=IF(B40=0,"",(J40+K40)/60)} -> 0.25 | F40: =IF(B40=0,"",HOUR(D40-C40)+(MINUTE(D40-C40)/60)) -> 8.9166667 | G40: =IF(B40=0,"",B40/F40) -> 53.831776 | H40: =IF(B40=0,"",B40/(F40-E40)) -> 55.384615 | I40: =IF(B40=0,"",B40/F40/AD40) -> 1.170256 | J40: 15 | M40: =IFERROR(__xludf.DUMMYFUNCTION("""COMPUTED_VALUE"""),57.0) -> 57 | N40: =IFERROR(__xludf.DUMMYFUNCTION("""COMPUTED_VALUE"""),52.0) -> 52 | O40: =IFERROR(__xludf.DUMMYFUNCTION("""COMPUTED_VALUE"""),1.0) -> 1 | P40: =IFERROR(__xludf.DUMMYFUNCTION("""COMPUTED_VALUE"""),1.0) -> 1 | Q40: =IFERROR(__xludf.DUMMYFUNCTION("""COMPUTED_VALUE"""),0.0) -> 0 | R40: =IFERROR(__xludf.DUMMYFUNCTION("""COMPUTED_VALUE"""),0.0) -> 0 | S40: =IFERROR(__xludf.DUMMYFUNCTION("""COMPUTED_VALUE"""),2.0) -> 2 | T40: =IFERROR(__xludf.DUMMYFUNCTION("""COMPUTED_VALUE"""),0.0) -> 0 | U40: =IFERROR(__xludf.DUMMYFUNCTION("""COMPUTED_VALUE"""),3.0) -> 3 | V40: =IFERROR(__xludf.DUMMYFUNCTION("""COMPUTED_VALUE"""),0.0) -> 0 | W40: =IFERROR(__xludf.DUMMYFUNCTION("""COMPUTED_VALUE"""),0.0) -> 0 | X40: =IFERROR(__xludf.DUMMYFUNCTION("""COMPUTED_VALUE"""),0.0) -> 0 | Y40: =IFERROR(__xludf.DUMMYFUNCTION("""COMPUTED_VALUE"""),0.0) -> 0 | Z40: =IFERROR(__xludf.DUMMYFUNCTION("""COMPUTED_VALUE"""),0.0) -> 0 | AA40: =IFERROR(__xludf.DUMMYFUNCTION("""COMPUTED_VALUE"""),2.0) -> 2 | AB40: =IFERROR(__xludf.DUMMYFUNCTION("""COMPUTED_VALUE"""),0.0) -> 0 | AC40: =IFERROR(__xludf.DUMMYFUNCTION("""COMPUTED_VALUE"""),0.0) -> 0 | AD40: =IFERROR(__xludf.DUMMYFUNCTION("""COMPUTED_VALUE"""),46.0) -> 46 | AE40: =IFERROR(__xludf.DUMMYFUNCTION("""COMPUTED_VALUE"""),11.0) -> 11 | AF40: =IFERROR(__xludf.DUMMYFUNCTION("""COMPUTED_VALUE"""),5.0) -> 5 | AG40: FEBRERO | AH40: 2024
A41: =IF(B41="","",A40+1) -> 45331 | B41: 460 | C41: 0.55833333 | D41: 0.89930556 | E41: {=IF(B41=0,"",(J41+K41)/60)} -> 0.25 | F41: =IF(B41=0,"",HOUR(D41-C41)+(MINUTE(D41-C41)/60)) -> 8.1833333 | G41: =IF(B41=0,"",B41/F41) -> 56.211813 | H41: =IF(B41=0,"",B41/(F41-E41)) -> 57.983193 | I41: =IF(B41=0,"",B41/F41/AD41) -> 1.1710794 | J41: 15 | M41: =IFERROR(__xludf.DUMMYFUNCTION("""COMPUTED_VALUE"""),57.0) -> 57 | N41: =IFERROR(__xludf.DUMMYFUNCTION("""COMPUTED_VALUE"""),52.0) -> 52 | O41: =IFERROR(__xludf.DUMMYFUNCTION("""COMPUTED_VALUE"""),1.0) -> 1 | P41: =IFERROR(__xludf.DUMMYFUNCTION("""COMPUTED_VALUE"""),0.0) -> 0 | Q41: =IFERROR(__xludf.DUMMYFUNCTION("""COMPUTED_VALUE"""),0.0) -> 0 | R41: =IFERROR(__xludf.DUMMYFUNCTION("""COMPUTED_VALUE"""),0.0) -> 0 | S41: =IFERROR(__xludf.DUMMYFUNCTION("""COMPUTED_VALUE"""),1.0) -> 1 | T41: =IFERROR(__xludf.DUMMYFUNCTION("""COMPUTED_VALUE"""),0.0) -> 0 | U41: =IFERROR(__xludf.DUMMYFUNCTION("""COMPUTED_VALUE"""),3.0) -> 3 | V41: =IFERROR(__xludf.DUMMYFUNCTION("""COMPUTED_VALUE"""),2.0) -> 2 | W41: =IFERROR(__xludf.DUMMYFUNCTION("""COMPUTED_VALUE"""),0.0) -> 0 | X41: =IFERROR(__xludf.DUMMYFUNCTION("""COMPUTED_VALUE"""),0.0) -> 0 | Y41: =IFERROR(__xludf.DUMMYFUNCTION("""COMPUTED_VALUE"""),0.0) -> 0 | Z41: =IFERROR(__xludf.DUMMYFUNCTION("""COMPUTED_VALUE"""),0.0) -> 0 | AA41: =IFERROR(__xludf.DUMMYFUNCTION("""COMPUTED_VALUE"""),0.0) -> 0 | AB41: =IFERROR(__xludf.DUMMYFUNCTION("""COMPUTED_VALUE"""),0.0) -> 0 | AC41: =IFERROR(__xludf.DUMMYFUNCTION("""COMPUTED_VALUE"""),0.0) -> 0 | AD41: =IFERROR(__xludf.DUMMYFUNCTION("""COMPUTED_VALUE"""),48.0) -> 48 | AE41: =IFERROR(__xludf.DUMMYFUNCTION("""COMPUTED_VALUE"""),9.0) -> 9 | AF41: =IFERROR(__xludf.DUMMYFUNCTION("""COMPUTED_VALUE"""),5.0) -> 5 | AG41: FEBRERO | AH41: 2024
A42: =IF(B42="","",A41+1) -> 45332 | B42: 335 | C42: 0.51666667 | D42: 0.77083333 | E42: {=IF(B42=0,"",(J42+K42)/60)} -> 0.25 | F42: =IF(B42=0,"",HOUR(D42-C42)+(MINUTE(D42-C42)/60)) -> 6.1 | G42: =IF(B42=0,"",B42/F42) -> 54.918033 | H42: =IF(B42=0,"",B42/(F42-E42)) -> 57.264957 | I42: =IF(B42=0,"",B42/F42/AD42) -> 1.1207762 | J42: 15 | M42: =IFERROR(__xludf.DUMMYFUNCTION("""COMPUTED_VALUE"""),57.0) -> 57 | N42: =IFERROR(__xludf.DUMMYFUNCTION("""COMPUTED_VALUE"""),52.0) -> 52 | O42: =IFERROR(__xludf.DUMMYFUNCTION("""COMPUTED_VALUE"""),0.0) -> 0 | P42: =IFERROR(__xludf.DUMMYFUNCTION("""COMPUTED_VALUE"""),0.0) -> 0 | Q42: =IFERROR(__xludf.DUMMYFUNCTION("""COMPUTED_VALUE"""),0.0) -> 0 | R42: =IFERROR(__xludf.DUMMYFUNCTION("""COMPUTED_VALUE"""),0.0) -> 0 | S42: =IFERROR(__xludf.DUMMYFUNCTION("""COMPUTED_VALUE"""),1.0) -> 1 | T42: =IFERROR(__xludf.DUMMYFUNCTION("""COMPUTED_VALUE"""),0.0) -> 0 | U42: =IFERROR(__xludf.DUMMYFUNCTION("""COMPUTED_VALUE"""),3.0) -> 3 | V42: =IFERROR(__xludf.DUMMYFUNCTION("""COMPUTED_VALUE"""),2.0) -> 2 | W42: =IFERROR(__xludf.DUMMYFUNCTION("""COMPUTED_VALUE"""),0.0) -> 0 | X42: =IFERROR(__xludf.DUMMYFUNCTION("""COMPUTED_VALUE"""),0.0) -> 0 | Y42: =IFERROR(__xludf.DUMMYFUNCTION("""COMPUTED_VALUE"""),0.0) -> 0 | Z42: =IFERROR(__xludf.DUMMYFUNCTION("""COMPUTED_VALUE"""),0.0) -> 0 | AA42: =IFERROR(__xludf.DUMMYFUNCTION("""COMPUTED_VALUE"""),0.0) -> 0 | AB42: =IFERROR(__xludf.DUMMYFUNCTION("""COMPUTED_VALUE"""),0.0) -> 0 | AC42: =IFERROR(__xludf.DUMMYFUNCTION("""COMPUTED_VALUE"""),0.0) -> 0 | AD42: =IFERROR(__xludf.DUMMYFUNCTION("""COMPUTED_VALUE"""),49.0) -> 49 | AE42: =IFERROR(__xludf.DUMMYFUNCTION("""COMPUTED_VALUE"""),8.0) -> 8 | AF42: =IFERROR(__xludf.DUMMYFUNCTION("""COMPUTED_VALUE"""),5.0) -> 5 | AG42: FEBRERO | AH42: 2024
A43: =IF(B43="","",A42+1) -> 45333 | B43: 0 | E43: {=IF(B43=0,"",(J43+K43)/60)} | F43: =IF(B43=0,"",HOUR(D43-C43)+(MINUTE(D43-C43)/60)) | G43: =IF(B43=0,"",B43/F43) | H43: =IF(B43=0,"",B43/(F43-E43)) | I43: =IF(B43=0,"",B43/F43/AD43) | M43: =IFERROR(__xludf.DUMMYFUNCTION("""COMPUTED_VALUE"""),57.0) -> 57 | N43: =IFERROR(__xludf.DUMMYFUNCTION("""COMPUTED_VALUE"""),53.0) -> 53 | O43: =IFERROR(__xludf.DUMMYFUNCTION("""COMPUTED_VALUE"""),0.0) -> 0 | P43: =IFERROR(__xludf.DUMMYFUNCTION("""COMPUTED_VALUE"""),0.0) -> 0 | Q43: =IFERROR(__xludf.DUMMYFUNCTION("""COMPUTED_VALUE"""),0.0) -> 0 | R43: =IFERROR(__xludf.DUMMYFUNCTION("""COMPUTED_VALUE"""),0.0) -> 0 | S43: =IFERROR(__xludf.DUMMYFUNCTION("""COMPUTED_VALUE"""),0.0) -> 0 | T43: =IFERROR(__xludf.DUMMYFUNCTION("""COMPUTED_VALUE"""),0.0) -> 0 | U43: =IFERROR(__xludf.DUMMYFUNCTION("""COMPUTED_VALUE"""),2.0) -> 2 | V43: =IFERROR(__xludf.DUMMYFUNCTION("""COMPUTED_VALUE"""),0.0) -> 0 | W43: =IFERROR(__xludf.DUMMYFUNCTION("""COMPUTED_VALUE"""),0.0) -> 0 | X43: =IFERROR(__xludf.DUMMYFUNCTION("""COMPUTED_VALUE"""),0.0) -> 0 | Y43: =IFERROR(__xludf.DUMMYFUNCTION("""COMPUTED_VALUE"""),0.0) -> 0 | Z43: =IFERROR(__xludf.DUMMYFUNCTION("""COMPUTED_VALUE"""),0.0) -> 0 | AA43: =IFERROR(__xludf.DUMMYFUNCTION("""COMPUTED_VALUE"""),0.0) -> 0 | AB43: =IFERROR(__xludf.DUMMYFUNCTION("""COMPUTED_VALUE"""),0.0) -> 0 | AC43: =IFERROR(__xludf.DUMMYFUNCTION("""COMPUTED_VALUE"""),0.0) -> 0 | AD43: =IFERROR(__xludf.DUMMYFUNCTION("""COMPUTED_VALUE"""),0.0) -> 0 | AE43: =IFERROR(__xludf.DUMMYFUNCTION("""COMPUTED_VALUE"""),4.0) -> 4 | AF43: =IFERROR(__xludf.DUMMYFUNCTION("""COMPUTED_VALUE"""),4.0) -> 4 | AG43: FEBRERO | AH43: 2024
A44: =IF(B44="","",A43+1) -> 45334 | B44: 510 | C44: 0.55833333 | D44: 0.94305556 | E44: {=IF(B44=0,"",(J44+K44)/60)} -> 0.25 | F44: =IF(B44=0,"",HOUR(D44-C44)+(MINUTE(D44-C44)/60)) -> 9.2333333 | G44: =IF(B44=0,"",B44/F44) -> 55.234657 | H44: =IF(B44=0,"",B44/(F44-E44)) -> 56.7718 | I44: =IF(B44=0,"",B44/F44/AD44) -> 1.1272379 | J44: 15 | M44: =IFERROR(__xludf.DUMMYFUNCTION("""COMPUTED_VALUE"""),57.0) -> 57 | N44: =IFERROR(__xludf.DUMMYFUNCTION("""COMPUTED_VALUE"""),52.0) -> 52 | O44: =IFERROR(__xludf.DUMMYFUNCTION("""COMPUTED_VALUE"""),0.0) -> 0 | P44: =IFERROR(__xludf.DUMMYFUNCTION("""COMPUTED_VALUE"""),0.0) -> 0 | Q44: =IFERROR(__xludf.DUMMYFUNCTION("""COMPUTED_VALUE"""),0.0) -> 0 | R44: =IFERROR(__xludf.DUMMYFUNCTION("""COMPUTED_VALUE"""),0.0) -> 0 | S44: =IFERROR(__xludf.DUMMYFUNCTION("""COMPUTED_VALUE"""),1.0) -> 1 | T44: =IFERROR(__xludf.DUMMYFUNCTION("""COMPUTED_VALUE"""),0.0) -> 0 | U44: =IFERROR(__xludf.DUMMYFUNCTION("""COMPUTED_VALUE"""),3.0) -> 3 | V44: =IFERROR(__xludf.DUMMYFUNCTION("""COMPUTED_VALUE"""),2.0) -> 2 | W44: =IFERROR(__xludf.DUMMYFUNCTION("""COMPUTED_VALUE"""),0.0) -> 0 | X44: =IFERROR(__xludf.DUMMYFUNCTION("""COMPUTED_VALUE"""),0.0) -> 0 | Y44: =IFERROR(__xludf.DUMMYFUNCTION("""COMPUTED_VALUE"""),0.0) -> 0 | Z44: =IFERROR(__xludf.DUMMYFUNCTION("""COMPUTED_VALUE"""),0.0) -> 0 | AA44: =IFERROR(__xludf.DUMMYFUNCTION("""COMPUTED_VALUE"""),0.0) -> 0 | AB44: =IFERROR(__xludf.DUMMYFUNCTION("""COMPUTED_VALUE"""),0.0) -> 0 | AC44: =IFERROR(__xludf.DUMMYFUNCTION("""COMPUTED_VALUE"""),0.0) -> 0 | AD44: =IFERROR(__xludf.DUMMYFUNCTION("""COMPUTED_VALUE"""),49.0) -> 49 | AE44: =IFERROR(__xludf.DUMMYFUNCTION("""COMPUTED_VALUE"""),8.0) -> 8 | AF44: =IFERROR(__xludf.DUMMYFUNCTION("""COMPUTED_VALUE"""),5.0) -> 5 | AG44: FEBRERO | AH44: 2024
A45: =IF(B45="","",A44+1) -> 45335 | B45: 566 | C45: 0.51666667 | D45: 0.95833333 | E45: {=IF(B45=0,"",(J45+K45)/60)} -> 1.6666667 | F45: =IF(B45=0,"",HOUR(D45-C45)+(MINUTE(D45-C45)/60)) -> 10.6 | G45: =IF(B45=0,"",B45/F45) -> 53.396226 | H45: =IF(B45=0,"",B45/(F45-E45)) -> 63.358209 | I45: =IF(B45=0,"",B45/F45/AD45) -> 1.1124214 | J45: 60 | K45: 40 | M45: =IFERROR(__xludf.DUMMYFUNCTION("""COMPUTED_VALUE"""),57.0) -> 57 | N45: =IFERROR(__xludf.DUMMYFUNCTION("""COMPUTED_VALUE"""),52.0) -> 52 | O45: =IFERROR(__xludf.DUMMYFUNCTION("""COMPUTED_VALUE"""),1.0) -> 1 | P45: =IFERROR(__xludf.DUMMYFUNCTION("""COMPUTED_VALUE"""),0.0) -> 0 | Q45: =IFERROR(__xludf.DUMMYFUNCTION("""COMPUTED_VALUE"""),0.0) -> 0 | R45: =IFERROR(__xludf.DUMMYFUNCTION("""COMPUTED_VALUE"""),0.0) -> 0 | S45: =IFERROR(__xludf.DUMMYFUNCTION("""COMPUTED_VALUE"""),1.0) -> 1 | T45: =IFERROR(__xludf.DUMMYFUNCTION("""COMPUTED_VALUE"""),0.0) -> 0 | U45: =IFERROR(__xludf.DUMMYFUNCTION("""COMPUTED_VALUE"""),3.0) -> 3 | V45: =IFERROR(__xludf.DUMMYFUNCTION("""COMPUTED_VALUE"""),2.0) -> 2 | W45: =IFERROR(__xludf.DUMMYFUNCTION("""COMPUTED_VALUE"""),0.0) -> 0 | X45: =IFERROR(__xludf.DUMMYFUNCTION("""COMPUTED_VALUE"""),0.0) -> 0 | Y45: =IFERROR(__xludf.DUMMYFUNCTION("""COMPUTED_VALUE"""),0.0) -> 0 | Z45: =IFERROR(__xludf.DUMMYFUNCTION("""COMPUTED_VALUE"""),0.0) -> 0 | AA45: =IFERROR(__xludf.DUMMYFUNCTION("""COMPUTED_VALUE"""),0.0) -> 0 | AB45: =IFERROR(__xludf.DUMMYFUNCTION("""COMPUTED_VALUE"""),0.0) -> 0 | AC45: =IFERROR(__xludf.DUMMYFUNCTION("""COMPUTED_VALUE"""),0.0) -> 0 | AD45: =IFERROR(__xludf.DUMMYFUNCTION("""COMPUTED_VALUE"""),48.0) -> 48 | AE45: =IFERROR(__xludf.DUMMYFUNCTION("""COMPUTED_VALUE"""),9.0) -> 9 | AF45: =IFERROR(__xludf.DUMMYFUNCTION("""COMPUTED_VALUE"""),5.0) -> 5 | AG45: FEBRERO | AH45: 2024
A46: =IF(B46="","",A45+1) -> 45336 | B46: 432 | C46: 0.51666667 | D46: 0.85486111 | E46: {=IF(B46=0,"",(J46+K46)/60)} -> 0.25 | F46: =IF(B46=0,"",HOUR(D46-C46)+(MINUTE(D46-C46)/60)) -> 8.1166667 | G46: =IF(B46=0,"",B46/F46) -> 53.223819 | H46: =IF(B46=0,"",B46/(F46-E46)) -> 54.915254 | I46: =IF(B46=0,"",B46/F46/AD46) -> 1.0644764 | J46: 15 | M46: =IFERROR(__xludf.DUMMYFUNCTION("""COMPUTED_VALUE"""),57.0) -> 57 | N46: =IFERROR(__xludf.DUMMYFUNCTION("""COMPUTED_VALUE"""),54.0) -> 54 | O46: =IFERROR(__xludf.DUMMYFUNCTION("""COMPUTED_VALUE"""),0.0) -> 0 | P46: =IFERROR(__xludf.DUMMYFUNCTION("""COMPUTED_VALUE"""),0.0) -> 0 | Q46: =IFERROR(__xludf.DUMMYFUNCTION("""COMPUTED_VALUE"""),0.0) -> 0 | R46: =IFERROR(__xludf.DUMMYFUNCTION("""COMPUTED_VALUE"""),0.0) -> 0 | S46: =IFERROR(__xludf.DUMMYFUNCTION("""COMPUTED_VALUE"""),2.0) -> 2 | T46: =IFERROR(__xludf.DUMMYFUNCTION("""COMPUTED_VALUE"""),0.0) -> 0 | U46: =IFERROR(__xludf.DUMMYFUNCTION("""COMPUTED_VALUE"""),1.0) -> 1 | V46: =IFERROR(__xludf.DUMMYFUNCTION("""COMPUTED_VALUE"""),2.0) -> 2 | W46: =IFERROR(__xludf.DUMMYFUNCTION("""COMPUTED_VALUE"""),0.0) -> 0 | X46: =IFERROR(__xludf.DUMMYFUNCTION("""COMPUTED_VALUE"""),0.0) -> 0 | Y46: =IFERROR(__xludf.DUMMYFUNCTION("""COMPUTED_VALUE"""),0.0) -> 0 | Z46: =IFERROR(__xludf.DUMMYFUNCTION("""COMPUTED_VALUE"""),0.0) -> 0 | AA46: =IFERROR(__xludf.DUMMYFUNCTION("""COMPUTED_VALUE"""),0.0) -> 0 | AB46: =IFERROR(__xludf.DUMMYFUNCTION("""COMPUTED_VALUE"""),0.0) -> 0 | AC46: =IFERROR(__xludf.DUMMYFUNCTION("""COMPUTED_VALUE"""),0.0) -> 0 | AD46: =IFERROR(__xludf.DUMMYFUNCTION("""COMPUTED_VALUE"""),50.0) -> 50 | AE46: =IFERROR(__xludf.DUMMYFUNCTION("""COMPUTED_VALUE"""),7.0) -> 7 | AF46: =IFERROR(__xludf.DUMMYFUNCTION("""COMPUTED_VALUE"""),3.0) -> 3 | AG46: FEBRERO | AH46: 2024
A47: =IF(B47="","",A46+1) -> 45337 | B47: 530 | C47: 0.51666667 | D47: 0.93402778 | E47: {=IF(B47=0,"",(J47+K47)/60)} -> 1 | F47: =IF(B47=0,"",HOUR(D47-C47)+(MINUTE(D47-C47)/60)) -> 10.016667 | G47: =IF(B47=0,"",B47/F47) -> 52.911814 | H47: =IF(B47=0,"",B47/(F47-E47)) -> 58.780037 | I47: =IF(B47=0,"",B47/F47/AD47) -> 1.1257833 | J47: 60 | M47: =IFERROR(__xludf.DUMMYFUNCTION("""COMPUTED_VALUE"""),57.0) -> 57 | N47: =IFERROR(__xludf.DUMMYFUNCTION("""COMPUTED_VALUE"""),54.0) -> 54 | O47: =IFERROR(__xludf.DUMMYFUNCTION("""COMPUTED_VALUE"""),1.0) -> 1 | P47: =IFERROR(__xludf.DUMMYFUNCTION("""COMPUTED_VALUE"""),0.0) -> 0 | Q47: =IFERROR(__xludf.DUMMYFUNCTION("""COMPUTED_VALUE"""),1.0) -> 1 | R47: =IFERROR(__xludf.DUMMYFUNCTION("""COMPUTED_VALUE"""),0.0) -> 0 | S47: =IFERROR(__xludf.DUMMYFUNCTION("""COMPUTED_VALUE"""),3.0) -> 3 | T47: =IFERROR(__xludf.DUMMYFUNCTION("""COMPUTED_VALUE"""),0.0) -> 0 | U47: =IFERROR(__xludf.DUMMYFUNCTION("""COMPUTED_VALUE"""),1.0) -> 1 | V47: =IFERROR(__xludf.DUMMYFUNCTION("""COMPUTED_VALUE"""),2.0) -> 2 | W47: =IFERROR(__xludf.DUMMYFUNCTION("""COMPUTED_VALUE"""),0.0) -> 0 | X47: =IFERROR(__xludf.DUMMYFUNCTION("""COMPUTED_VALUE"""),0.0) -> 0 | Y47: =IFERROR(__xludf.DUMMYFUNCTION("""COMPUTED_VALUE"""),0.0) -> 0 | Z47: =IFERROR(__xludf.DUMMYFUNCTION("""COMPUTED_VALUE"""),0.0) -> 0 | AA47: =IFERROR(__xludf.DUMMYFUNCTION("""COMPUTED_VALUE"""),0.0) -> 0 | AB47: =IFERROR(__xludf.DUMMYFUNCTION("""COMPUTED_VALUE"""),0.0) -> 0 | AC47: =IFERROR(__xludf.DUMMYFUNCTION("""COMPUTED_VALUE"""),0.0) -> 0 | AD47: =IFERROR(__xludf.DUMMYFUNCTION("""COMPUTED_VALUE"""),47.0) -> 47 | AE47: =IFERROR(__xludf.DUMMYFUNCTION("""COMPUTED_VALUE"""),10.0) -> 10 | AF47: =IFERROR(__xludf.DUMMYFUNCTION("""COMPUTED_VALUE"""),3.0) -> 3 | AG47: FEBRERO | AH47: 2024
A48: =IF(B48="","",A47+1) -> 45338 | B48: 371 | C48: 0.6 | D48: 0.88819444 | E48: {=IF(B48=0,"",(J48+K48)/60)} -> 0 | F48: =IF(B48=0,"",HOUR(D48-C48)+(MINUTE(D48-C48)/60)) -> 6.9166667 | G48: =IF(B48=0,"",B48/F48) -> 53.638554 | H48: =IF(B48=0,"",B48/(F48-E48)) -> 53.638554 | I48: =IF(B48=0,"",B48/F48/AD48) -> 1.1412458 | J48: 0 | M48: =IFERROR(__xludf.DUMMYFUNCTION("""COMPUTED_VALUE"""),57.0) -> 57 | N48: =IFERROR(__xludf.DUMMYFUNCTION("""COMPUTED_VALUE"""),54.0) -> 54 | O48: =IFERROR(__xludf.DUMMYFUNCTION("""COMPUTED_VALUE"""),1.0) -> 1 | P48: =IFERROR(__xludf.DUMMYFUNCTION("""COMPUTED_VALUE"""),0.0) -> 0 | Q48: =IFERROR(__xludf.DUMMYFUNCTION("""COMPUTED_VALUE"""),1.0) -> 1 | R48: =IFERROR(__xludf.DUMMYFUNCTION("""COMPUTED_VALUE"""),0.0) -> 0 | S48: =IFERROR(__xludf.DUMMYFUNCTION("""COMPUTED_VALUE"""),3.0) -> 3 | T48: =IFERROR(__xludf.DUMMYFUNCTION("""COMPUTED_VALUE"""),0.0) -> 0 | U48: =IFERROR(__xludf.DUMMYFUNCTION("""COMPUTED_VALUE"""),1.0) -> 1 | V48: =IFERROR(__xludf.DUMMYFUNCTION("""COMPUTED_VALUE"""),2.0) -> 2 | W48: =IFERROR(__xludf.DUMMYFUNCTION("""COMPUTED_VALUE"""),0.0) -> 0 | X48: =IFERROR(__xludf.DUMMYFUNCTION("""COMPUTED_VALUE"""),0.0) -> 0 | Y48: =IFERROR(__xludf.DUMMYFUNCTION("""COMPUTED_VALUE"""),0.0) -> 0 | Z48: =IFERROR(__xludf.DUMMYFUNCTION("""COMPUTED_VALUE"""),0.0) -> 0 | AA48: =IFERROR(__xludf.DUMMYFUNCTION("""COMPUTED_VALUE"""),0.0) -> 0 | AB48: =IFERROR(__xludf.DUMMYFUNCTION("""COMPUTED_VALUE"""),0.0) -> 0 | AC48: =IFERROR(__xludf.DUMMYFUNCTION("""COMPUTED_VALUE"""),0.0) -> 0 | AD48: =IFERROR(__xludf.DUMMYFUNCTION("""COMPUTED_VALUE"""),47.0) -> 47 | AE48: =IFERROR(__xludf.DUMMYFUNCTION("""COMPUTED_VALUE"""),10.0) -> 10 | AF48: =IFERROR(__xludf.DUMMYFUNCTION("""COMPUTED_VALUE"""),3.0) -> 3 | AG48: FEBRERO | AH48: 2024
A49: =IF(B49="","",A48+1) -> 45339 | B49: 324 | C49: 0.51666667 | D49: 0.78611111 | E49: {=IF(B49=0,"",(J49+K49)/60)} -> 0 | F49: =IF(B49=0,"",HOUR(D49-C49)+(MINUTE(D49-C49)/60)) -> 6.4666667 | G49: =IF(B49=0,"",B49/F49) -> 50.103093 | H49: =IF(B49=0,"",B49/(F49-E49)) -> 50.103093 | I49: =IF(B49=0,"",B49/F49/AD49) -> 1.0438144 | J49: 0 | M49: =IFERROR(__xludf.DUMMYFUNCTION("""COMPUTED_VALUE"""),57.0) -> 57 | N49: =IFERROR(__xludf.DUMMYFUNCTION("""COMPUTED_VALUE"""),54.0) -> 54 | O49: =IFERROR(__xludf.DUMMYFUNCTION("""COMPUTED_VALUE"""),0.0) -> 0 | P49: =IFERROR(__xludf.DUMMYFUNCTION("""COMPUTED_VALUE"""),0.0) -> 0 | Q49: =IFERROR(__xludf.DUMMYFUNCTION("""COMPUTED_VALUE"""),1.0) -> 1 | R49: =IFERROR(__xludf.DUMMYFUNCTION("""COMPUTED_VALUE"""),0.0) -> 0 | S49: =IFERROR(__xludf.DUMMYFUNCTION("""COMPUTED_VALUE"""),3.0) -> 3 | T49: =IFERROR(__xludf.DUMMYFUNCTION("""COMPUTED_VALUE"""),0.0) -> 0 | U49: =IFERROR(__xludf.DUMMYFUNCTION("""COMPUTED_VALUE"""),1.0) -> 1 | V49: =IFERROR(__xludf.DUMMYFUNCTION("""COMPUTED_VALUE"""),2.0) -> 2 | W49: =IFERROR(__xludf.DUMMYFUNCTION("""COMPUTED_VALUE"""),0.0) -> 0 | X49: =IFERROR(__xludf.DUMMYFUNCTION("""COMPUTED_VALUE"""),0.0) -> 0 | Y49: =IFERROR(__xludf.DUMMYFUNCTION("""COMPUTED_VALUE"""),0.0) -> 0 | Z49: =IFERROR(__xludf.DUMMYFUNCTION("""COMPUTED_VALUE"""),0.0) -> 0 | AA49: =IFERROR(__xludf.DUMMYFUNCTION("""COMPUTED_VALUE"""),0.0) -> 0 | AB49: =IFERROR(__xludf.DUMMYFUNCTION("""COMPUTED_VALUE"""),0.0) -> 0 | AC49: =IFERROR(__xludf.DUMMYFUNCTION("""COMPUTED_VALUE"""),0.0) -> 0 | AD49: =IFERROR(__xludf.DUMMYFUNCTION("""COMPUTED_VALUE"""),48.0) -> 48 | AE49: =IFERROR(__xludf.DUMMYFUNCTION("""COMPUTED_VALUE"""),9.0) -> 9 | AF49: =IFERROR(__xludf.DUMMYFUNCTION("""COMPUTED_VALUE"""),3.0) -> 3 | AG49: FEBRERO | AH49: 2024
A50: =IF(B50="","",A49+1) -> 45340 | B50: 0 | E50: {=IF(B50=0,"",(J50+K50)/60)} | F50: =IF(B50=0,"",HOUR(D50-C50)+(MINUTE(D50-C50)/60)) | G50: =IF(B50=0,"",B50/F50) | H50: =IF(B50=0,"",B50/(F50-E50)) | I50: =IF(B50=0,"",B50/F50/AD50) | M50: =IFERROR(__xludf.DUMMYFUNCTION("""COMPUTED_VALUE"""),57.0) -> 57 | N50: =IFERROR(__xludf.DUMMYFUNCTION("""COMPUTED_VALUE"""),55.0) -> 55 | O50: =IFERROR(__xludf.DUMMYFUNCTION("""COMPUTED_VALUE"""),0.0) -> 0 | P50: =IFERROR(__xludf.DUMMYFUNCTION("""COMPUTED_VALUE"""),0.0) -> 0 | Q50: =IFERROR(__xludf.DUMMYFUNCTION("""COMPUTED_VALUE"""),0.0) -> 0 | R50: =IFERROR(__xludf.DUMMYFUNCTION("""COMPUTED_VALUE"""),0.0) -> 0 | S50: =IFERROR(__xludf.DUMMYFUNCTION("""COMPUTED_VALUE"""),0.0) -> 0 | T50: =IFERROR(__xludf.DUMMYFUNCTION("""COMPUTED_VALUE"""),0.0) -> 0 | U50: =IFERROR(__xludf.DUMMYFUNCTION("""COMPUTED_VALUE"""),0.0) -> 0 | V50: =IFERROR(__xludf.DUMMYFUNCTION("""COMPUTED_VALUE"""),0.0) -> 0 | ... AD50: =IFERROR(__xludf.DUMMYFUNCTION("""COMPUTED_VALUE"""),0.0) -> 0 | AE50: =IFERROR(__xludf.DUMMYFUNCTION("""COMPUTED_VALUE"""),2.0) -> 2 | AF50: =IFERROR(__xludf.DUMMYFUNCTION("""COMPUTED_VALUE"""),2.0) -> 2 | AG50: FEBRERO | AH50: 2024
A51: =IF(B51="","",A50+1) -> 45341 | B51: 427 | C51: 0.55833333 | D51: 0.89861111 | E51: {=IF(B51=0,"",(J51+K51)/60)} -> 0.25 | F51: =IF(B51=0,"",HOUR(D51-C51)+(MINUTE(D51-C51)/60)) -> 8.1666667 | G51: =IF(B51=0,"",B51/F51) -> 52.285714 | H51: =IF(B51=0,"",B51/(F51-E51)) -> 53.936842 | I51: =IF(B51=0,"",B51/F51/AD51) -> 1.0892857 | J51: 15 | M51: =IFERROR(__xludf.DUMMYFUNCTION("""COMPUTED_VALUE"""),57.0) -> 57 | N51: =IFERROR(__xludf.DUMMYFUNCTION("""COMPUTED_VALUE"""),54.0) -> 54 | O51: =IFERROR(__xludf.DUMMYFUNCTION("""COMPUTED_VALUE"""),0.0) -> 0 | P51: =IFERROR(__xludf.DUMMYFUNCTION("""COMPUTED_VALUE"""),0.0) -> 0 | Q51: =IFERROR(__xludf.DUMMYFUNCTION("""COMPUTED_VALUE"""),3.0) -> 3 | R51: =IFERROR(__xludf.DUMMYFUNCTION("""COMPUTED_VALUE"""),0.0) -> 0 | S51: =IFERROR(__xludf.DUMMYFUNCTION("""COMPUTED_VALUE"""),1.0) -> 1 | T51: =IFERROR(__xludf.DUMMYFUNCTION("""COMPUTED_VALUE"""),0.0) -> 0 | U51: =IFERROR(__xludf.DUMMYFUNCTION("""COMPUTED_VALUE"""),1.0) -> 1 | V51: =IFERROR(__xludf.DUMMYFUNCTION("""COMPUTED_VALUE"""),2.0) -> 2 | W51: =IFERROR(__xludf.DUMMYFUNCTION("""COMPUTED_VALUE"""),0.0) -> 0 | X51: =IFERROR(__xludf.DUMMYFUNCTION("""COMPUTED_VALUE"""),0.0) -> 0 | Y51: =IFERROR(__xludf.DUMMYFUNCTION("""COMPUTED_VALUE"""),0.0) -> 0 | Z51: =IFERROR(__xludf.DUMMYFUNCTION("""COMPUTED_VALUE"""),0.0) -> 0 | AA51: =IFERROR(__xludf.DUMMYFUNCTION("""COMPUTED_VALUE"""),0.0) -> 0 | AB51: =IFERROR(__xludf.DUMMYFUNCTION("""COMPUTED_VALUE"""),0.0) -> 0 | AC51: =IFERROR(__xludf.DUMMYFUNCTION("""COMPUTED_VALUE"""),0.0) -> 0 | AD51: =IFERROR(__xludf.DUMMYFUNCTION("""COMPUTED_VALUE"""),48.0) -> 48 | AE51: =IFERROR(__xludf.DUMMYFUNCTION("""COMPUTED_VALUE"""),9.0) -> 9 | AF51: =IFERROR(__xludf.DUMMYFUNCTION("""COMPUTED_VALUE"""),3.0) -> 3 | AG51: FEBRERO | AH51: 2024
A52: =IF(B52="","",A51+1) -> 45342 | B52: 388 | C52: 0.55833333 | D52: 0.84513889 | E52: {=IF(B52=0,"",(J52+K52)/60)} -> 0.25 | F52: =IF(B52=0,"",HOUR(D52-C52)+(MINUTE(D52-C52)/60)) -> 6.8833333 | G52: =IF(B52=0,"",B52/F52) -> 56.368039 | H52: =IF(B52=0,"",B52/(F52-E52)) -> 58.492462 | I52: =IF(B52=0,"",B52/F52/AD52) -> 1.1503681 | J52: 15 | M52: =IFERROR(__xludf.DUMMYFUNCTION("""COMPUTED_VALUE"""),57.0) -> 57 | N52: =IFERROR(__xludf.DUMMYFUNCTION("""COMPUTED_VALUE"""),55.0) -> 55 | O52: =IFERROR(__xludf.DUMMYFUNCTION("""COMPUTED_VALUE"""),0.0) -> 0 | P52: =IFERROR(__xludf.DUMMYFUNCTION("""COMPUTED_VALUE"""),0.0) -> 0 | Q52: =IFERROR(__xludf.DUMMYFUNCTION("""COMPUTED_VALUE"""),1.0) -> 1 | R52: =IFERROR(__xludf.DUMMYFUNCTION("""COMPUTED_VALUE"""),0.0) -> 0 | S52: =IFERROR(__xludf.DUMMYFUNCTION("""COMPUTED_VALUE"""),2.0) -> 2 | T52: =IFERROR(__xludf.DUMMYFUNCTION("""COMPUTED_VALUE"""),0.0) -> 0 | U52: =IFERROR(__xludf.DUMMYFUNCTION("""COMPUTED_VALUE"""),0.0) -> 0 | V52: =IFERROR(__xludf.DUMMYFUNCTION("""COMPUTED_VALUE"""),2.0) -> 2 | W52: =IFERROR(__xludf.DUMMYFUNCTION("""COMPUTED_VALUE"""),0.0) -> 0 | X52: =IFERROR(__xludf.DUMMYFUNCTION("""COMPUTED_VALUE"""),0.0) -> 0 | Y52: =IFERROR(__xludf.DUMMYFUNCTION("""COMPUTED_VALUE"""),0.0) -> 0 | Z52: =IFERROR(__xludf.DUMMYFUNCTION("""COMPUTED_VALUE"""),0.0) -> 0 | AA52: =IFERROR(__xludf.DUMMYFUNCTION("""COMPUTED_VALUE"""),0.0) -> 0 | AB52: =IFERROR(__xludf.DUMMYFUNCTION("""COMPUTED_VALUE"""),1.0) -> 1 | AC52: =IFERROR(__xludf.DUMMYFUNCTION("""COMPUTED_VALUE"""),0.0) -> 0 | AD52: =IFERROR(__xludf.DUMMYFUNCTION("""COMPUTED_VALUE"""),49.0) -> 49 | AE52: =IFERROR(__xludf.DUMMYFUNCTION("""COMPUTED_VALUE"""),7.0) -> 7 | AF52: =IFERROR(__xludf.DUMMYFUNCTION("""COMPUTED_VALUE"""),2.0) -> 2 | AG52: FEBRERO | AH52: 2024
A53: =IF(B53="","",A52+1) -> 45343 | B53: 514 | C53: 0.55833333 | D53: 0.94444444 | E53: {=IF(B53=0,"",(J53+K53)/60)} -> 0.25 | F53: =IF(B53=0,"",HOUR(D53-C53)+(MINUTE(D53-C53)/60)) -> 9.2666667 | G53: =IF(B53=0,"",B53/F53) -> 55.467626 | H53: =IF(B53=0,"",B53/(F53-E53)) -> 57.005545 | I53: =IF(B53=0,"",B53/F53/AD53) -> 1.1319924 | J53: 15 | M53: =IFERROR(__xludf.DUMMYFUNCTION("""COMPUTED_VALUE"""),57.0) -> 57 | N53: =IFERROR(__xludf.DUMMYFUNCTION("""COMPUTED_VALUE"""),55.0) -> 55 | O53: =IFERROR(__xludf.DUMMYFUNCTION("""COMPUTED_VALUE"""),0.0) -> 0 | P53: =IFERROR(__xludf.DUMMYFUNCTION("""COMPUTED_VALUE"""),0.0) -> 0 | Q53: =IFERROR(__xludf.DUMMYFUNCTION("""COMPUTED_VALUE"""),2.0) -> 2 | R53: =IFERROR(__xludf.DUMMYFUNCTION("""COMPUTED_VALUE"""),0.0) -> 0 | S53: =IFERROR(__xludf.DUMMYFUNCTION("""COMPUTED_VALUE"""),2.0) -> 2 | T53: =IFERROR(__xludf.DUMMYFUNCTION("""COMPUTED_VALUE"""),0.0) -> 0 | U53: =IFERROR(__xludf.DUMMYFUNCTION("""COMPUTED_VALUE"""),0.0) -> 0 | V53: =IFERROR(__xludf.DUMMYFUNCTION("""COMPUTED_VALUE"""),2.0) -> 2 | W53: =IFERROR(__xludf.DUMMYFUNCTION("""COMPUTED_VALUE"""),0.0) -> 0 | X53: =IFERROR(__xludf.DUMMYFUNCTION("""COMPUTED_VALUE"""),0.0) -> 0 | Y53: =IFERROR(__xludf.DUMMYFUNCTION("""COMPUTED_VALUE"""),0.0) -> 0 | Z53: =IFERROR(__xludf.DUMMYFUNCTION("""COMPUTED_VALUE"""),0.0) -> 0 | AA53: =IFERROR(__xludf.DUMMYFUNCTION("""COMPUTED_VALUE"""),0.0) -> 0 | AB53: =IFERROR(__xludf.DUMMYFUNCTION("""COMPUTED_VALUE"""),0.0) -> 0 | AC53: =IFERROR(__xludf.DUMMYFUNCTION("""COMPUTED_VALUE"""),0.0) -> 0 | AD53: =IFERROR(__xludf.DUMMYFUNCTION("""COMPUTED_VALUE"""),49.0) -> 49 | AE53: =IFERROR(__xludf.DUMMYFUNCTION("""COMPUTED_VALUE"""),8.0) -> 8 | AF53: =IFERROR(__xludf.DUMMYFUNCTION("""COMPUTED_VALUE"""),2.0) -> 2 | AG53: FEBRERO | AH53: 2024
A54: =IF(B54="","",A53+1) -> 45344 | B54: 438 | C54: 0.55833333 | D54: 0.92222222 | E54: {=IF(B54=0,"",(J54+K54)/60)} -> 0 | F54: =IF(B54=0,"",HOUR(D54-C54)+(MINUTE(D54-C54)/60)) -> 8.7333333 | G54: =IF(B54=0,"",B54/F54) -> 50.152672 | H54: =IF(B54=0,"",B54/(F54-E54)) -> 50.152672 | I54: =IF(B54=0,"",B54/F54/AD54) -> 1.0448473 | J54: 0 | M54: =IFERROR(__xludf.DUMMYFUNCTION("""COMPUTED_VALUE"""),57.0) -> 57 | N54: =IFERROR(__xludf.DUMMYFUNCTION("""COMPUTED_VALUE"""),55.0) -> 55 | O54: =IFERROR(__xludf.DUMMYFUNCTION("""COMPUTED_VALUE"""),1.0) -> 1 | P54: =IFERROR(__xludf.DUMMYFUNCTION("""COMPUTED_VALUE"""),0.0) -> 0 | Q54: =IFERROR(__xludf.DUMMYFUNCTION("""COMPUTED_VALUE"""),2.0) -> 2 | R54: =IFERROR(__xludf.DUMMYFUNCTION("""COMPUTED_VALUE"""),0.0) -> 0 | S54: =IFERROR(__xludf.DUMMYFUNCTION("""COMPUTED_VALUE"""),2.0) -> 2 | T54: =IFERROR(__xludf.DUMMYFUNCTION("""COMPUTED_VALUE"""),0.0) -> 0 | U54: =IFERROR(__xludf.DUMMYFUNCTION("""COMPUTED_VALUE"""),0.0) -> 0 | V54: =IFERROR(__xludf.DUMMYFUNCTION("""COMPUTED_VALUE"""),2.0) -> 2 | W54: =IFERROR(__xludf.DUMMYFUNCTION("""COMPUTED_VALUE"""),0.0) -> 0 | X54: =IFERROR(__xludf.DUMMYFUNCTION("""COMPUTED_VALUE"""),0.0) -> 0 | Y54: =IFERROR(__xludf.DUMMYFUNCTION("""COMPUTED_VALUE"""),0.0) -> 0 | Z54: =IFERROR(__xludf.DUMMYFUNCTION("""COMPUTED_VALUE"""),0.0) -> 0 | AA54: =IFERROR(__xludf.DUMMYFUNCTION("""COMPUTED_VALUE"""),0.0) -> 0 | AB54: =IFERROR(__xludf.DUMMYFUNCTION("""COMPUTED_VALUE"""),0.0) -> 0 | AC54: =IFERROR(__xludf.DUMMYFUNCTION("""COMPUTED_VALUE"""),0.0) -> 0 | AD54: =IFERROR(__xludf.DUMMYFUNCTION("""COMPUTED_VALUE"""),48.0) -> 48 | AE54: =IFERROR(__xludf.DUMMYFUNCTION("""COMPUTED_VALUE"""),9.0) -> 9 | AF54: =IFERROR(__xludf.DUMMYFUNCTION("""COMPUTED_VALUE"""),2.0) -> 2 | AG54: FEBRERO | AH54: 2024
A55: =IF(B55="","",A54+1) -> 45345 | B55: 374 | C55: 0.55833333 | D55: 0.83888889 | E55: {=IF(B55=0,"",(J55+K55)/60)} -> 0.25 | F55: =IF(B55=0,"",HOUR(D55-C55)+(MINUTE(D55-C55)/60)) -> 6.7333333 | G55: =IF(B55=0,"",B55/F55) -> 55.544554 | H55: =IF(B55=0,"",B55/(F55-E55)) -> 57.686375 | I55: =IF(B55=0,"",B55/F55/AD55) -> 1.181799 | J55: 15 | M55: =IFERROR(__xludf.DUMMYFUNCTION("""COMPUTED_VALUE"""),57.0) -> 57 | N55: =IFERROR(__xludf.DUMMYFUNCTION("""COMPUTED_VALUE"""),54.0) -> 54 | O55: =IFERROR(__xludf.DUMMYFUNCTION("""COMPUTED_VALUE"""),1.0) -> 1 | P55: =IFERROR(__xludf.DUMMYFUNCTION("""COMPUTED_VALUE"""),1.0) -> 1 | Q55: =IFERROR(__xludf.DUMMYFUNCTION("""COMPUTED_VALUE"""),1.0) -> 1 | R55: =IFERROR(__xludf.DUMMYFUNCTION("""COMPUTED_VALUE"""),1.0) -> 1 | S55: =IFERROR(__xludf.DUMMYFUNCTION("""COMPUTED_VALUE"""),2.0) -> 2 | T55: =IFERROR(__xludf.DUMMYFUNCTION("""COMPUTED_VALUE"""),0.0) -> 0 | U55: =IFERROR(__xludf.DUMMYFUNCTION("""COMPUTED_VALUE"""),0.0) -> 0 | V55: =IFERROR(__xludf.DUMMYFUNCTION("""COMPUTED_VALUE"""),2.0) -> 2 | W55: =IFERROR(__xludf.DUMMYFUNCTION("""COMPUTED_VALUE"""),0.0) -> 0 | X55: =IFERROR(__xludf.DUMMYFUNCTION("""COMPUTED_VALUE"""),0.0) -> 0 | Y55: =IFERROR(__xludf.DUMMYFUNCTION("""COMPUTED_VALUE"""),0.0) -> 0 | Z55: =IFERROR(__xludf.DUMMYFUNCTION("""COMPUTED_VALUE"""),0.0) -> 0 | AA55: =IFERROR(__xludf.DUMMYFUNCTION("""COMPUTED_VALUE"""),0.0) -> 0 | AB55: =IFERROR(__xludf.DUMMYFUNCTION("""COMPUTED_VALUE"""),0.0) -> 0 | AC55: =IFERROR(__xludf.DUMMYFUNCTION("""COMPUTED_VALUE"""),0.0) -> 0 | AD55: =IFERROR(__xludf.DUMMYFUNCTION("""COMPUTED_VALUE"""),47.0) -> 47 | AE55: =IFERROR(__xludf.DUMMYFUNCTION("""COMPUTED_VALUE"""),9.0) -> 9 | AF55: =IFERROR(__xludf.DUMMYFUNCTION("""COMPUTED_VALUE"""),3.0) -> 3 | AG55: FEBRERO | AH55: 2024
A56: =IF(B56="","",A55+1) -> 45346 | B56: 424 | C56: 0.51666667 | D56: 0.84027778 | E56: {=IF(B56=0,"",(J56+K56)/60)} -> 0.25 | F56: =IF(B56=0,"",HOUR(D56-C56)+(MINUTE(D56-C56)/60)) -> 7.7666667 | G56: =IF(B56=0,"",B56/F56) -> 54.592275 | H56: =IF(B56=0,"",B56/(F56-E56)) -> 56.407982 | I56: =IF(B56=0,"",B56/F56/AD56) -> 1.0918455 | J56: 15 | M56: =IFERROR(__xludf.DUMMYFUNCTION("""COMPUTED_VALUE"""),57.0) -> 57 | N56: =IFERROR(__xludf.DUMMYFUNCTION("""COMPUTED_VALUE"""),54.0) -> 54 | O56: =IFERROR(__xludf.DUMMYFUNCTION("""COMPUTED_VALUE"""),0.0) -> 0 | P56: =IFERROR(__xludf.DUMMYFUNCTION("""COMPUTED_VALUE"""),0.0) -> 0 | Q56: =IFERROR(__xludf.DUMMYFUNCTION("""COMPUTED_VALUE"""),1.0) -> 1 | R56: =IFERROR(__xludf.DUMMYFUNCTION("""COMPUTED_VALUE"""),0.0) -> 0 | S56: =IFERROR(__xludf.DUMMYFUNCTION("""COMPUTED_VALUE"""),1.0) -> 1 | T56: =IFERROR(__xludf.DUMMYFUNCTION("""COMPUTED_VALUE"""),0.0) -> 0 | U56: =IFERROR(__xludf.DUMMYFUNCTION("""COMPUTED_VALUE"""),1.0) -> 1 | V56: =IFERROR(__xludf.DUMMYFUNCTION("""COMPUTED_VALUE"""),2.0) -> 2 | W56: =IFERROR(__xludf.DUMMYFUNCTION("""COMPUTED_VALUE"""),0.0) -> 0 | X56: =IFERROR(__xludf.DUMMYFUNCTION("""COMPUTED_VALUE"""),0.0) -> 0 | Y56: =IFERROR(__xludf.DUMMYFUNCTION("""COMPUTED_VALUE"""),0.0) -> 0 | Z56: =IFERROR(__xludf.DUMMYFUNCTION("""COMPUTED_VALUE"""),0.0) -> 0 | AA56: =IFERROR(__xludf.DUMMYFUNCTION("""COMPUTED_VALUE"""),0.0) -> 0 | AB56: =IFERROR(__xludf.DUMMYFUNCTION("""COMPUTED_VALUE"""),0.0) -> 0 | AC56: =IFERROR(__xludf.DUMMYFUNCTION("""COMPUTED_VALUE"""),0.0) -> 0 | AD56: =IFERROR(__xludf.DUMMYFUNCTION("""COMPUTED_VALUE"""),50.0) -> 50 | AE56: =IFERROR(__xludf.DUMMYFUNCTION("""COMPUTED_VALUE"""),7.0) -> 7 | AF56: =IFERROR(__xludf.DUMMYFUNCTION("""COMPUTED_VALUE"""),3.0) -> 3 | AG56: FEBRERO | AH56: 2024
A57: =IF(B57="","",A56+1) -> 45347 | B57: 0 | E57: {=IF(B57=0,"",(J57+K57)/60)} | F57: =IF(B57=0,"",HOUR(D57-C57)+(MINUTE(D57-C57)/60)) | G57: =IF(B57=0,"",B57/F57) | H57: =IF(B57=0,"",B57/(F57-E57)) | I57: =IF(B57=0,"",B57/F57/AD57) | M57: =IFERROR(__xludf.DUMMYFUNCTION("""COMPUTED_VALUE"""),57.0) -> 57 | N57: =IFERROR(__xludf.DUMMYFUNCTION("""COMPUTED_VALUE"""),54.0) -> 54 | O57: =IFERROR(__xludf.DUMMYFUNCTION("""COMPUTED_VALUE"""),0.0) -> 0 | P57: =IFERROR(__xludf.DUMMYFUNCTION("""COMPUTED_VALUE"""),0.0) -> 0 | Q57: =IFERROR(__xludf.DUMMYFUNCTION("""COMPUTED_VALUE"""),0.0) -> 0 | R57: =IFERROR(__xludf.DUMMYFUNCTION("""COMPUTED_VALUE"""),0.0) -> 0 | S57: =IFERROR(__xludf.DUMMYFUNCTION("""COMPUTED_VALUE"""),0.0) -> 0 | T57: =IFERROR(__xludf.DUMMYFUNCTION("""COMPUTED_VALUE"""),0.0) -> 0 | U57: =IFERROR(__xludf.DUMMYFUNCTION("""COMPUTED_VALUE"""),1.0) -> 1 | V57: =IFERROR(__xludf.DUMMYFUNCTION("""COMPUTED_VALUE"""),0.0) -> 0 | W57: =IFERROR(__xludf.DUMMYFUNCTION("""COMPUTED_VALUE"""),0.0) -> 0 | X57: =IFERROR(__xludf.DUMMYFUNCTION("""COMPUTED_VALUE"""),0.0) -> 0 | Y57: =IFERROR(__xludf.DUMMYFUNCTION("""COMPUTED_VALUE"""),0.0) -> 0 | Z57: =IFERROR(__xludf.DUMMYFUNCTION("""COMPUTED_VALUE"""),0.0) -> 0 | AA57: =IFERROR(__xludf.DUMMYFUNCTION("""COMPUTED_VALUE"""),0.0) -> 0 | AB57: =IFERROR(__xludf.DUMMYFUNCTION("""COMPUTED_VALUE"""),0.0) -> 0 | AC57: =IFERROR(__xludf.DUMMYFUNCTION("""COMPUTED_VALUE"""),0.0) -> 0 | AD57: =IFERROR(__xludf.DUMMYFUNCTION("""COMPUTED_VALUE"""),0.0) -> 0 | AE57: =IFERROR(__xludf.DUMMYFUNCTION("""COMPUTED_VALUE"""),3.0) -> 3 | AF57: =IFERROR(__xludf.DUMMYFUNCTION("""COMPUTED_VALUE"""),3.0) -> 3 | AG57: FEBRERO | AH57: 2024
A58: =IF(B58="","",A57+1) -> 45348 | B58: 394 | C58: 0.55833333 | D58: 0.85416667 | E58: {=IF(B58=0,"",(J58+K58)/60)} -> 0.25 | F58: =IF(B58=0,"",HOUR(D58-C58)+(MINUTE(D58-C58)/60)) -> 7.1 | G58: =IF(B58=0,"",B58/F58) -> 55.492958 | H58: =IF(B58=0,"",B58/(F58-E58)) -> 57.518248 | I58: =IF(B58=0,"",B58/F58/AD58) -> 1.1098592 | J58: 15 | M58: =IFERROR(__xludf.DUMMYFUNCTION("""COMPUTED_VALUE"""),57.0) -> 57 | N58: =IFERROR(__xludf.DUMMYFUNCTION("""COMPUTED_VALUE"""),56.0) -> 56 | O58: =IFERROR(__xludf.DUMMYFUNCTION("""COMPUTED_VALUE"""),0.0) -> 0 | P58: =IFERROR(__xludf.DUMMYFUNCTION("""COMPUTED_VALUE"""),0.0) -> 0 | Q58: =IFERROR(__xludf.DUMMYFUNCTION("""COMPUTED_VALUE"""),0.0) -> 0 | R58: =IFERROR(__xludf.DUMMYFUNCTION("""COMPUTED_VALUE"""),0.0) -> 0 | S58: =IFERROR(__xludf.DUMMYFUNCTION("""COMPUTED_VALUE"""),2.0) -> 2 | T58: =IFERROR(__xludf.DUMMYFUNCTION("""COMPUTED_VALUE"""),0.0) -> 0 | U58: =IFERROR(__xludf.DUMMYFUNCTION("""COMPUTED_VALUE"""),1.0) -> 1 | V58: =IFERROR(__xludf.DUMMYFUNCTION("""COMPUTED_VALUE"""),2.0) -> 2 | W58: =IFERROR(__xludf.DUMMYFUNCTION("""COMPUTED_VALUE"""),0.0) -> 0 | X58: =IFERROR(__xludf.DUMMYFUNCTION("""COMPUTED_VALUE"""),0.0) -> 0 | Y58: =IFERROR(__xludf.DUMMYFUNCTION("""COMPUTED_VALUE"""),0.0) -> 0 | Z58: =IFERROR(__xludf.DUMMYFUNCTION("""COMPUTED_VALUE"""),0.0) -> 0 | AA58: =IFERROR(__xludf.DUMMYFUNCTION("""COMPUTED_VALUE"""),0.0) -> 0 | AB58: =IFERROR(__xludf.DUMMYFUNCTION("""COMPUTED_VALUE"""),0.0) -> 0 | AC58: =IFERROR(__xludf.DUMMYFUNCTION("""COMPUTED_VALUE"""),0.0) -> 0 | AD58: =IFERROR(__xludf.DUMMYFUNCTION("""COMPUTED_VALUE"""),50.0) -> 50 | AE58: =IFERROR(__xludf.DUMMYFUNCTION("""COMPUTED_VALUE"""),5.0) -> 5 | AF58: =IFERROR(__xludf.DUMMYFUNCTION("""COMPUTED_VALUE"""),1.0) -> 1 | AG58: FEBRERO | AH58: 2024
A59: =IF(B59="","",A58+1) -> 45349 | B59: 461 | C59: 0.55833333 | D59: 0.90625 | E59: {=IF(B59=0,"",(J59+K59)/60)} -> 0.25 | F59: =IF(B59=0,"",HOUR(D59-C59)+(MINUTE(D59-C59)/60)) -> 8.35 | G59: =IF(B59=0,"",B59/F59) -> 55.209581 | H59: =IF(B59=0,"",B59/(F59-E59)) -> 56.91358 | I59: =IF(B59=0,"",B59/F59/AD59) -> 1.0617227 | J59: 15 | M59: =IFERROR(__xludf.DUMMYFUNCTION("""COMPUTED_VALUE"""),57.0) -> 57 | N59: =IFERROR(__xludf.DUMMYFUNCTION("""COMPUTED_VALUE"""),56.0) -> 56 | O59: =IFERROR(__xludf.DUMMYFUNCTION("""COMPUTED_VALUE"""),0.0) -> 0 | P59: =IFERROR(__xludf.DUMMYFUNCTION("""COMPUTED_VALUE"""),0.0) -> 0 | Q59: =IFERROR(__xludf.DUMMYFUNCTION("""COMPUTED_VALUE"""),0.0) -> 0 | R59: =IFERROR(__xludf.DUMMYFUNCTION("""COMPUTED_VALUE"""),0.0) -> 0 | S59: =IFERROR(__xludf.DUMMYFUNCTION("""COMPUTED_VALUE"""),2.0) -> 2 | T59: =IFERROR(__xludf.DUMMYFUNCTION("""COMPUTED_VALUE"""),0.0) -> 0 | U59: =IFERROR(__xludf.DUMMYFUNCTION("""COMPUTED_VALUE"""),1.0) -> 1 | V59: =IFERROR(__xludf.DUMMYFUNCTION("""COMPUTED_VALUE"""),0.0) -> 0 | W59: =IFERROR(__xludf.DUMMYFUNCTION("""COMPUTED_VALUE"""),0.0) -> 0 | X59: =IFERROR(__xludf.DUMMYFUNCTION("""COMPUTED_VALUE"""),0.0) -> 0 | Y59: =IFERROR(__xludf.DUMMYFUNCTION("""COMPUTED_VALUE"""),0.0) -> 0 | Z59: =IFERROR(__xludf.DUMMYFUNCTION("""COMPUTED_VALUE"""),0.0) -> 0 | AA59: =IFERROR(__xludf.DUMMYFUNCTION("""COMPUTED_VALUE"""),2.0) -> 2 | AB59: =IFERROR(__xludf.DUMMYFUNCTION("""COMPUTED_VALUE"""),0.0) -> 0 | AC59: =IFERROR(__xludf.DUMMYFUNCTION("""COMPUTED_VALUE"""),0.0) -> 0 | AD59: =IFERROR(__xludf.DUMMYFUNCTION("""COMPUTED_VALUE"""),52.0) -> 52 | AE59: =IFERROR(__xludf.DUMMYFUNCTION("""COMPUTED_VALUE"""),5.0) -> 5 | AF59: =IFERROR(__xludf.DUMMYFUNCTION("""COMPUTED_VALUE"""),1.0) -> 1 | AG59: FEBRERO | AH59: 2024
A60: =IF(B60="","",A59+1) -> 45350 | B60: 493 | C60: 0.55833333 | D60: 0.92916667 | E60: {=IF(B60=0,"",(J60+K60)/60)} -> 0.25 | F60: =IF(B60=0,"",HOUR(D60-C60)+(MINUTE(D60-C60)/60)) -> 8.9 | G60: =IF(B60=0,"",B60/F60) -> 55.393258 | H60: =IF(B60=0,"",B60/(F60-E60)) -> 56.99422 | I60: =IF(B60=0,"",B60/F60/AD60) -> 1.1078652 | J60: 15 | M60: =IFERROR(__xludf.DUMMYFUNCTION("""COMPUTED_VALUE"""),57.0) -> 57 | N60: =IFERROR(__xludf.DUMMYFUNCTION("""COMPUTED_VALUE"""),56.0) -> 56 | O60: =IFERROR(__xludf.DUMMYFUNCTION("""COMPUTED_VALUE"""),0.0) -> 0 | P60: =IFERROR(__xludf.DUMMYFUNCTION("""COMPUTED_VALUE"""),0.0) -> 0 | Q60: =IFERROR(__xludf.DUMMYFUNCTION("""COMPUTED_VALUE"""),0.0) -> 0 | R60: =IFERROR(__xludf.DUMMYFUNCTION("""COMPUTED_VALUE"""),0.0) -> 0 | S60: =IFERROR(__xludf.DUMMYFUNCTION("""COMPUTED_VALUE"""),2.0) -> 2 | T60: =IFERROR(__xludf.DUMMYFUNCTION("""COMPUTED_VALUE"""),0.0) -> 0 | U60: =IFERROR(__xludf.DUMMYFUNCTION("""COMPUTED_VALUE"""),1.0) -> 1 | V60: =IFERROR(__xludf.DUMMYFUNCTION("""COMPUTED_VALUE"""),3.0) -> 3 | W60: =IFERROR(__xludf.DUMMYFUNCTION("""COMPUTED_VALUE"""),1.0) -> 1 | X60: =IFERROR(__xludf.DUMMYFUNCTION("""COMPUTED_VALUE"""),0.0) -> 0 | Y60: =IFERROR(__xludf.DUMMYFUNCTION("""COMPUTED_VALUE"""),0.0) -> 0 | Z60: =IFERROR(__xludf.DUMMYFUNCTION("""COMPUTED_VALUE"""),0.0) -> 0 | AA60: =IFERROR(__xludf.DUMMYFUNCTION("""COMPUTED_VALUE"""),0.0) -> 0 | AB60: =IFERROR(__xludf.DUMMYFUNCTION("""COMPUTED_VALUE"""),0.0) -> 0 | AC60: =IFERROR(__xludf.DUMMYFUNCTION("""COMPUTED_VALUE"""),0.0) -> 0 | AD60: =IFERROR(__xludf.DUMMYFUNCTION("""COMPUTED_VALUE"""),50.0) -> 50 | AE60: =IFERROR(__xludf.DUMMYFUNCTION("""COMPUTED_VALUE"""),7.0) -> 7 | AF60: =IFERROR(__xludf.DUMMYFUNCTION("""COMPUTED_VALUE"""),1.0) -> 1 | AG60: FEBRERO | AH60: 2024
A61: =IF(B61="","",A60+1) -> 45351 | B61: 447 | C61: 0.55833333 | D61: 0.91666667 | E61: {=IF(B61=0,"",(J61+K61)/60)} -> 0.25 | F61: =IF(B61=0,"",HOUR(D61-C61)+(MINUTE(D61-C61)/60)) -> 8.6 | G61: =IF(B61=0,"",B61/F61) -> 51.976744 | H61: =IF(B61=0,"",B61/(F61-E61)) -> 53.532934 | I61: =IF(B61=0,"",B61/F61/AD61) -> 1.0607499 | J61: 15 | M61: =IFERROR(__xludf.DUMMYFUNCTION("""COMPUTED_VALUE"""),57.0) -> 57 | N61: =IFERROR(__xludf.DUMMYFUNCTION("""COMPUTED_VALUE"""),56.0) -> 56 | O61: =IFERROR(__xludf.DUMMYFUNCTION("""COMPUTED_VALUE"""),1.0) -> 1 | P61: =IFERROR(__xludf.DUMMYFUNCTION("""COMPUTED_VALUE"""),0.0) -> 0 | Q61: =IFERROR(__xludf.DUMMYFUNCTION("""COMPUTED_VALUE"""),1.0) -> 1 | R61: =IFERROR(__xludf.DUMMYFUNCTION("""COMPUTED_VALUE"""),0.0) -> 0 | S61: =IFERROR(__xludf.DUMMYFUNCTION("""COMPUTED_VALUE"""),2.0) -> 2 | T61: =IFERROR(__xludf.DUMMYFUNCTION("""COMPUTED_VALUE"""),0.0) -> 0 | U61: =IFERROR(__xludf.DUMMYFUNCTION("""COMPUTED_VALUE"""),1.0) -> 1 | V61: =IFERROR(__xludf.DUMMYFUNCTION("""COMPUTED_VALUE"""),3.0) -> 3 | W61: =IFERROR(__xludf.DUMMYFUNCTION("""COMPUTED_VALUE"""),0.0) -> 0 | X61: =IFERROR(__xludf.DUMMYFUNCTION("""COMPUTED_VALUE"""),0.0) -> 0 | Y61: =IFERROR(__xludf.DUMMYFUNCTION("""COMPUTED_VALUE"""),0.0) -> 0 | Z61: =IFERROR(__xludf.DUMMYFUNCTION("""COMPUTED_VALUE"""),0.0) -> 0 | AA61: =IFERROR(__xludf.DUMMYFUNCTION("""COMPUTED_VALUE"""),0.0) -> 0 | AB61: =IFERROR(__xludf.DUMMYFUNCTION("""COMPUTED_VALUE"""),0.0) -> 0 | AC61: =IFERROR(__xludf.DUMMYFUNCTION("""COMPUTED_VALUE"""),0.0) -> 0 | AD61: =IFERROR(__xludf.DUMMYFUNCTION("""COMPUTED_VALUE"""),49.0) -> 49 | AE61: =IFERROR(__xludf.DUMMYFUNCTION("""COMPUTED_VALUE"""),8.0) -> 8 | AF61: =IFERROR(__xludf.DUMMYFUNCTION("""COMPUTED_VALUE"""),1.0) -> 1 | AG61: FEBRERO | AH61: 2024
A62: =IF(B62="","",A61+1) -> 45352 | B62: 463 | C62: 0.55833333 | D62: 0.91875 | E62: {=IF(B62=0,"",(J62+K62)/60)} -> 0.25 | F62: =IF(B62=0,"",HOUR(D62-C62)+(MINUTE(D62-C62)/60)) -> 8.65 | G62: =IF(B62=0,"",B62/F62) -> 53.526012 | H62: =IF(B62=0,"",B62/(F62-E62)) -> 55.119048 | I62: =IF(B62=0,"",B62/F62/AD62) -> 1.0495296 | J62: 15 | M62: =IFERROR(__xludf.DUMMYFUNCTION("TRANSPOSE(IMPORTRANGE(""https://docs.google.com/spreadsheets/d/1CNeKSHTeNNJnfn5EymHwGg5Mkuk6EcepW7_9QkJxalc/edit#gid=1218471306"",""MARZO 2024!F2:AJ21""))"),57.0) -> 57 | N62: =IFERROR(__xludf.DUMMYFUNCTION("""COMPUTED_VALUE"""),56.0) -> 56 | O62: =IFERROR(__xludf.DUMMYFUNCTION("""COMPUTED_VALUE"""),0.0) -> 0 | P62: =IFERROR(__xludf.DUMMYFUNCTION("""COMPUTED_VALUE"""),0.0) -> 0 | Q62: =IFERROR(__xludf.DUMMYFUNCTION("""COMPUTED_VALUE"""),1.0) -> 1 | R62: =IFERROR(__xludf.DUMMYFUNCTION("""COMPUTED_VALUE"""),0.0) -> 0 | S62: =IFERROR(__xludf.DUMMYFUNCTION("""COMPUTED_VALUE"""),2.0) -> 2 | T62: =IFERROR(__xludf.DUMMYFUNCTION("""COMPUTED_VALUE"""),0.0) -> 0 | U62: =IFERROR(__xludf.DUMMYFUNCTION("""COMPUTED_VALUE"""),1.0) -> 1 | V62: =IFERROR(__xludf.DUMMYFUNCTION("""COMPUTED_VALUE"""),3.0) -> 3 | W62: =IFERROR(__xludf.DUMMYFUNCTION("""COMPUTED_VALUE"""),0.0) -> 0 | X62: =IFERROR(__xludf.DUMMYFUNCTION("""COMPUTED_VALUE"""),0.0) -> 0 | Y62: =IFERROR(__xludf.DUMMYFUNCTION("""COMPUTED_VALUE"""),0.0) -> 0 | Z62: =IFERROR(__xludf.DUMMYFUNCTION("""COMPUTED_VALUE"""),0.0) -> 0 | AA62: =IFERROR(__xludf.DUMMYFUNCTION("""COMPUTED_VALUE"""),0.0) -> 0 | AB62: =IFERROR(__xludf.DUMMYFUNCTION("""COMPUTED_VALUE"""),0.0) -> 0 | AC62: =IFERROR(__xludf.DUMMYFUNCTION("""COMPUTED_VALUE"""),0.0) -> 0 | AD62: =IFERROR(__xludf.DUMMYFUNCTION("""COMPUTED_VALUE"""),51.0) -> 51 | AE62: =IFERROR(__xludf.DUMMYFUNCTION("""COMPUTED_VALUE"""),7.0) -> 7 | AF62: =IFERROR(__xludf.DUMMYFUNCTION("""COMPUTED_VALUE"""),1.0) -> 1 | AG62: MARZO | AH62: 2024
A63: =IF(B63="","",A62+1) -> 45353 | B63: 316 | C63: 0.51666667 | D63: 0.75 | E63: {=IF(B63=0,"",(J63+K63)/60)} -> 0.25 | F63: =IF(B63=0,"",HOUR(D63-C63)+(MINUTE(D63-C63)/60)) -> 5.6 | G63: =IF(B63=0,"",B63/F63) -> 56.428571 | H63: =IF(B63=0,"",B63/(F63-E63)) -> 59.065421 | I63: =IF(B63=0,"",B63/F63/AD63) -> 1.1755952 | J63: 15 | M63: =IFERROR(__xludf.DUMMYFUNCTION("""COMPUTED_VALUE"""),57.0) -> 57 | N63: =IFERROR(__xludf.DUMMYFUNCTION("""COMPUTED_VALUE"""),56.0) -> 56 | O63: =IFERROR(__xludf.DUMMYFUNCTION("""COMPUTED_VALUE"""),0.0) -> 0 | P63: =IFERROR(__xludf.DUMMYFUNCTION("""COMPUTED_VALUE"""),0.0) -> 0 | Q63: =IFERROR(__xludf.DUMMYFUNCTION("""COMPUTED_VALUE"""),3.0) -> 3 | R63: =IFERROR(__xludf.DUMMYFUNCTION("""COMPUTED_VALUE"""),0.0) -> 0 | S63: =IFERROR(__xludf.DUMMYFUNCTION("""COMPUTED_VALUE"""),2.0) -> 2 | T63: =IFERROR(__xludf.DUMMYFUNCTION("""COMPUTED_VALUE"""),0.0) -> 0 | U63: =IFERROR(__xludf.DUMMYFUNCTION("""COMPUTED_VALUE"""),1.0) -> 1 | V63: =IFERROR(__xludf.DUMMYFUNCTION("""COMPUTED_VALUE"""),4.0) -> 4 | W63: =IFERROR(__xludf.DUMMYFUNCTION("""COMPUTED_VALUE"""),0.0) -> 0 | X63: =IFERROR(__xludf.DUMMYFUNCTION("""COMPUTED_VALUE"""),0.0) -> 0 | Y63: =IFERROR(__xludf.DUMMYFUNCTION("""COMPUTED_VALUE"""),0.0) -> 0 | Z63: =IFERROR(__xludf.DUMMYFUNCTION("""COMPUTED_VALUE"""),0.0) -> 0 | AA63: =IFERROR(__xludf.DUMMYFUNCTION("""COMPUTED_VALUE"""),0.0) -> 0 | AB63: =IFERROR(__xludf.DUMMYFUNCTION("""COMPUTED_VALUE"""),0.0) -> 0 | AC63: =IFERROR(__xludf.DUMMYFUNCTION("""COMPUTED_VALUE"""),0.0) -> 0 | AD63: =IFERROR(__xludf.DUMMYFUNCTION("""COMPUTED_VALUE"""),48.0) -> 48 | AE63: =IFERROR(__xludf.DUMMYFUNCTION("""COMPUTED_VALUE"""),10.0) -> 10 | AF63: =IFERROR(__xludf.DUMMYFUNCTION("""COMPUTED_VALUE"""),1.0) -> 1 | AG63: MARZO | AH63: 2024
A64: =IF(B64="","",A63+1) -> 45354 | B64: 0 | E64: {=IF(B64=0,"",(J64+K64)/60)} | F64: =IF(B64=0,"",HOUR(D64-C64)+(MINUTE(D64-C64)/60)) | G64: =IF(B64=0,"",B64/F64) | H64: =IF(B64=0,"",B64/(F64-E64)) | I64: =IF(B64=0,"",B64/F64/AD64) | M64: =IFERROR(__xludf.DUMMYFUNCTION("""COMPUTED_VALUE"""),57.0) -> 57 | N64: =IFERROR(__xludf.DUMMYFUNCTION("""COMPUTED_VALUE"""),57.0) -> 57 | O64: =IFERROR(__xludf.DUMMYFUNCTION("""COMPUTED_VALUE"""),0.0) -> 0 | P64: =IFERROR(__xludf.DUMMYFUNCTION("""COMPUTED_VALUE"""),0.0) -> 0 | Q64: =IFERROR(__xludf.DUMMYFUNCTION("""COMPUTED_VALUE"""),0.0) -> 0 | R64: =IFERROR(__xludf.DUMMYFUNCTION("""COMPUTED_VALUE"""),0.0) -> 0 | S64: =IFERROR(__xludf.DUMMYFUNCTION("""COMPUTED_VALUE"""),0.0) -> 0 | T64: =IFERROR(__xludf.DUMMYFUNCTION("""COMPUTED_VALUE"""),0.0) -> 0 | U64: =IFERROR(__xludf.DUMMYFUNCTION("""COMPUTED_VALUE"""),0.0) -> 0 | V64: =IFERROR(__xludf.DUMMYFUNCTION("""COMPUTED_VALUE"""),0.0) -> 0 | ... AF64: =IFERROR(__xludf.DUMMYFUNCTION("""COMPUTED_VALUE"""),0.0) -> 0 | AG64: MARZO | AH64: 2024
